[{"prefectureJisCode":"28","cityJisCode":"28201","townNameKana":"ｱｲﾉ","townName":"相野","zipCode":"6712232"},{"prefectureJisCode":"28","cityJisCode":"28201","townNameKana":"ｱｵﾔﾏ","townName":"青山","zipCode":"6712222"},{"prefectureJisCode":"28","cityJisCode":"28201","townNameKana":"ｱｵﾔﾏｷﾀ","townName":"青山北","zipCode":"6712221"},{"prefectureJisCode":"28","cityJisCode":"28201","townNameKana":"ｱｵﾔﾏﾆｼ","townName":"青山西","zipCode":"6712224"},{"prefectureJisCode":"28","cityJisCode":"28201","townNameKana":"ｱｵﾔﾏﾐﾅﾐ","townName":"青山南","zipCode":"6712223"},{"prefectureJisCode":"28","cityJisCode":"28201","townNameKana":"ｱｻﾋﾏﾁ","townName":"朝日町","zipCode":"6700934"},{"prefectureJisCode":"28","cityJisCode":"28201","townNameKana":"ｱﾎﾞ","townName":"阿保","zipCode":"6700944"},{"prefectureJisCode":"28","cityJisCode":"28201","townNameKana":"ｱﾎﾞｼｸｱﾎﾞｼﾊﾏ","townName":"網干区網干浜","zipCode":"6711236"},{"prefectureJisCode":"28","cityJisCode":"28201","townNameKana":"ｱﾎﾞｼｸｵｵｴｼﾞﾏ","townName":"網干区大江島","zipCode":"6711231"},{"prefectureJisCode":"28","cityJisCode":"28201","townNameKana":"ｱﾎﾞｼｸｵｵｴｼﾞﾏﾃﾗﾏｴﾁｮｳ","townName":"網干区大江島寺前町","zipCode":"6711232"},{"prefectureJisCode":"28","cityJisCode":"28201","townNameKana":"ｱﾎﾞｼｸｵｵｴｼﾞﾏﾌﾙｶﾜﾁｮｳ","townName":"網干区大江島古川町","zipCode":"6711233"},{"prefectureJisCode":"28","cityJisCode":"28201","townNameKana":"ｱﾎﾞｼｸｵｷﾉﾊﾏ","townName":"網干区興浜","zipCode":"6711241"},{"prefectureJisCode":"28","cityJisCode":"28201","townNameKana":"ｱﾎﾞｼｸｶｲﾁｷﾀﾏﾁ","townName":"網干区垣内北町","zipCode":"6711251"},{"prefectureJisCode":"28","cityJisCode":"28201","townNameKana":"ｱﾎﾞｼｸｶｲﾁﾅｶﾏﾁ","townName":"網干区垣内中町","zipCode":"6711253"},{"prefectureJisCode":"28","cityJisCode":"28201","townNameKana":"ｱﾎﾞｼｸｶｲﾁﾆｼﾏﾁ","townName":"網干区垣内西町","zipCode":"6711256"},{"prefectureJisCode":"28","cityJisCode":"28201","townNameKana":"ｱﾎﾞｼｸｶｲﾁﾋｶﾞｼﾏﾁ","townName":"網干区垣内東町","zipCode":"6711252"},{"prefectureJisCode":"28","cityJisCode":"28201","townNameKana":"ｱﾎﾞｼｸｶｲﾁﾎﾝﾏﾁ","townName":"網干区垣内本町","zipCode":"6711257"},{"prefectureJisCode":"28","cityJisCode":"28201","townNameKana":"ｱﾎﾞｼｸｶｲﾁﾐﾅﾐﾏﾁ","townName":"網干区垣内南町","zipCode":"6711255"},{"prefectureJisCode":"28","cityJisCode":"28201","townNameKana":"ｱﾎﾞｼｸｷﾀｼﾝｻﾞｲｹ","townName":"網干区北新在家","zipCode":"6711235"},{"prefectureJisCode":"28","cityJisCode":"28201","townNameKana":"ｱﾎﾞｼｸｻｶｳｴ","townName":"網干区坂上","zipCode":"6711223"},{"prefectureJisCode":"28","cityJisCode":"28201","townNameKana":"ｱﾎﾞｼｸｻｶﾃﾞ","townName":"網干区坂出","zipCode":"6711228"},{"prefectureJisCode":"28","cityJisCode":"28201","townNameKana":"ｱﾎﾞｼｸｼﾝｻﾞｲｹ","townName":"網干区新在家","zipCode":"6711234"},{"prefectureJisCode":"28","cityJisCode":"28201","townNameKana":"ｱﾎﾞｼｸﾀｲ","townName":"網干区田井","zipCode":"6711221"},{"prefectureJisCode":"28","cityJisCode":"28201","townNameKana":"ｱﾎﾞｼｸﾀｶﾀﾞ","townName":"網干区高田","zipCode":"6711226"},{"prefectureJisCode":"28","cityJisCode":"28201","townNameKana":"ｱﾎﾞｼｸﾂｲﾁﾊﾞ","townName":"網干区津市場","zipCode":"6711224"},{"prefectureJisCode":"28","cityJisCode":"28201","townNameKana":"ｱﾎﾞｼｸﾊﾏﾀﾞ","townName":"網干区浜田","zipCode":"6711242"},{"prefectureJisCode":"28","cityJisCode":"28201","townNameKana":"ｱﾎﾞｼｸﾌｸｲ","townName":"網干区福井","zipCode":"6711225"},{"prefectureJisCode":"28","cityJisCode":"28201","townNameKana":"ｱﾎﾞｼｸﾐﾔｳﾁ","townName":"網干区宮内","zipCode":"6711222"},{"prefectureJisCode":"28","cityJisCode":"28201","townNameKana":"ｱﾎﾞｼｸﾖｺﾊﾏ","townName":"網干区余子浜","zipCode":"6711254"},{"prefectureJisCode":"28","cityJisCode":"28201","townNameKana":"ｱﾎﾞｼｸﾜｸ","townName":"網干区和久","zipCode":"6711227"},{"prefectureJisCode":"28","cityJisCode":"28201","townNameKana":"ｱﾗｼﾔﾏﾁｮｳ","townName":"嵐山町","zipCode":"6700029"},{"prefectureJisCode":"28","cityJisCode":"28201","townNameKana":"ｲｲﾀﾞ","townName":"飯田","zipCode":"6700974"},{"prefectureJisCode":"28","cityJisCode":"28201","townNameKana":"ｲｴｼﾏﾁｮｳﾎﾞｳｾﾞ","townName":"家島町坊勢","zipCode":"6720103"},{"prefectureJisCode":"28","cityJisCode":"28201","townNameKana":"ｲｴｼﾏﾁｮｳﾏｳﾗ","townName":"家島町真浦","zipCode":"6720101"},{"prefectureJisCode":"28","cityJisCode":"28201","townNameKana":"ｲｴｼﾏﾁｮｳﾐﾔ","townName":"家島町宮","zipCode":"6720102"},{"prefectureJisCode":"28","cityJisCode":"28201","townNameKana":"ｲｸﾉﾏﾁ","townName":"生野町","zipCode":"6700007"},{"prefectureJisCode":"28","cityJisCode":"28201","townNameKana":"ｲｼｸﾗ","townName":"石倉","zipCode":"6712231"},{"prefectureJisCode":"28","cityJisCode":"28201","townNameKana":"ｲﾁｶﾜﾀﾞｲ","townName":"市川台","zipCode":"6700822"},{"prefectureJisCode":"28","cityJisCode":"28201","townNameKana":"ｲﾁｶﾜﾊﾞｼﾄﾞｵﾘ","townName":"市川橋通","zipCode":"6700825"},{"prefectureJisCode":"28","cityJisCode":"28201","townNameKana":"ｲﾁﾉｺﾞｳﾁｮｳ","townName":"市之郷町","zipCode":"6700943"},{"prefectureJisCode":"28","cityJisCode":"28201","townNameKana":"ｲﾃﾞｲ","townName":"伊伝居","zipCode":"6700871"},{"prefectureJisCode":"28","cityJisCode":"28201","townNameKana":"ｲﾄｸｼﾞﾏﾁ","townName":"威徳寺町","zipCode":"6700816"},{"prefectureJisCode":"28","cityJisCode":"28201","townNameKana":"ｲﾉｸﾞﾁ","townName":"井ノ口","zipCode":"6700983"},{"prefectureJisCode":"28","cityJisCode":"28201","townNameKana":"ｲﾏｼﾞｭｸ","townName":"今宿","zipCode":"6700052"},{"prefectureJisCode":"28","cityJisCode":"28201","townNameKana":"ｲﾜﾊﾞﾅﾁｮｳ","townName":"岩端町","zipCode":"6700028"},{"prefectureJisCode":"28","cityJisCode":"28201","townNameKana":"ｳｵﾏﾁ","townName":"魚町","zipCode":"6700905"},{"prefectureJisCode":"28","cityJisCode":"28201","townNameKana":"ｳﾁｺｼ","townName":"打越","zipCode":"6712246"},{"prefectureJisCode":"28","cityJisCode":"28201","townNameKana":"ｳﾒｶﾞｴﾁｮｳ","townName":"梅ケ枝町","zipCode":"6700817"},{"prefectureJisCode":"28","cityJisCode":"28201","townNameKana":"ｳﾒｶﾞﾀﾆﾁｮｳ","townName":"梅ケ谷町","zipCode":"6700894"},{"prefectureJisCode":"28","cityJisCode":"28201","townNameKana":"ｴｷﾏｴﾁｮｳ","townName":"駅前町","zipCode":"6700927"},{"prefectureJisCode":"28","cityJisCode":"28201","townNameKana":"ｵｵｲﾁﾅｶ","townName":"太市中","zipCode":"6712233"},{"prefectureJisCode":"28","cityJisCode":"28201","townNameKana":"ｵｵｼｵﾁｮｳ","townName":"大塩町","zipCode":"6710101"},{"prefectureJisCode":"28","cityJisCode":"28201","townNameKana":"ｵｵｼｵﾁｮｳｼｵｻｷ","townName":"大塩町汐咲","zipCode":"6710102"},{"prefectureJisCode":"28","cityJisCode":"28201","townNameKana":"ｵｵｼｵﾁｮｳﾐﾔﾏｴ","townName":"大塩町宮前","zipCode":"6710103"},{"prefectureJisCode":"28","cityJisCode":"28201","townNameKana":"ｵｵﾂｸｴﾋﾞｽﾏﾁ","townName":"大津区恵美酒町","zipCode":"6711136"},{"prefectureJisCode":"28","cityJisCode":"28201","townNameKana":"ｵｵﾂｸｵｵﾂﾁｮｳ","townName":"大津区大津町","zipCode":"6711146"},{"prefectureJisCode":"28","cityJisCode":"28201","townNameKana":"ｵｵﾂｸｶﾝﾍﾞｴﾁｮｳ","townName":"大津区勘兵衛町","zipCode":"6711132"},{"prefectureJisCode":"28","cityJisCode":"28201","townNameKana":"ｵｵﾂｸｷﾀﾃﾝﾏﾝﾁｮｳ","townName":"大津区北天満町","zipCode":"6711142"},{"prefectureJisCode":"28","cityJisCode":"28201","townNameKana":"ｵｵﾂｸｷﾋﾞ","townName":"大津区吉美","zipCode":"6711133"},{"prefectureJisCode":"28","cityJisCode":"28201","townNameKana":"ｵｵﾂｸｼﾝﾏﾁ","townName":"大津区新町","zipCode":"6711135"},{"prefectureJisCode":"28","cityJisCode":"28201","townNameKana":"ｵｵﾂｸﾃﾝｼﾞﾝﾏﾁ","townName":"大津区天神町","zipCode":"6711131"},{"prefectureJisCode":"28","cityJisCode":"28201","townNameKana":"ｵｵﾂｸﾃﾝﾏ","townName":"大津区天満","zipCode":"6711143"},{"prefectureJisCode":"28","cityJisCode":"28201","townNameKana":"ｵｵﾂｸﾅｶﾞﾏﾂ","townName":"大津区長松","zipCode":"6711144"},{"prefectureJisCode":"28","cityJisCode":"28201","townNameKana":"ｵｵﾂｸﾆｼﾄﾞｲ","townName":"大津区西土井","zipCode":"6711141"},{"prefectureJisCode":"28","cityJisCode":"28201","townNameKana":"ｵｵﾂｸﾋﾗﾏﾂ","townName":"大津区平松","zipCode":"6711145"},{"prefectureJisCode":"28","cityJisCode":"28201","townNameKana":"ｵｵﾂｸﾏｻｺﾞﾁｮｳ","townName":"大津区真砂町","zipCode":"6711134"},{"prefectureJisCode":"28","cityJisCode":"28201","townNameKana":"ｵｵﾉﾏﾁ","townName":"大野町","zipCode":"6700868"},{"prefectureJisCode":"28","cityJisCode":"28201","townNameKana":"ｵｶﾀﾞ","townName":"岡田","zipCode":"6700982"},{"prefectureJisCode":"28","cityJisCode":"28201","townNameKana":"ｵｶﾏﾁ","townName":"岡町","zipCode":"6700026"},{"prefectureJisCode":"28","cityJisCode":"28201","townNameKana":"ｵｸﾔﾏ","townName":"奥山","zipCode":"6728003"},{"prefectureJisCode":"28","cityJisCode":"28201","townNameKana":"ｶｷﾔﾏﾌﾞｼ","townName":"柿山伏","zipCode":"6700037"},{"prefectureJisCode":"28","cityJisCode":"28201","townNameKana":"ｶｷﾞﾏﾁ","townName":"鍵町","zipCode":"6700009"},{"prefectureJisCode":"28","cityJisCode":"28201","townNameKana":"ｶｼﾞﾏﾁ","townName":"鍛冶町","zipCode":"6700002"},{"prefectureJisCode":"28","cityJisCode":"28201","townNameKana":"ｶﾀﾀﾞﾏﾁ","townName":"片田町","zipCode":"6700045"},{"prefectureJisCode":"28","cityJisCode":"28201","townNameKana":"ｶﾀﾅﾃﾞ","townName":"刀出","zipCode":"6712241"},{"prefectureJisCode":"28","cityJisCode":"28201","townNameKana":"ｶﾂﾊﾗｸｱｻﾋﾀﾞﾆ","townName":"勝原区朝日谷","zipCode":"6711204"},{"prefectureJisCode":"28","cityJisCode":"28201","townNameKana":"ｶﾂﾊﾗｸｵｵﾀﾆ","townName":"勝原区大谷","zipCode":"6711205"},{"prefectureJisCode":"28","cityJisCode":"28201","townNameKana":"ｶﾂﾊﾗｸｶﾂﾊﾗﾁｮｳ","townName":"勝原区勝原町","zipCode":"6711212"},{"prefectureJisCode":"28","cityJisCode":"28201","townNameKana":"ｶﾂﾊﾗｸｶﾂﾔﾏﾁｮｳ","townName":"勝原区勝山町","zipCode":"6711202"},{"prefectureJisCode":"28","cityJisCode":"28201","townNameKana":"ｶﾂﾊﾗｸｸﾏﾐ","townName":"勝原区熊見","zipCode":"6711211"},{"prefectureJisCode":"28","cityJisCode":"28201","townNameKana":"ｶﾂﾊﾗｸｼﾓｵｵﾀ","townName":"勝原区下太田","zipCode":"6711201"},{"prefectureJisCode":"28","cityJisCode":"28201","townNameKana":"ｶﾂﾊﾗｸﾐﾔﾀ","townName":"勝原区宮田","zipCode":"6711213"},{"prefectureJisCode":"28","cityJisCode":"28201","townNameKana":"ｶﾂﾊﾗｸﾔﾏﾄ","townName":"勝原区山戸","zipCode":"6711214"},{"prefectureJisCode":"28","cityJisCode":"28201","townNameKana":"ｶﾂﾊﾗｸﾖﾛ","townName":"勝原区丁","zipCode":"6711203"},{"prefectureJisCode":"28","cityJisCode":"28201","townNameKana":"ｶﾅﾔﾏﾁ","townName":"金屋町","zipCode":"6700005"},{"prefectureJisCode":"28","cityJisCode":"28201","townNameKana":"ｶﾈﾀﾞ","townName":"兼田","zipCode":"6728001"},{"prefectureJisCode":"28","cityJisCode":"28201","townNameKana":"ｶﾐｵｵﾉ","townName":"上大野","zipCode":"6700896"},{"prefectureJisCode":"28","cityJisCode":"28201","townNameKana":"ｶﾐｶﾀﾏﾁ","townName":"上片町","zipCode":"6700041"},{"prefectureJisCode":"28","cityJisCode":"28201","townNameKana":"ｶﾐﾃﾉ","townName":"上手野","zipCode":"6700065"},{"prefectureJisCode":"28","cityJisCode":"28201","townNameKana":"ｶﾐﾔﾁｮｳ","townName":"神屋町","zipCode":"6700836"},{"prefectureJisCode":"28","cityJisCode":"28201","townNameKana":"ｶﾒｲﾏﾁ","townName":"亀井町","zipCode":"6700925"},{"prefectureJisCode":"28","cityJisCode":"28201","townNameKana":"ｶﾒﾔﾏ","townName":"亀山","zipCode":"6700973"},{"prefectureJisCode":"28","cityJisCode":"28201","townNameKana":"ｶﾜﾆｼ","townName":"川西","zipCode":"6712212"},{"prefectureJisCode":"28","cityJisCode":"28201","townNameKana":"ｶﾜﾆｼﾀﾞｲ","townName":"川西台","zipCode":"6712213"},{"prefectureJisCode":"28","cityJisCode":"28201","townNameKana":"ｶﾝﾀﾞﾁｮｳ","townName":"神田町","zipCode":"6700991"},{"prefectureJisCode":"28","cityJisCode":"28201","townNameKana":"ｷｮｳｸﾞﾁﾏﾁ","townName":"京口町","zipCode":"6700851"},{"prefectureJisCode":"28","cityJisCode":"28201","townNameKana":"ｷｮｳﾏﾁ","townName":"京町","zipCode":"6700824"},{"prefectureJisCode":"28","cityJisCode":"28201","townNameKana":"ｷﾀｲﾏｼﾞｭｸ","townName":"北今宿","zipCode":"6700057"},{"prefectureJisCode":"28","cityJisCode":"28201","townNameKana":"ｷﾀｼﾝｻﾞｲｹ","townName":"北新在家","zipCode":"6700091"},{"prefectureJisCode":"28","cityJisCode":"28201","townNameKana":"ｷﾀﾊﾗ","townName":"北原","zipCode":"6728002"},{"prefectureJisCode":"28","cityJisCode":"28201","townNameKana":"ｷﾀﾋﾗﾉ","townName":"北平野","zipCode":"6700893"},{"prefectureJisCode":"28","cityJisCode":"28201","townNameKana":"ｷﾀﾋﾗﾉｵｸｶﾞｲﾁ","townName":"北平野奥垣内","zipCode":"6700892"},{"prefectureJisCode":"28","cityJisCode":"28201","townNameKana":"ｷﾀﾋﾗﾉﾀﾞｲﾁｮｳ","townName":"北平野台町","zipCode":"6700895"},{"prefectureJisCode":"28","cityJisCode":"28201","townNameKana":"ｷﾀﾋﾗﾉﾐﾅﾐﾉﾁｮｳ","townName":"北平野南の町","zipCode":"6700887"},{"prefectureJisCode":"28","cityJisCode":"28201","townNameKana":"ｷﾀﾔｼﾛ","townName":"北八代","zipCode":"6700877"},{"prefectureJisCode":"28","cityJisCode":"28201","townNameKana":"ｷﾀﾕﾒｻｷﾀﾞｲ","townName":"北夢前台","zipCode":"6700075"},{"prefectureJisCode":"28","cityJisCode":"28201","townNameKana":"ｷﾊﾞ","townName":"木場","zipCode":"6728016"},{"prefectureJisCode":"28","cityJisCode":"28201","townNameKana":"ｷﾊﾞｼﾞｭｳﾊｯﾀﾝﾁｮｳ","townName":"木場十八反町","zipCode":"6728017"},{"prefectureJisCode":"28","cityJisCode":"28201","townNameKana":"ｷﾊﾞﾏｴﾅｶﾁｮｳ","townName":"木場前中町","zipCode":"6728018"},{"prefectureJisCode":"28","cityJisCode":"28201","townNameKana":"ｷﾊﾞﾏｴﾅﾅﾀﾝﾁｮｳ","townName":"木場前七反町","zipCode":"6728019"},{"prefectureJisCode":"28","cityJisCode":"28201","townNameKana":"ｸｽﾉｷﾁｮｳ","townName":"楠町","zipCode":"6700826"},{"prefectureJisCode":"28","cityJisCode":"28201","townNameKana":"ｸﾎﾞﾁｮｳ","townName":"久保町","zipCode":"6700916"},{"prefectureJisCode":"28","cityJisCode":"28201","townNameKana":"ｸﾘﾔﾏﾁｮｳ","townName":"栗山町","zipCode":"6700954"},{"prefectureJisCode":"28","cityJisCode":"28201","townNameKana":"ｸﾙﾏｻﾞｷ","townName":"車崎","zipCode":"6700058"},{"prefectureJisCode":"28","cityJisCode":"28201","townNameKana":"ｹｲﾌｸｼﾞﾏｴ","townName":"景福寺前","zipCode":"6700027"},{"prefectureJisCode":"28","cityJisCode":"28201","townNameKana":"ｺｳﾃﾞﾗﾁｮｳｱｲｻｶ","townName":"香寺町相坂","zipCode":"6792154"},{"prefectureJisCode":"28","cityJisCode":"28201","townNameKana":"ｺｳﾃﾞﾗﾁｮｳｲﾇｶｲ","townName":"香寺町犬飼","zipCode":"6792131"},{"prefectureJisCode":"28","cityJisCode":"28201","townNameKana":"ｺｳﾃﾞﾗﾁｮｳｲﾜﾍﾞ","townName":"香寺町岩部","zipCode":"6792141"},{"prefectureJisCode":"28","cityJisCode":"28201","townNameKana":"ｺｳﾃﾞﾗﾁｮｳｸﾊﾞﾀ","townName":"香寺町久畑","zipCode":"6792167"},{"prefectureJisCode":"28","cityJisCode":"28201","townNameKana":"ｺｳﾃﾞﾗﾁｮｳｺｳﾛ","townName":"香寺町香呂","zipCode":"6792151"},{"prefectureJisCode":"28","cityJisCode":"28201","townNameKana":"ｺｳﾃﾞﾗﾁｮｳｽｶｲﾝ","townName":"香寺町須加院","zipCode":"6792132"},{"prefectureJisCode":"28","cityJisCode":"28201","townNameKana":"ｺｳﾃﾞﾗﾁｮｳﾀﾉ","townName":"香寺町田野","zipCode":"6792153"},{"prefectureJisCode":"28","cityJisCode":"28201","townNameKana":"ｺｳﾃﾞﾗﾁｮｳﾂﾈﾔ","townName":"香寺町恒屋","zipCode":"6792165"},{"prefectureJisCode":"28","cityJisCode":"28201","townNameKana":"ｺｳﾃﾞﾗﾁｮｳﾅｶﾃﾞﾗ","townName":"香寺町中寺","zipCode":"6792164"},{"prefectureJisCode":"28","cityJisCode":"28201","townNameKana":"ｺｳﾃﾞﾗﾁｮｳﾅｶﾆﾉ","townName":"香寺町中仁野","zipCode":"6792143"},{"prefectureJisCode":"28","cityJisCode":"28201","townNameKana":"ｺｳﾃﾞﾗﾁｮｳﾅｶﾑﾗ","townName":"香寺町中村","zipCode":"6792166"},{"prefectureJisCode":"28","cityJisCode":"28201","townNameKana":"ｺｳﾃﾞﾗﾁｮｳﾅｶﾔ","townName":"香寺町中屋","zipCode":"6792144"},{"prefectureJisCode":"28","cityJisCode":"28201","townNameKana":"ｺｳﾃﾞﾗﾁｮｳﾉﾀﾞ","townName":"香寺町野田","zipCode":"6792162"},{"prefectureJisCode":"28","cityJisCode":"28201","townNameKana":"ｺｳﾃﾞﾗﾁｮｳﾊｾﾞ","townName":"香寺町土師","zipCode":"6792163"},{"prefectureJisCode":"28","cityJisCode":"28201","townNameKana":"ｺｳﾃﾞﾗﾁｮｳﾋﾛｾ","townName":"香寺町広瀬","zipCode":"6792142"},{"prefectureJisCode":"28","cityJisCode":"28201","townNameKana":"ｺｳﾃﾞﾗﾁｮｳﾐｿﾞｸﾞﾁ","townName":"香寺町溝口","zipCode":"6792161"},{"prefectureJisCode":"28","cityJisCode":"28201","townNameKana":"ｺｳﾃﾞﾗﾁｮｳﾔﾀﾍﾞ","townName":"香寺町矢田部","zipCode":"6792155"},{"prefectureJisCode":"28","cityJisCode":"28201","townNameKana":"ｺｳﾃﾞﾗﾁｮｳﾕｷｼｹﾞ","townName":"香寺町行重","zipCode":"6792152"},{"prefectureJisCode":"28","cityJisCode":"28201","townNameKana":"ｺｵﾃﾞﾗﾏﾁ","townName":"国府寺町","zipCode":"6700852"},{"prefectureJisCode":"28","cityJisCode":"28201","townNameKana":"ｺｼｮｳﾏﾁ","townName":"小姓町","zipCode":"6700043"},{"prefectureJisCode":"28","cityJisCode":"28201","townNameKana":"ｺﾄｵｶﾁｮｳ","townName":"琴岡町","zipCode":"6700035"},{"prefectureJisCode":"28","cityJisCode":"28201","townNameKana":"ｺﾆｶｲﾏﾁ","townName":"古二階町","zipCode":"6700936"},{"prefectureJisCode":"28","cityJisCode":"28201","townNameKana":"ｺﾊﾞｻﾏﾁｮｳ","townName":"河間町","zipCode":"6700001"},{"prefectureJisCode":"28","cityJisCode":"28201","townNameKana":"ｺﾒﾔﾏﾁ","townName":"米屋町","zipCode":"6700003"},{"prefectureJisCode":"28","cityJisCode":"28201","townNameKana":"ｺﾘｷﾏﾁ","townName":"小利木町","zipCode":"6700022"},{"prefectureJisCode":"28","cityJisCode":"28201","townNameKana":"ｺﾝﾔﾏﾁ","townName":"紺屋町","zipCode":"6700924"},{"prefectureJisCode":"28","cityJisCode":"28201","townNameKana":"ｺﾞｹﾝﾔｼｷ","townName":"五軒邸","zipCode":"6700854"},{"prefectureJisCode":"28","cityJisCode":"28201","townNameKana":"ｺﾞﾌｸﾏﾁ","townName":"呉服町","zipCode":"6700923"},{"prefectureJisCode":"28","cityJisCode":"28201","townNameKana":"ｺﾞﾛｳｴﾓﾝﾃｲ","townName":"五郎右衛門邸","zipCode":"6700857"},{"prefectureJisCode":"28","cityJisCode":"28201","townNameKana":"ｻｲｼｮｳ","townName":"西庄","zipCode":"6700981"},{"prefectureJisCode":"28","cityJisCode":"28201","townNameKana":"ｻｲﾜｲﾁｮｳ","townName":"幸町","zipCode":"6700835"},{"prefectureJisCode":"28","cityJisCode":"28201","townNameKana":"ｻｶｲﾏﾁ","townName":"堺町","zipCode":"6700014"},{"prefectureJisCode":"28","cityJisCode":"28201","townNameKana":"ｻｶﾀﾏﾁ","townName":"坂田町","zipCode":"6700931"},{"prefectureJisCode":"28","cityJisCode":"28201","townNameKana":"ｻｶﾓﾄﾏﾁ","townName":"坂元町","zipCode":"6700016"},{"prefectureJisCode":"28","cityJisCode":"28201","townNameKana":"ｻﾀﾞﾓﾄﾏﾁ","townName":"定元町","zipCode":"6700994"},{"prefectureJisCode":"28","cityJisCode":"28201","townNameKana":"ｻﾝｻﾞｴﾓﾝﾎﾞﾘﾆｼﾉﾏﾁ","townName":"三左衛門堀西の町","zipCode":"6700940"},{"prefectureJisCode":"28","cityJisCode":"28201","townNameKana":"ｻﾝｻﾞｴﾓﾝﾎﾞﾘﾋｶﾞｼﾉﾏﾁ","townName":"三左衛門堀東の町","zipCode":"6700949"},{"prefectureJisCode":"28","cityJisCode":"28201","townNameKana":"ｻﾝｼﾞｮｳﾁｮｳ","townName":"三条町","zipCode":"6700953"},{"prefectureJisCode":"28","cityJisCode":"28201","townNameKana":"ｻﾞｲﾓｸﾏﾁ","townName":"材木町","zipCode":"6700025"},{"prefectureJisCode":"28","cityJisCode":"28201","townNameKana":"ｼｮｳﾀﾞ","townName":"庄田","zipCode":"6700951"},{"prefectureJisCode":"28","cityJisCode":"28201","townNameKana":"ｼｮｼｬ","townName":"書写","zipCode":"6712201"},{"prefectureJisCode":"28","cityJisCode":"28201","townNameKana":"ｼｮｼｬﾀﾞｲ","townName":"書写台","zipCode":"6712203"},{"prefectureJisCode":"28","cityJisCode":"28201","townNameKana":"ｼｵﾏﾁ","townName":"塩町","zipCode":"6700904"},{"prefectureJisCode":"28","cityJisCode":"28201","townNameKana":"ｼｶﾏｸｱｶﾞ","townName":"飾磨区英賀","zipCode":"6728078"},{"prefectureJisCode":"28","cityJisCode":"28201","townNameKana":"ｼｶﾏｸｱｶﾞｶｽｶﾞﾁｮｳ","townName":"飾磨区英賀春日町","zipCode":"6728092"},{"prefectureJisCode":"28","cityJisCode":"28201","townNameKana":"ｼｶﾏｸｱｶﾞｼﾐｽﾞﾁｮｳ","townName":"飾磨区英賀清水町","zipCode":"6728084"},{"prefectureJisCode":"28","cityJisCode":"28201","townNameKana":"ｼｶﾏｸｱｶﾞﾆｼﾁｮｳ","townName":"飾磨区英賀西町","zipCode":"6728088"},{"prefectureJisCode":"28","cityJisCode":"28201","townNameKana":"ｼｶﾏｸｱｶﾞﾋｶﾞｼﾁｮｳ","townName":"飾磨区英賀東町","zipCode":"6728087"},{"prefectureJisCode":"28","cityJisCode":"28201","townNameKana":"ｼｶﾏｸｱｶﾞﾎｴｷﾏｴﾁｮｳ","townName":"飾磨区英賀保駅前町","zipCode":"6728091"},{"prefectureJisCode":"28","cityJisCode":"28201","townNameKana":"ｼｶﾏｸｱｶﾞﾐﾔﾀﾞｲ","townName":"飾磨区英賀宮台","zipCode":"6728089"},{"prefectureJisCode":"28","cityJisCode":"28201","townNameKana":"ｼｶﾏｸｱｶﾞﾐﾔﾁｮｳ","townName":"飾磨区英賀宮町","zipCode":"6728080"},{"prefectureJisCode":"28","cityJisCode":"28201","townNameKana":"ｼｶﾏｸｱﾅｾ","townName":"飾磨区阿成","zipCode":"6728037"},{"prefectureJisCode":"28","cityJisCode":"28201","townNameKana":"ｼｶﾏｸｱﾅｾｳｴｷ","townName":"飾磨区阿成植木","zipCode":"6728030"},{"prefectureJisCode":"28","cityJisCode":"28201","townNameKana":"ｼｶﾏｸｱﾅｾｶｺ","townName":"飾磨区阿成鹿古","zipCode":"6728038"},{"prefectureJisCode":"28","cityJisCode":"28201","townNameKana":"ｼｶﾏｸｱﾅｾｼﾓｶｲﾁ","townName":"飾磨区阿成下垣内","zipCode":"6728059"},{"prefectureJisCode":"28","cityJisCode":"28201","townNameKana":"ｼｶﾏｸｱﾅｾﾅｶｶｲﾁ","townName":"飾磨区阿成中垣内","zipCode":"6728058"},{"prefectureJisCode":"28","cityJisCode":"28201","townNameKana":"ｼｶﾏｸｱﾅｾﾜﾀｼﾊﾞ","townName":"飾磨区阿成渡場","zipCode":"6728039"},{"prefectureJisCode":"28","cityJisCode":"28201","townNameKana":"ｼｶﾏｸｲﾏｻﾞｲｹ","townName":"飾磨区今在家","zipCode":"6728079"},{"prefectureJisCode":"28","cityJisCode":"28201","townNameKana":"ｼｶﾏｸｲﾏｻﾞｲｹｷﾀ","townName":"飾磨区今在家北","zipCode":"6728090"},{"prefectureJisCode":"28","cityJisCode":"28201","townNameKana":"ｼｶﾏｸｲﾘﾌﾈﾁｮｳ","townName":"飾磨区入船町","zipCode":"6728076"},{"prefectureJisCode":"28","cityJisCode":"28201","townNameKana":"ｼｶﾏｸｴﾋﾞｽ","townName":"飾磨区恵美酒","zipCode":"6728057"},{"prefectureJisCode":"28","cityJisCode":"28201","townNameKana":"ｼｶﾏｸｵｵﾊﾏ","townName":"飾磨区大浜","zipCode":"6728062"},{"prefectureJisCode":"28","cityJisCode":"28201","townNameKana":"ｼｶﾏｸｶｽﾔｼﾝﾏﾁ","townName":"飾磨区粕谷新町","zipCode":"6728077"},{"prefectureJisCode":"28","cityJisCode":"28201","townNameKana":"ｼｶﾏｸｶﾏｴ","townName":"飾磨区構","zipCode":"6728071"},{"prefectureJisCode":"28","cityJisCode":"28201","townNameKana":"ｼｶﾏｸｶﾏｸﾗﾁｮｳ","townName":"飾磨区鎌倉町","zipCode":"6728094"},{"prefectureJisCode":"28","cityJisCode":"28201","townNameKana":"ｼｶﾏｸｶﾐﾉﾀﾞ","townName":"飾磨区上野田","zipCode":"6728043"},{"prefectureJisCode":"28","cityJisCode":"28201","townNameKana":"ｼｶﾏｸｶﾒﾔﾏ","townName":"飾磨区亀山","zipCode":"6728047"},{"prefectureJisCode":"28","cityJisCode":"28201","townNameKana":"ｼｶﾏｸｶﾓ","townName":"飾磨区加茂","zipCode":"6728074"},{"prefectureJisCode":"28","cityJisCode":"28201","townNameKana":"ｼｶﾏｸｶﾓｷﾀ","townName":"飾磨区加茂北","zipCode":"6728073"},{"prefectureJisCode":"28","cityJisCode":"28201","townNameKana":"ｼｶﾏｸｶﾓﾋｶﾞｼ","townName":"飾磨区加茂東","zipCode":"6728070"},{"prefectureJisCode":"28","cityJisCode":"28201","townNameKana":"ｼｶﾏｸｶﾓﾐﾅﾐ","townName":"飾磨区加茂南","zipCode":"6728069"},{"prefectureJisCode":"28","cityJisCode":"28201","townNameKana":"ｼｶﾏｸｺﾞｺｳ","townName":"飾磨区御幸","zipCode":"6728056"},{"prefectureJisCode":"28","cityJisCode":"28201","townNameKana":"ｼｶﾏｸｻｶｴﾏﾁ","townName":"飾磨区栄町","zipCode":"6728053"},{"prefectureJisCode":"28","cityJisCode":"28201","townNameKana":"ｼｶﾏｸｻﾝﾜﾁｮｳ","townName":"飾磨区三和町","zipCode":"6728036"},{"prefectureJisCode":"28","cityJisCode":"28201","townNameKana":"ｼｶﾏｸｼｱﾝﾊﾞｼ","townName":"飾磨区思案橋","zipCode":"6728075"},{"prefectureJisCode":"28","cityJisCode":"28201","townNameKana":"ｼｶﾏｸｼﾐｽﾞ","townName":"飾磨区清水","zipCode":"6728051"},{"prefectureJisCode":"28","cityJisCode":"28201","townNameKana":"ｼｶﾏｸｼﾓﾉﾀﾞ","townName":"飾磨区下野田","zipCode":"6728044"},{"prefectureJisCode":"28","cityJisCode":"28201","townNameKana":"ｼｶﾏｸｼﾞｮｳﾅﾝﾁｮｳ","townName":"飾磨区城南町","zipCode":"6728083"},{"prefectureJisCode":"28","cityJisCode":"28201","townNameKana":"ｼｶﾏｸｽｶ","townName":"飾磨区須加","zipCode":"6728063"},{"prefectureJisCode":"28","cityJisCode":"28201","townNameKana":"ｼｶﾏｸﾀｶﾏﾁ","townName":"飾磨区高町","zipCode":"6728081"},{"prefectureJisCode":"28","cityJisCode":"28201","townNameKana":"ｼｶﾏｸﾀﾃﾞﾉﾁｮｳ","townName":"飾磨区蓼野町","zipCode":"6728072"},{"prefectureJisCode":"28","cityJisCode":"28201","townNameKana":"ｼｶﾏｸﾀﾏﾁ","townName":"飾磨区玉地","zipCode":"6728052"},{"prefectureJisCode":"28","cityJisCode":"28201","townNameKana":"ｼｶﾏｸﾂｹｼﾛ","townName":"飾磨区付城","zipCode":"6728082"},{"prefectureJisCode":"28","cityJisCode":"28201","townNameKana":"ｼｶﾏｸﾃﾝｼﾞﾝ","townName":"飾磨区天神","zipCode":"6728061"},{"prefectureJisCode":"28","cityJisCode":"28201","townNameKana":"ｼｶﾏｸﾄｸﾗ","townName":"飾磨区都倉","zipCode":"6728046"},{"prefectureJisCode":"28","cityJisCode":"28201","townNameKana":"ｼｶﾏｸﾅｶｼﾏ","townName":"飾磨区中島","zipCode":"6728035"},{"prefectureJisCode":"28","cityJisCode":"28201","townNameKana":"ｼｶﾏｸﾅｶﾉﾀﾞ","townName":"飾磨区中野田","zipCode":"6728045"},{"prefectureJisCode":"28","cityJisCode":"28201","townNameKana":"ｼｶﾏｸﾅｶﾊﾏﾁｮｳ","townName":"飾磨区中浜町","zipCode":"6728085"},{"prefectureJisCode":"28","cityJisCode":"28201","townNameKana":"ｼｶﾏｸﾆｼﾊﾏﾁｮｳ","townName":"飾磨区西浜町","zipCode":"6728086"},{"prefectureJisCode":"28","cityJisCode":"28201","townNameKana":"ｼｶﾏｸﾉﾀﾞﾁｮｳ","townName":"飾磨区野田町","zipCode":"6728040"},{"prefectureJisCode":"28","cityJisCode":"28201","townNameKana":"ｼｶﾏｸﾋｶﾞｼﾎﾞﾘ","townName":"飾磨区東堀","zipCode":"6728054"},{"prefectureJisCode":"28","cityJisCode":"28201","townNameKana":"ｼｶﾏｸﾌｼﾞﾐｶﾞｵｶﾁｮｳ","townName":"飾磨区富士見ケ丘町","zipCode":"6728098"},{"prefectureJisCode":"28","cityJisCode":"28201","townNameKana":"ｼｶﾏｸﾎｿｴ","townName":"飾磨区細江","zipCode":"6728064"},{"prefectureJisCode":"28","cityJisCode":"28201","townNameKana":"ｼｶﾏｸﾎﾘｶﾜﾁｮｳ","townName":"飾磨区堀川町","zipCode":"6728025"},{"prefectureJisCode":"28","cityJisCode":"28201","townNameKana":"ｼｶﾏｸﾐﾔ","townName":"飾磨区宮","zipCode":"6728055"},{"prefectureJisCode":"28","cityJisCode":"28201","townNameKana":"ｼｶﾏｸﾐﾔｹ","townName":"飾磨区三宅","zipCode":"6728048"},{"prefectureJisCode":"28","cityJisCode":"28201","townNameKana":"ｼｶﾏｸﾒｶﾞ","townName":"飾磨区妻鹿","zipCode":"6728031"},{"prefectureJisCode":"28","cityJisCode":"28201","townNameKana":"ｼｶﾏｸﾒｶﾞﾄｳｶｲﾁｮｳ","townName":"飾磨区妻鹿東海町","zipCode":"6728032"},{"prefectureJisCode":"28","cityJisCode":"28201","townNameKana":"ｼｶﾏｸﾒｶﾞﾄｷﾜﾁｮｳ","townName":"飾磨区妻鹿常盤町","zipCode":"6728034"},{"prefectureJisCode":"28","cityJisCode":"28201","townNameKana":"ｼｶﾏｸﾒｶﾞﾋﾀﾞﾁｮｳ","townName":"飾磨区妻鹿日田町","zipCode":"6728033"},{"prefectureJisCode":"28","cityJisCode":"28201","townNameKana":"ｼｶﾏｸﾔｸﾞﾗﾁｮｳ","townName":"飾磨区矢倉町","zipCode":"6728093"},{"prefectureJisCode":"28","cityJisCode":"28201","townNameKana":"ｼｶﾏｸﾔﾏｻｷ","townName":"飾磨区山崎","zipCode":"6728097"},{"prefectureJisCode":"28","cityJisCode":"28201","townNameKana":"ｼｶﾏｸﾔﾏｻｷﾀﾞｲ","townName":"飾磨区山崎台","zipCode":"6728096"},{"prefectureJisCode":"28","cityJisCode":"28201","townNameKana":"ｼｶﾏｸﾜｶﾐﾔﾁｮｳ","townName":"飾磨区若宮町","zipCode":"6728095"},{"prefectureJisCode":"28","cityJisCode":"28201","townNameKana":"ｼｷｻｲ","townName":"飾西","zipCode":"6712216"},{"prefectureJisCode":"28","cityJisCode":"28201","townNameKana":"ｼｷｻｲﾀﾞｲ","townName":"飾西台","zipCode":"6712215"},{"prefectureJisCode":"28","cityJisCode":"28201","townNameKana":"ｼｷﾄｳﾁｮｳｵｵｶﾞﾏ","townName":"飾東町大釜","zipCode":"6710203"},{"prefectureJisCode":"28","cityJisCode":"28201","townNameKana":"ｼｷﾄｳﾁｮｳｵｵｶﾞﾏｼﾝ","townName":"飾東町大釜新","zipCode":"6710204"},{"prefectureJisCode":"28","cityJisCode":"28201","townNameKana":"ｼｷﾄｳﾁｮｳｵﾊﾗ","townName":"飾東町小原","zipCode":"6710209"},{"prefectureJisCode":"28","cityJisCode":"28201","townNameKana":"ｼｷﾄｳﾁｮｳｵﾊﾗｼﾝ","townName":"飾東町小原新","zipCode":"6710201"},{"prefectureJisCode":"28","cityJisCode":"28201","townNameKana":"ｼｷﾄｳﾁｮｳｶﾗﾊﾀｼﾝ","townName":"飾東町唐端新","zipCode":"6710214"},{"prefectureJisCode":"28","cityJisCode":"28201","townNameKana":"ｼｷﾄｳﾁｮｳｷﾀﾉ","townName":"飾東町北野","zipCode":"6710202"},{"prefectureJisCode":"28","cityJisCode":"28201","townNameKana":"ｼｷﾄｳﾁｮｳｷﾀﾔﾏ","townName":"飾東町北山","zipCode":"6710212"},{"prefectureJisCode":"28","cityJisCode":"28201","townNameKana":"ｼｷﾄｳﾁｮｳｷﾖｽﾐ","townName":"飾東町清住","zipCode":"6710205"},{"prefectureJisCode":"28","cityJisCode":"28201","townNameKana":"ｼｷﾄｳﾁｮｳｻﾛｵ","townName":"飾東町佐良和","zipCode":"6710217"},{"prefectureJisCode":"28","cityJisCode":"28201","townNameKana":"ｼｷﾄｳﾁｮｳｼｮｳ","townName":"飾東町庄","zipCode":"6710218"},{"prefectureJisCode":"28","cityJisCode":"28201","townNameKana":"ｼｷﾄｳﾁｮｳｼｵｻﾞｷ","townName":"飾東町塩崎","zipCode":"6710211"},{"prefectureJisCode":"28","cityJisCode":"28201","townNameKana":"ｼｷﾄｳﾁｮｳｼﾌﾞｷ","townName":"飾東町志吹","zipCode":"6710216"},{"prefectureJisCode":"28","cityJisCode":"28201","townNameKana":"ｼｷﾄｳﾁｮｳﾄﾖｸﾆ","townName":"飾東町豊国","zipCode":"6710219"},{"prefectureJisCode":"28","cityJisCode":"28201","townNameKana":"ｼｷﾄｳﾁｮｳﾔｴﾊﾞﾀ","townName":"飾東町八重畑","zipCode":"6710208"},{"prefectureJisCode":"28","cityJisCode":"28201","townNameKana":"ｼｷﾄｳﾁｮｳﾔﾏｻｷ","townName":"飾東町山崎","zipCode":"6710207"},{"prefectureJisCode":"28","cityJisCode":"28201","townNameKana":"ｼｷﾄｳﾁｮｳﾕｳﾋｶﾞｵｶ","townName":"飾東町夕陽ケ丘","zipCode":"6710215"},{"prefectureJisCode":"28","cityJisCode":"28201","townNameKana":"ｼｺﾞｳﾁｮｳｱｹﾀﾞ","townName":"四郷町明田","zipCode":"6710245"},{"prefectureJisCode":"28","cityJisCode":"28201","townNameKana":"ｼｺﾞｳﾁｮｳｶﾐｽｽﾞ","townName":"四郷町上鈴","zipCode":"6710241"},{"prefectureJisCode":"28","cityJisCode":"28201","townNameKana":"ｼｺﾞｳﾁｮｳｻｶﾓﾄ","townName":"四郷町坂元","zipCode":"6710246"},{"prefectureJisCode":"28","cityJisCode":"28201","townNameKana":"ｼｺﾞｳﾁｮｳﾅｶｽｽﾞ","townName":"四郷町中鈴","zipCode":"6710242"},{"prefectureJisCode":"28","cityJisCode":"28201","townNameKana":"ｼｺﾞｳﾁｮｳﾋｶﾞｼｱﾎﾞ","townName":"四郷町東阿保","zipCode":"6710247"},{"prefectureJisCode":"28","cityJisCode":"28201","townNameKana":"ｼｺﾞｳﾁｮｳﾎﾝｺﾞｳ","townName":"四郷町本郷","zipCode":"6710243"},{"prefectureJisCode":"28","cityJisCode":"28201","townNameKana":"ｼｺﾞｳﾁｮｳﾐﾉ","townName":"四郷町見野","zipCode":"6710244"},{"prefectureJisCode":"28","cityJisCode":"28201","townNameKana":"ｼｺﾞｳﾁｮｳﾔﾏﾜｷ","townName":"四郷町山脇","zipCode":"6710248"},{"prefectureJisCode":"28","cityJisCode":"28201","townNameKana":"ｼﾉﾉﾒﾁｮｳ","townName":"東雲町","zipCode":"6700046"},{"prefectureJisCode":"28","cityJisCode":"28201","townNameKana":"ｼﾉﾌﾞﾏﾁ","townName":"忍町","zipCode":"6700917"},{"prefectureJisCode":"28","cityJisCode":"28201","townNameKana":"ｼﾓﾃﾉ","townName":"下手野","zipCode":"6700063"},{"prefectureJisCode":"28","cityJisCode":"28201","townNameKana":"ｼﾓﾃﾞﾗﾏﾁ","townName":"下寺町","zipCode":"6700932"},{"prefectureJisCode":"28","cityJisCode":"28201","townNameKana":"ｼﾗｸﾆ","townName":"白国","zipCode":"6700808"},{"prefectureJisCode":"28","cityJisCode":"28201","townNameKana":"ｼﾗﾊﾏﾁｮｳ","townName":"白浜町","zipCode":"6728023"},{"prefectureJisCode":"28","cityJisCode":"28201","townNameKana":"ｼﾗﾊﾏﾁｮｳｳｻｻﾞｷｷﾀ","townName":"白浜町宇佐崎北","zipCode":"6728013"},{"prefectureJisCode":"28","cityJisCode":"28201","townNameKana":"ｼﾗﾊﾏﾁｮｳｳｻｻﾞｷﾅｶ","townName":"白浜町宇佐崎中","zipCode":"6728021"},{"prefectureJisCode":"28","cityJisCode":"28201","townNameKana":"ｼﾗﾊﾏﾁｮｳｳｻｻﾞｷﾐﾅﾐ","townName":"白浜町宇佐崎南","zipCode":"6728022"},{"prefectureJisCode":"28","cityJisCode":"28201","townNameKana":"ｼﾗﾊﾏﾁｮｳｶﾝﾀﾞ","townName":"白浜町神田","zipCode":"6728011"},{"prefectureJisCode":"28","cityJisCode":"28201","townNameKana":"ｼﾗﾊﾏﾁｮｳｼﾞｹ","townName":"白浜町寺家","zipCode":"6728012"},{"prefectureJisCode":"28","cityJisCode":"28201","townNameKana":"ｼﾗﾊﾏﾁｮｳﾅﾀﾞﾊﾏ","townName":"白浜町灘浜","zipCode":"6728024"},{"prefectureJisCode":"28","cityJisCode":"28201","townNameKana":"ｼﾛｶﾞﾈﾏﾁ","townName":"白銀町","zipCode":"6700902"},{"prefectureJisCode":"28","cityJisCode":"28201","townNameKana":"ｼﾛﾐﾀﾞｲ","townName":"城見台","zipCode":"6700803"},{"prefectureJisCode":"28","cityJisCode":"28201","townNameKana":"ｼﾛﾐﾁｮｳ","townName":"城見町","zipCode":"6700831"},{"prefectureJisCode":"28","cityJisCode":"28201","townNameKana":"ｼﾝｻﾞｲｹ","townName":"新在家","zipCode":"6700095"},{"prefectureJisCode":"28","cityJisCode":"28201","townNameKana":"ｼﾝｻﾞｲｹﾅｶﾉﾁｮｳ","townName":"新在家中の町","zipCode":"6700094"},{"prefectureJisCode":"28","cityJisCode":"28201","townNameKana":"ｼﾝｻﾞｲｹﾎﾝﾁｮｳ","townName":"新在家本町","zipCode":"6700092"},{"prefectureJisCode":"28","cityJisCode":"28201","townNameKana":"ｼﾝﾜﾁｮｳ","townName":"神和町","zipCode":"6700834"},{"prefectureJisCode":"28","cityJisCode":"28201","townNameKana":"ｼﾞｭｳﾆｼｮﾏｴﾁｮｳ","townName":"十二所前町","zipCode":"6700911"},{"prefectureJisCode":"28","cityJisCode":"28201","townNameKana":"ｼﾞｮｳﾄｳﾏﾁ","townName":"城東町","zipCode":"6700841"},{"prefectureJisCode":"28","cityJisCode":"28201","townNameKana":"ｼﾞｮｳﾄｳﾏﾁｷｮｳｸﾞﾁﾀﾞｲ","townName":"城東町京口台","zipCode":"6700845"},{"prefectureJisCode":"28","cityJisCode":"28201","townNameKana":"ｼﾞｮｳﾄｳﾏﾁｺﾞｹﾝﾔ","townName":"城東町五軒屋","zipCode":"6700849"},{"prefectureJisCode":"28","cityJisCode":"28201","townNameKana":"ｼﾞｮｳﾄｳﾏﾁｼﾐｽﾞ","townName":"城東町清水","zipCode":"6700843"},{"prefectureJisCode":"28","cityJisCode":"28201","townNameKana":"ｼﾞｮｳﾄｳﾏﾁﾀｹﾉﾓﾝ","townName":"城東町竹之門","zipCode":"6700848"},{"prefectureJisCode":"28","cityJisCode":"28201","townNameKana":"ｼﾞｮｳﾄｳﾏﾁﾅｶｶﾞﾜﾗ","townName":"城東町中河原","zipCode":"6700847"},{"prefectureJisCode":"28","cityJisCode":"28201","townNameKana":"ｼﾞｮｳﾄｳﾏﾁﾉﾀﾞ","townName":"城東町野田","zipCode":"6700844"},{"prefectureJisCode":"28","cityJisCode":"28201","townNameKana":"ｼﾞｮｳﾄｳﾏﾁﾋﾞｼｬﾓﾝ","townName":"城東町毘沙門","zipCode":"6700842"},{"prefectureJisCode":"28","cityJisCode":"28201","townNameKana":"ｼﾞｮｳﾎｸｼﾝﾏﾁ","townName":"城北新町","zipCode":"6700883"},{"prefectureJisCode":"28","cityJisCode":"28201","townNameKana":"ｼﾞｮｳﾎｸﾎﾝﾁｮｳ","townName":"城北本町","zipCode":"6700884"},{"prefectureJisCode":"28","cityJisCode":"28201","townNameKana":"ｼﾞﾅｲﾏﾁ","townName":"地内町","zipCode":"6700044"},{"prefectureJisCode":"28","cityJisCode":"28201","townNameKana":"ｼﾞﾎｳｼﾞ","townName":"実法寺","zipCode":"6712244"},{"prefectureJisCode":"28","cityJisCode":"28201","townNameKana":"ｽｺﾞｳﾀﾞｲ","townName":"菅生台","zipCode":"6712243"},{"prefectureJisCode":"28","cityJisCode":"28201","townNameKana":"ｿｳｼｬﾎﾝﾏﾁ","townName":"総社本町","zipCode":"6700015"},{"prefectureJisCode":"28","cityJisCode":"28201","townNameKana":"ﾀｲﾀﾞｲ","townName":"田井台","zipCode":"6712211"},{"prefectureJisCode":"28","cityJisCode":"28201","townNameKana":"ﾀｶｵｶｼﾝﾏﾁ","townName":"高岡新町","zipCode":"6700062"},{"prefectureJisCode":"28","cityJisCode":"28201","townNameKana":"ﾀｶｵﾁｮｳ","townName":"高尾町","zipCode":"6700915"},{"prefectureJisCode":"28","cityJisCode":"28201","townNameKana":"ﾀｶｼﾞｮｳﾁｮｳ","townName":"鷹匠町","zipCode":"6700024"},{"prefectureJisCode":"28","cityJisCode":"28201","townNameKana":"ﾀｹﾀﾞﾏﾁ","townName":"竹田町","zipCode":"6700013"},{"prefectureJisCode":"28","cityJisCode":"28201","townNameKana":"ﾀﾂﾉﾏﾁ","townName":"龍野町","zipCode":"6700032"},{"prefectureJisCode":"28","cityJisCode":"28201","townNameKana":"ﾀﾃﾏﾁ","townName":"立町","zipCode":"6700903"},{"prefectureJisCode":"28","cityJisCode":"28201","townNameKana":"ﾀﾃﾞﾗ","townName":"田寺","zipCode":"6700086"},{"prefectureJisCode":"28","cityJisCode":"28201","townNameKana":"ﾀﾃﾞﾗﾋｶﾞｼ","townName":"田寺東","zipCode":"6700081"},{"prefectureJisCode":"28","cityJisCode":"28201","townNameKana":"ﾀﾃﾞﾗﾔﾏﾃﾁｮｳ","townName":"田寺山手町","zipCode":"6700082"},{"prefectureJisCode":"28","cityJisCode":"28201","townNameKana":"ﾀﾏﾃ","townName":"玉手","zipCode":"6700985"},{"prefectureJisCode":"28","cityJisCode":"28201","townNameKana":"ﾀﾞｲｺｸｲｯﾁｮｳﾏﾁ","townName":"大黒壱丁町","zipCode":"6700853"},{"prefectureJisCode":"28","cityJisCode":"28201","townNameKana":"ﾀﾞｲｼﾞｭﾀﾞｲ","townName":"大寿台","zipCode":"6700898"},{"prefectureJisCode":"28","cityJisCode":"28201","townNameKana":"ﾀﾞｲｾﾞﾝﾁｮｳ","townName":"大善町","zipCode":"6700833"},{"prefectureJisCode":"28","cityJisCode":"28201","townNameKana":"ﾁｭｳｼﾞ","townName":"中地","zipCode":"6700976"},{"prefectureJisCode":"28","cityJisCode":"28201","townNameKana":"ﾁｭｳｼﾞﾐﾅﾐﾉﾁｮｳ","townName":"中地南町","zipCode":"6700975"},{"prefectureJisCode":"28","cityJisCode":"28201","townNameKana":"ﾁｮｳﾀﾞ","townName":"町田","zipCode":"6712217"},{"prefectureJisCode":"28","cityJisCode":"28201","townNameKana":"ﾁｮｳﾉﾂﾎﾞ","townName":"町坪","zipCode":"6700984"},{"prefectureJisCode":"28","cityJisCode":"28201","townNameKana":"ﾁｮｳﾉﾂﾎﾞﾐﾅﾐﾏﾁ","townName":"町坪南町","zipCode":"6700989"},{"prefectureJisCode":"28","cityJisCode":"28201","townNameKana":"ﾁﾖﾀﾞﾏﾁ","townName":"千代田町","zipCode":"6700993"},{"prefectureJisCode":"28","cityJisCode":"28201","townNameKana":"ﾂｷﾞ","townName":"継","zipCode":"6728004"},{"prefectureJisCode":"28","cityJisCode":"28201","townNameKana":"ﾂｸﾀﾞﾁｮｳ","townName":"佃町","zipCode":"6728049"},{"prefectureJisCode":"28","cityJisCode":"28201","townNameKana":"ﾂｼﾞｲ","townName":"辻井","zipCode":"6700083"},{"prefectureJisCode":"28","cityJisCode":"28201","townNameKana":"ﾂﾁﾔﾏ","townName":"土山","zipCode":"6700996"},{"prefectureJisCode":"28","cityJisCode":"28201","townNameKana":"ﾂﾁﾔﾏﾋｶﾞｼﾉﾁｮｳ","townName":"土山東の町","zipCode":"6700995"},{"prefectureJisCode":"28","cityJisCode":"28201","townNameKana":"ﾃｶﾞﾗ","townName":"手柄","zipCode":"6700972"},{"prefectureJisCode":"28","cityJisCode":"28201","townNameKana":"ﾃﾝｼﾞﾝﾏﾁ","townName":"天神町","zipCode":"6700846"},{"prefectureJisCode":"28","cityJisCode":"28201","townNameKana":"ﾄｳｺﾞｳﾁｮｳ","townName":"東郷町","zipCode":"6700821"},{"prefectureJisCode":"28","cityJisCode":"28201","townNameKana":"ﾄｳﾌﾏﾁ","townName":"豆腐町","zipCode":"6700914"},{"prefectureJisCode":"28","cityJisCode":"28201","townNameKana":"ﾄﾎﾘ","townName":"砥堀","zipCode":"6700802"},{"prefectureJisCode":"28","cityJisCode":"28201","townNameKana":"ﾄﾏﾐ","townName":"苫編","zipCode":"6700986"},{"prefectureJisCode":"28","cityJisCode":"28201","townNameKana":"ﾄﾏﾐﾐﾅﾐ","townName":"苫編南","zipCode":"6700987"},{"prefectureJisCode":"28","cityJisCode":"28201","townNameKana":"ﾄﾖｻﾞﾜﾁｮｳ","townName":"豊沢町","zipCode":"6700964"},{"prefectureJisCode":"28","cityJisCode":"28201","townNameKana":"ﾄﾖﾄﾐﾁｮｳｶﾌﾞﾄｵｶ","townName":"豊富町甲丘","zipCode":"6792124"},{"prefectureJisCode":"28","cityJisCode":"28201","townNameKana":"ﾄﾖﾄﾐﾁｮｳｺﾀﾞﾆ","townName":"豊富町神谷","zipCode":"6792121"},{"prefectureJisCode":"28","cityJisCode":"28201","townNameKana":"ﾄﾖﾄﾐﾁｮｳﾄﾖﾄﾐ","townName":"豊富町豊富","zipCode":"6792123"},{"prefectureJisCode":"28","cityJisCode":"28201","townNameKana":"ﾄﾖﾄﾐﾁｮｳﾐｶｹﾞ","townName":"豊富町御蔭","zipCode":"6792122"},{"prefectureJisCode":"28","cityJisCode":"28201","townNameKana":"ﾄﾞｳｼﾝﾏﾁ","townName":"同心町","zipCode":"6700856"},{"prefectureJisCode":"28","cityJisCode":"28201","townNameKana":"ﾅｺﾞﾔﾏﾁｮｳ","townName":"名古山町","zipCode":"6700051"},{"prefectureJisCode":"28","cityJisCode":"28201","townNameKana":"ﾅﾝｼﾞｮｳ","townName":"南条","zipCode":"6700952"},{"prefectureJisCode":"28","cityJisCode":"28201","townNameKana":"ﾆｶｲﾏﾁ","townName":"二階町","zipCode":"6700922"},{"prefectureJisCode":"28","cityJisCode":"28201","townNameKana":"ﾆｼｲﾏｼﾞｭｸ","townName":"西今宿","zipCode":"6700061"},{"prefectureJisCode":"28","cityJisCode":"28201","townNameKana":"ﾆｼｴｷﾏｴﾁｮｳ","townName":"西駅前町","zipCode":"6700913"},{"prefectureJisCode":"28","cityJisCode":"28201","townNameKana":"ﾆｼｼﾝｻﾞｲｹ","townName":"西新在家","zipCode":"6700096"},{"prefectureJisCode":"28","cityJisCode":"28201","townNameKana":"ﾆｼｼﾝﾏﾁ","townName":"西新町","zipCode":"6700033"},{"prefectureJisCode":"28","cityJisCode":"28201","townNameKana":"ﾆｼﾀﾞｲｼﾞｭﾀﾞｲ","townName":"西大寿台","zipCode":"6700897"},{"prefectureJisCode":"28","cityJisCode":"28201","townNameKana":"ﾆｼﾅｶｼﾞﾏ","townName":"西中島","zipCode":"6700805"},{"prefectureJisCode":"28","cityJisCode":"28201","townNameKana":"ﾆｼﾆｶｲﾏﾁ","townName":"西二階町","zipCode":"6700901"},{"prefectureJisCode":"28","cityJisCode":"28201","townNameKana":"ﾆｼﾉﾌﾞｽｴ","townName":"西延末","zipCode":"6700971"},{"prefectureJisCode":"28","cityJisCode":"28201","townNameKana":"ﾆｼﾔｼﾛﾁｮｳ","townName":"西八代町","zipCode":"6700876"},{"prefectureJisCode":"28","cityJisCode":"28201","townNameKana":"ﾆｼﾕﾒｻｷﾀﾞｲ","townName":"西夢前台","zipCode":"6712214"},{"prefectureJisCode":"28","cityJisCode":"28201","townNameKana":"ﾆｼﾜｷ","townName":"西脇","zipCode":"6712234"},{"prefectureJisCode":"28","cityJisCode":"28201","townNameKana":"ﾆﾌﾞﾉ","townName":"仁豊野","zipCode":"6700801"},{"prefectureJisCode":"28","cityJisCode":"28201","townNameKana":"ﾉｳﾆﾝﾏﾁ","townName":"農人町","zipCode":"6700038"},{"prefectureJisCode":"28","cityJisCode":"28201","townNameKana":"ﾉｳﾈﾝﾁｮｳ","townName":"南畝町","zipCode":"6700961"},{"prefectureJisCode":"28","cityJisCode":"28201","townNameKana":"ﾉｻﾞﾄ","townName":"野里","zipCode":"6700811"},{"prefectureJisCode":"28","cityJisCode":"28201","townNameKana":"ﾉｻﾞﾄｳｴﾉﾁｮｳ","townName":"野里上野町","zipCode":"6700814"},{"prefectureJisCode":"28","cityJisCode":"28201","townNameKana":"ﾉｻﾞﾄｹｲｳﾝｼﾞﾏｴﾁｮｳ","townName":"野里慶雲寺前町","zipCode":"6700813"},{"prefectureJisCode":"28","cityJisCode":"28201","townNameKana":"ﾉｻﾞﾄｼﾝﾏﾁ","townName":"野里新町","zipCode":"6700862"},{"prefectureJisCode":"28","cityJisCode":"28201","townNameKana":"ﾉｻﾞﾄﾂｷｵｶﾏﾁ","townName":"野里月丘町","zipCode":"6700865"},{"prefectureJisCode":"28","cityJisCode":"28201","townNameKana":"ﾉｻﾞﾄﾃﾗﾏﾁ","townName":"野里寺町","zipCode":"6700867"},{"prefectureJisCode":"28","cityJisCode":"28201","townNameKana":"ﾉｻﾞﾄﾅｶﾏﾁ","townName":"野里中町","zipCode":"6700864"},{"prefectureJisCode":"28","cityJisCode":"28201","townNameKana":"ﾉｻﾞﾄﾋｶﾞｼﾄﾞｳｼﾝﾏﾁ","townName":"野里東同心町","zipCode":"6700863"},{"prefectureJisCode":"28","cityJisCode":"28201","townNameKana":"ﾉｻﾞﾄﾋｶﾞｼﾏﾁ","townName":"野里東町","zipCode":"6700861"},{"prefectureJisCode":"28","cityJisCode":"28201","townNameKana":"ﾉｻﾞﾄﾎﾘﾄﾞﾒﾏﾁ","townName":"野里堀留町","zipCode":"6700866"},{"prefectureJisCode":"28","cityJisCode":"28201","townNameKana":"ﾉｻﾞﾄﾔﾏﾄﾁｮｳ","townName":"野里大和町","zipCode":"6700815"},{"prefectureJisCode":"28","cityJisCode":"28201","townNameKana":"ﾉﾌﾞｽｴ","townName":"延末","zipCode":"6700966"},{"prefectureJisCode":"28","cityJisCode":"28201","townNameKana":"ﾊｸﾁｮｳﾀﾞｲ","townName":"白鳥台","zipCode":"6712245"},{"prefectureJisCode":"28","cityJisCode":"28201","townNameKana":"ﾊｼﾉﾏﾁ","townName":"橋之町","zipCode":"6700008"},{"prefectureJisCode":"28","cityJisCode":"28201","townNameKana":"ﾊﾅｶｹﾞﾁｮｳ","townName":"花影町","zipCode":"6700047"},{"prefectureJisCode":"28","cityJisCode":"28201","townNameKana":"ﾊﾅﾀﾞﾁｮｳｲｯﾎﾟﾝﾏﾂ","townName":"花田町一本松","zipCode":"6710253"},{"prefectureJisCode":"28","cityJisCode":"28201","townNameKana":"ﾊﾅﾀﾞﾁｮｳｵｶﾞﾜ","townName":"花田町小川","zipCode":"6710255"},{"prefectureJisCode":"28","cityJisCode":"28201","townNameKana":"ﾊﾅﾀﾞﾁｮｳｶﾉｳﾊﾗﾀﾞ","townName":"花田町加納原田","zipCode":"6710252"},{"prefectureJisCode":"28","cityJisCode":"28201","townNameKana":"ﾊﾅﾀﾞﾁｮｳｶﾐﾊﾗﾀﾞ","townName":"花田町上原田","zipCode":"6710251"},{"prefectureJisCode":"28","cityJisCode":"28201","townNameKana":"ﾊﾅﾀﾞﾁｮｳﾀｶｷﾞ","townName":"花田町高木","zipCode":"6710256"},{"prefectureJisCode":"28","cityJisCode":"28201","townNameKana":"ﾊﾅﾀﾞﾁｮｳﾁｮｸｼ","townName":"花田町勅旨","zipCode":"6710254"},{"prefectureJisCode":"28","cityJisCode":"28201","townNameKana":"ﾊﾔｼﾀﾞﾁｮｳｵｵﾂﾞﾂﾐ","townName":"林田町大堤","zipCode":"6794231"},{"prefectureJisCode":"28","cityJisCode":"28201","townNameKana":"ﾊﾔｼﾀﾞﾁｮｳｵｸｻﾐ","townName":"林田町奥佐見","zipCode":"6794223"},{"prefectureJisCode":"28","cityJisCode":"28201","townNameKana":"ﾊﾔｼﾀﾞﾁｮｳｶﾐｲｾ","townName":"林田町上伊勢","zipCode":"6794232"},{"prefectureJisCode":"28","cityJisCode":"28201","townNameKana":"ﾊﾔｼﾀﾞﾁｮｳｶﾐｶﾏｴ","townName":"林田町上構","zipCode":"6794204"},{"prefectureJisCode":"28","cityJisCode":"28201","townNameKana":"ﾊﾔｼﾀﾞﾁｮｳｸﾁｻﾐ","townName":"林田町口佐見","zipCode":"6794222"},{"prefectureJisCode":"28","cityJisCode":"28201","townNameKana":"ﾊﾔｼﾀﾞﾁｮｳｸﾎﾞ","townName":"林田町久保","zipCode":"6794201"},{"prefectureJisCode":"28","cityJisCode":"28201","townNameKana":"ﾊﾔｼﾀﾞﾁｮｳｼﾓｲｾ","townName":"林田町下伊勢","zipCode":"6794233"},{"prefectureJisCode":"28","cityJisCode":"28201","townNameKana":"ﾊﾔｼﾀﾞﾁｮｳｼﾓｶﾏｴ","townName":"林田町下構","zipCode":"6794202"},{"prefectureJisCode":"28","cityJisCode":"28201","townNameKana":"ﾊﾔｼﾀﾞﾁｮｳｼﾝﾏﾁ","townName":"林田町新町","zipCode":"6794205"},{"prefectureJisCode":"28","cityJisCode":"28201","townNameKana":"ﾊﾔｼﾀﾞﾁｮｳﾅｶｶﾏｴ","townName":"林田町中構","zipCode":"6794203"},{"prefectureJisCode":"28","cityJisCode":"28201","townNameKana":"ﾊﾔｼﾀﾞﾁｮｳﾅｶﾔﾏｼﾀ","townName":"林田町中山下","zipCode":"6794214"},{"prefectureJisCode":"28","cityJisCode":"28201","townNameKana":"ﾊﾔｼﾀﾞﾁｮｳﾊﾔｼﾀﾞ","townName":"林田町林田","zipCode":"6794206"},{"prefectureJisCode":"28","cityJisCode":"28201","townNameKana":"ﾊﾔｼﾀﾞﾁｮｳﾊﾔｼﾀﾞﾆ","townName":"林田町林谷","zipCode":"6794221"},{"prefectureJisCode":"28","cityJisCode":"28201","townNameKana":"ﾊﾔｼﾀﾞﾁｮｳﾏﾂﾔﾏ","townName":"林田町松山","zipCode":"6794212"},{"prefectureJisCode":"28","cityJisCode":"28201","townNameKana":"ﾊﾔｼﾀﾞﾁｮｳﾑｸﾀﾞﾆ","townName":"林田町六九谷","zipCode":"6794211"},{"prefectureJisCode":"28","cityJisCode":"28201","townNameKana":"ﾊﾔｼﾀﾞﾁｮｳﾔﾊﾀ","townName":"林田町八幡","zipCode":"6794215"},{"prefectureJisCode":"28","cityJisCode":"28201","townNameKana":"ﾊﾔｼﾀﾞﾁｮｳﾔﾏﾀﾞ","townName":"林田町山田","zipCode":"6794213"},{"prefectureJisCode":"28","cityJisCode":"28201","townNameKana":"ﾊﾞｸﾛｳﾏﾁ","townName":"博労町","zipCode":"6700906"},{"prefectureJisCode":"28","cityJisCode":"28201","townNameKana":"ﾋｶﾞｼｲﾏｼﾞｭｸ","townName":"東今宿","zipCode":"6700056"},{"prefectureJisCode":"28","cityJisCode":"28201","townNameKana":"ﾋｶﾞｼｴｷﾏｴﾁｮｳ","townName":"東駅前町","zipCode":"6700926"},{"prefectureJisCode":"28","cityJisCode":"28201","townNameKana":"ﾋｶﾞｼﾂｼﾞｲ","townName":"東辻井","zipCode":"6700084"},{"prefectureJisCode":"28","cityJisCode":"28201","townNameKana":"ﾋｶﾞｼﾉﾌﾞｽｴ","townName":"東延末","zipCode":"6700965"},{"prefectureJisCode":"28","cityJisCode":"28201","townNameKana":"ﾋｶﾞｼﾔﾏ","townName":"東山","zipCode":"6728014"},{"prefectureJisCode":"28","cityJisCode":"28201","townNameKana":"ﾋｶﾞｼﾕﾒｻｷﾀﾞｲ","townName":"東夢前台","zipCode":"6700064"},{"prefectureJisCode":"28","cityJisCode":"28201","townNameKana":"ﾋﾉﾃﾞﾁｮｳ","townName":"日出町","zipCode":"6700942"},{"prefectureJisCode":"28","cityJisCode":"28201","townNameKana":"ﾋﾗﾉﾏﾁ","townName":"平野町","zipCode":"6700933"},{"prefectureJisCode":"28","cityJisCode":"28201","townNameKana":"ﾋﾛﾊﾀｸｱﾂﾞﾏﾁｮｳ","townName":"広畑区吾妻町","zipCode":"6711154"},{"prefectureJisCode":"28","cityJisCode":"28201","townNameKana":"ﾋﾛﾊﾀｸｵｵﾏﾁ","townName":"広畑区大町","zipCode":"6711155"},{"prefectureJisCode":"28","cityJisCode":"28201","townNameKana":"ﾋﾛﾊﾀｸｶﾏﾀﾞ","townName":"広畑区蒲田","zipCode":"6711102"},{"prefectureJisCode":"28","cityJisCode":"28201","townNameKana":"ﾋﾛﾊﾀｸｷｮｳﾐﾁｮｳ","townName":"広畑区京見町","zipCode":"6711106"},{"prefectureJisCode":"28","cityJisCode":"28201","townNameKana":"ﾋﾛﾊﾀｸｷﾀｶﾜﾗﾁｮｳ","townName":"広畑区北河原町","zipCode":"6711111"},{"prefectureJisCode":"28","cityJisCode":"28201","townNameKana":"ﾋﾛﾊﾀｸｷﾀﾉﾁｮｳ","townName":"広畑区北野町","zipCode":"6711112"},{"prefectureJisCode":"28","cityJisCode":"28201","townNameKana":"ﾋﾛﾊﾀｸｺｻｶ","townName":"広畑区小坂","zipCode":"6711156"},{"prefectureJisCode":"28","cityJisCode":"28201","townNameKana":"ﾋﾛﾊﾀｸｺﾏﾂﾁｮｳ","townName":"広畑区小松町","zipCode":"6711152"},{"prefectureJisCode":"28","cityJisCode":"28201","townNameKana":"ﾋﾛﾊﾀｸｻｲ","townName":"広畑区才","zipCode":"6711104"},{"prefectureJisCode":"28","cityJisCode":"28201","townNameKana":"ﾋﾛﾊﾀｸｼﾐｽﾞﾁｮｳ","townName":"広畑区清水町","zipCode":"6711113"},{"prefectureJisCode":"28","cityJisCode":"28201","townNameKana":"ﾋﾛﾊﾀｸｼﾛﾔﾏﾁｮｳ","townName":"広畑区城山町","zipCode":"6711108"},{"prefectureJisCode":"28","cityJisCode":"28201","townNameKana":"ﾋﾛﾊﾀｸｽｴﾋﾛﾁｮｳ","townName":"広畑区末広町","zipCode":"6711115"},{"prefectureJisCode":"28","cityJisCode":"28201","townNameKana":"ﾋﾛﾊﾀｸｾｲﾓﾝﾄﾞｵﾘ","townName":"広畑区正門通","zipCode":"6711116"},{"prefectureJisCode":"28","cityJisCode":"28201","townNameKana":"ﾋﾛﾊﾀｸﾀｶﾊﾏﾁｮｳ","townName":"広畑区高浜町","zipCode":"6711153"},{"prefectureJisCode":"28","cityJisCode":"28201","townNameKana":"ﾋﾛﾊﾀｸﾂﾙﾏﾁ","townName":"広畑区鶴町","zipCode":"6711124"},{"prefectureJisCode":"28","cityJisCode":"28201","townNameKana":"ﾋﾛﾊﾀｸﾅｶﾞﾏﾁ","townName":"広畑区長町","zipCode":"6711125"},{"prefectureJisCode":"28","cityJisCode":"28201","townNameKana":"ﾋﾛﾊﾀｸﾆｼｶﾏﾀﾞ","townName":"広畑区西蒲田","zipCode":"6711107"},{"prefectureJisCode":"28","cityJisCode":"28201","townNameKana":"ﾋﾛﾊﾀｸﾆｼﾕﾒｻｷﾀﾞｲ","townName":"広畑区西夢前台","zipCode":"6711103"},{"prefectureJisCode":"28","cityJisCode":"28201","townNameKana":"ﾋﾛﾊﾀｸﾉﾘﾅｵ","townName":"広畑区則直","zipCode":"6711105"},{"prefectureJisCode":"28","cityJisCode":"28201","townNameKana":"ﾋﾛﾊﾀｸﾊﾔｾﾁｮｳ","townName":"広畑区早瀬町","zipCode":"6711151"},{"prefectureJisCode":"28","cityJisCode":"28201","townNameKana":"ﾋﾛﾊﾀｸﾋｶﾞｼｼﾝﾏﾁ","townName":"広畑区東新町","zipCode":"6711121"},{"prefectureJisCode":"28","cityJisCode":"28201","townNameKana":"ﾋﾛﾊﾀｸﾋｶﾞｼﾕﾒｻｷﾀﾞｲ","townName":"広畑区東夢前台","zipCode":"6711101"},{"prefectureJisCode":"28","cityJisCode":"28201","townNameKana":"ﾋﾛﾊﾀｸﾌｼﾞﾁｮｳ","townName":"広畑区富士町","zipCode":"6711123"},{"prefectureJisCode":"28","cityJisCode":"28201","townNameKana":"ﾋﾛﾊﾀｸﾎﾝﾏﾁ","townName":"広畑区本町","zipCode":"6711114"},{"prefectureJisCode":"28","cityJisCode":"28201","townNameKana":"ﾋﾛﾊﾀｸﾕﾒｻｷﾁｮｳ","townName":"広畑区夢前町","zipCode":"6711122"},{"prefectureJisCode":"28","cityJisCode":"28201","townNameKana":"ﾋﾛﾐﾈ","townName":"広峰","zipCode":"6700882"},{"prefectureJisCode":"28","cityJisCode":"28201","townNameKana":"ﾋﾛﾐﾈﾔﾏ","townName":"広嶺山","zipCode":"6700891"},{"prefectureJisCode":"28","cityJisCode":"28201","townNameKana":"ﾌｸｲﾏﾁ","townName":"福居町","zipCode":"6700855"},{"prefectureJisCode":"28","cityJisCode":"28201","townNameKana":"ﾌｸｻﾞﾜﾁｮｳ","townName":"福沢町","zipCode":"6700992"},{"prefectureJisCode":"28","cityJisCode":"28201","townNameKana":"ﾌｸﾅｶﾏﾁ","townName":"福中町","zipCode":"6700017"},{"prefectureJisCode":"28","cityJisCode":"28201","townNameKana":"ﾌｸﾓﾄﾏﾁ","townName":"福本町","zipCode":"6700004"},{"prefectureJisCode":"28","cityJisCode":"28201","townNameKana":"ﾌｼﾞｶﾞﾀﾞｲ","townName":"藤ケ台","zipCode":"6700066"},{"prefectureJisCode":"28","cityJisCode":"28201","townNameKana":"ﾌﾀﾊﾞﾁｮｳ","townName":"双葉町","zipCode":"6700832"},{"prefectureJisCode":"28","cityJisCode":"28201","townNameKana":"ﾌﾅｵｶﾁｮｳ","townName":"船丘町","zipCode":"6700034"},{"prefectureJisCode":"28","cityJisCode":"28201","townNameKana":"ﾌﾅﾂﾁｮｳ","townName":"船津町","zipCode":"6792101"},{"prefectureJisCode":"28","cityJisCode":"28201","townNameKana":"ﾌﾅﾊｼﾁｮｳ","townName":"船橋町","zipCode":"6700048"},{"prefectureJisCode":"28","cityJisCode":"28201","townNameKana":"ﾍﾞｯｼｮﾁｮｳｶｸﾞﾏﾁ","townName":"別所町家具町","zipCode":"6710225"},{"prefectureJisCode":"28","cityJisCode":"28201","townNameKana":"ﾍﾞｯｼｮﾁｮｳｷﾀｼﾞｭｸ","townName":"別所町北宿","zipCode":"6710223"},{"prefectureJisCode":"28","cityJisCode":"28201","townNameKana":"ﾍﾞｯｼｮﾁｮｳｺﾊﾞﾔｼ","townName":"別所町小林","zipCode":"6710222"},{"prefectureJisCode":"28","cityJisCode":"28201","townNameKana":"ﾍﾞｯｼｮﾁｮｳｻﾂﾞﾁ","townName":"別所町佐土","zipCode":"6710224"},{"prefectureJisCode":"28","cityJisCode":"28201","townNameKana":"ﾍﾞｯｼｮﾁｮｳｻﾂﾞﾁｼﾝ","townName":"別所町佐土新","zipCode":"6710226"},{"prefectureJisCode":"28","cityJisCode":"28201","townNameKana":"ﾍﾞｯｼｮﾁｮｳﾍﾞｯｼｮ","townName":"別所町別所","zipCode":"6710221"},{"prefectureJisCode":"28","cityJisCode":"28201","townNameKana":"ﾎｳｼﾛ","townName":"保城","zipCode":"6700804"},{"prefectureJisCode":"28","cityJisCode":"28201","townNameKana":"ﾎｳｼﾞｮｳ","townName":"北条","zipCode":"6700947"},{"prefectureJisCode":"28","cityJisCode":"28201","townNameKana":"ﾎｳｼﾞｮｳｳﾒﾊﾗﾁｮｳ","townName":"北条梅原町","zipCode":"6700945"},{"prefectureJisCode":"28","cityJisCode":"28201","townNameKana":"ﾎｳｼﾞｮｳｸﾞﾁ","townName":"北条口","zipCode":"6700935"},{"prefectureJisCode":"28","cityJisCode":"28201","townNameKana":"ﾎｳｼﾞｮｳﾅｶﾞﾗﾁｮｳ","townName":"北条永良町","zipCode":"6700946"},{"prefectureJisCode":"28","cityJisCode":"28201","townNameKana":"ﾎｳｼﾞｮｳﾐﾔﾉﾏﾁ","townName":"北条宮の町","zipCode":"6700948"},{"prefectureJisCode":"28","cityJisCode":"28201","townNameKana":"ﾎｳﾅﾝﾁｮｳ","townName":"峰南町","zipCode":"6700881"},{"prefectureJisCode":"28","cityJisCode":"28201","townNameKana":"ﾎﾝﾏﾁ","townName":"本町","zipCode":"6700012"},{"prefectureJisCode":"28","cityJisCode":"28201","townNameKana":"ﾎﾞｳｽﾞﾏﾁ","townName":"坊主町","zipCode":"6700011"},{"prefectureJisCode":"28","cityJisCode":"28201","townNameKana":"ﾏｽｲｼﾝﾏﾁ","townName":"増位新町","zipCode":"6700806"},{"prefectureJisCode":"28","cityJisCode":"28201","townNameKana":"ﾏｽｲﾎﾝﾏﾁ","townName":"増位本町","zipCode":"6700807"},{"prefectureJisCode":"28","cityJisCode":"28201","townNameKana":"ﾏﾄｶﾞﾀﾁｮｳﾌｸﾄﾞﾏﾘ","townName":"的形町福泊","zipCode":"6710112"},{"prefectureJisCode":"28","cityJisCode":"28201","townNameKana":"ﾏﾄｶﾞﾀﾁｮｳﾏﾄｶﾞﾀ","townName":"的形町的形","zipCode":"6710111"},{"prefectureJisCode":"28","cityJisCode":"28201","townNameKana":"ﾏﾙｵﾁｮｳ","townName":"丸尾町","zipCode":"6700827"},{"prefectureJisCode":"28","cityJisCode":"28201","townNameKana":"ﾐｸﾆﾉﾁｮｳｺｸﾌﾞﾝｼﾞ","townName":"御国野町国分寺","zipCode":"6710234"},{"prefectureJisCode":"28","cityJisCode":"28201","townNameKana":"ﾐｸﾆﾉﾁｮｳｺﾞﾁｬｸ","townName":"御国野町御着","zipCode":"6710232"},{"prefectureJisCode":"28","cityJisCode":"28201","townNameKana":"ﾐｸﾆﾉﾁｮｳﾆｼｺﾞﾁｬｸ","townName":"御国野町西御着","zipCode":"6710233"},{"prefectureJisCode":"28","cityJisCode":"28201","townNameKana":"ﾐｸﾆﾉﾁｮｳﾌｶｼﾉ","townName":"御国野町深志野","zipCode":"6710231"},{"prefectureJisCode":"28","cityJisCode":"28201","townNameKana":"ﾐｺｵｶﾏｴ","townName":"神子岡前","zipCode":"6700055"},{"prefectureJisCode":"28","cityJisCode":"28201","townNameKana":"ﾐﾀﾁｷﾀ","townName":"御立北","zipCode":"6700071"},{"prefectureJisCode":"28","cityJisCode":"28201","townNameKana":"ﾐﾀﾁﾅｶ","townName":"御立中","zipCode":"6700073"},{"prefectureJisCode":"28","cityJisCode":"28201","townNameKana":"ﾐﾀﾁﾆｼ","townName":"御立西","zipCode":"6700074"},{"prefectureJisCode":"28","cityJisCode":"28201","townNameKana":"ﾐﾀﾁﾋｶﾞｼ","townName":"御立東","zipCode":"6700072"},{"prefectureJisCode":"28","cityJisCode":"28201","townNameKana":"ﾐﾄﾞﾘﾀﾞｲ","townName":"緑台","zipCode":"6712247"},{"prefectureJisCode":"28","cityJisCode":"28201","townNameKana":"ﾐﾅﾐｲﾏｼﾞｭｸ","townName":"南今宿","zipCode":"6700054"},{"prefectureJisCode":"28","cityJisCode":"28201","townNameKana":"ﾐﾅﾐｴｷﾏｴﾁｮｳ","townName":"南駅前町","zipCode":"6700962"},{"prefectureJisCode":"28","cityJisCode":"28201","townNameKana":"ﾐﾅﾐｸﾙﾏｻﾞｷ","townName":"南車崎","zipCode":"6700053"},{"prefectureJisCode":"28","cityJisCode":"28201","townNameKana":"ﾐﾅﾐｼﾝｻﾞｲｹ","townName":"南新在家","zipCode":"6700093"},{"prefectureJisCode":"28","cityJisCode":"28201","townNameKana":"ﾐﾅﾐﾏﾁ","townName":"南町","zipCode":"6700912"},{"prefectureJisCode":"28","cityJisCode":"28201","townNameKana":"ﾐﾅﾐﾔｼﾛﾁｮｳ","townName":"南八代町","zipCode":"6700875"},{"prefectureJisCode":"28","cityJisCode":"28201","townNameKana":"ﾐﾔｳｴﾁｮｳ","townName":"宮上町","zipCode":"6700823"},{"prefectureJisCode":"28","cityJisCode":"28201","townNameKana":"ﾐﾔﾆｼﾁｮｳ","townName":"宮西町","zipCode":"6700837"},{"prefectureJisCode":"28","cityJisCode":"28201","townNameKana":"ﾑﾂﾐﾁｮｳ","townName":"睦町","zipCode":"6700812"},{"prefectureJisCode":"28","cityJisCode":"28201","townNameKana":"ﾓﾄｼｵﾏﾁ","townName":"元塩町","zipCode":"6700937"},{"prefectureJisCode":"28","cityJisCode":"28201","townNameKana":"ﾓﾄﾏﾁ","townName":"元町","zipCode":"6700049"},{"prefectureJisCode":"28","cityJisCode":"28201","townNameKana":"ﾔｶ","townName":"八家","zipCode":"6728015"},{"prefectureJisCode":"28","cityJisCode":"28201","townNameKana":"ﾔｷﾞﾏﾁ","townName":"八木町","zipCode":"6700006"},{"prefectureJisCode":"28","cityJisCode":"28201","townNameKana":"ﾔｼﾛ","townName":"八代","zipCode":"6700872"},{"prefectureJisCode":"28","cityJisCode":"28201","townNameKana":"ﾔｼﾛﾄｳｺｳｼﾞﾁｮｳ","townName":"八代東光寺町","zipCode":"6700873"},{"prefectureJisCode":"28","cityJisCode":"28201","townNameKana":"ﾔｼﾛﾎﾝﾁｮｳ","townName":"八代本町","zipCode":"6700874"},{"prefectureJisCode":"28","cityJisCode":"28201","townNameKana":"ﾔｼﾛﾐﾄﾞﾘｶﾞｵｶﾁｮｳ","townName":"八代緑ケ丘町","zipCode":"6700886"},{"prefectureJisCode":"28","cityJisCode":"28201","townNameKana":"ﾔｼﾛﾐﾔﾏｴﾁｮｳ","townName":"八代宮前町","zipCode":"6700885"},{"prefectureJisCode":"28","cityJisCode":"28201","townNameKana":"ﾔｽﾀﾞ","townName":"安田","zipCode":"6700955"},{"prefectureJisCode":"28","cityJisCode":"28201","townNameKana":"ﾔｽﾄﾐﾁｮｳｱﾝｼﾞ","townName":"安富町安志","zipCode":"6712401"},{"prefectureJisCode":"28","cityJisCode":"28201","townNameKana":"ﾔｽﾄﾐﾁｮｳｳｴｷﾉ","townName":"安富町植木野","zipCode":"6712426"},{"prefectureJisCode":"28","cityJisCode":"28201","townNameKana":"ﾔｽﾄﾐﾁｮｳｼｵﾉ","townName":"安富町塩野","zipCode":"6712422"},{"prefectureJisCode":"28","cityJisCode":"28201","townNameKana":"ﾔｽﾄﾐﾁｮｳｽｴﾋﾛ","townName":"安富町末広","zipCode":"6712413"},{"prefectureJisCode":"28","cityJisCode":"28201","townNameKana":"ﾔｽﾄﾐﾁｮｳｾｶﾞﾜ","townName":"安富町瀬川","zipCode":"6712424"},{"prefectureJisCode":"28","cityJisCode":"28201","townNameKana":"ﾔｽﾄﾐﾁｮｳｾｷ","townName":"安富町関","zipCode":"6712416"},{"prefectureJisCode":"28","cityJisCode":"28201","townNameKana":"ﾔｽﾄﾐﾁｮｳｾﾊﾞﾄ","townName":"安富町狭戸","zipCode":"6712423"},{"prefectureJisCode":"28","cityJisCode":"28201","townNameKana":"ﾔｽﾄﾐﾁｮｳﾄﾁﾊﾗ","townName":"安富町杤原","zipCode":"6712414"},{"prefectureJisCode":"28","cityJisCode":"28201","townNameKana":"ﾔｽﾄﾐﾁｮｳﾅｶﾞﾉ","townName":"安富町長野","zipCode":"6712421"},{"prefectureJisCode":"28","cityJisCode":"28201","townNameKana":"ﾔｽﾄﾐﾁｮｳﾅｻｶ","townName":"安富町名坂","zipCode":"6712412"},{"prefectureJisCode":"28","cityJisCode":"28201","townNameKana":"ﾔｽﾄﾐﾁｮｳﾐｻｶ","townName":"安富町三坂","zipCode":"6712425"},{"prefectureJisCode":"28","cityJisCode":"28201","townNameKana":"ﾔｽﾄﾐﾁｮｳﾐﾂﾓﾘ","townName":"安富町三森","zipCode":"6712411"},{"prefectureJisCode":"28","cityJisCode":"28201","townNameKana":"ﾔｽﾄﾐﾁｮｳﾐﾅｺﾞ","townName":"安富町皆河","zipCode":"6712415"},{"prefectureJisCode":"28","cityJisCode":"28201","townNameKana":"ﾔﾅｷﾞﾏﾁ","townName":"柳町","zipCode":"6700023"},{"prefectureJisCode":"28","cityJisCode":"28201","townNameKana":"ﾔﾏﾀﾞﾁｮｳｷﾀﾔﾏﾀﾞ","townName":"山田町北山田","zipCode":"6792112"},{"prefectureJisCode":"28","cityJisCode":"28201","townNameKana":"ﾔﾏﾀﾞﾁｮｳﾀﾀﾞ","townName":"山田町多田","zipCode":"6792111"},{"prefectureJisCode":"28","cityJisCode":"28201","townNameKana":"ﾔﾏﾀﾞﾁｮｳﾆｼﾔﾏﾀﾞ","townName":"山田町西山田","zipCode":"6792115"},{"prefectureJisCode":"28","cityJisCode":"28201","townNameKana":"ﾔﾏﾀﾞﾁｮｳﾏｷﾉ","townName":"山田町牧野","zipCode":"6792114"},{"prefectureJisCode":"28","cityJisCode":"28201","townNameKana":"ﾔﾏﾀﾞﾁｮｳﾐﾅﾐﾔﾏﾀﾞ","townName":"山田町南山田","zipCode":"6792113"},{"prefectureJisCode":"28","cityJisCode":"28201","townNameKana":"ﾔﾏﾉｲﾁｮｳ","townName":"山野井町","zipCode":"6700021"},{"prefectureJisCode":"28","cityJisCode":"28201","townNameKana":"ﾔﾏﾊﾀｼﾝﾃﾞﾝ","townName":"山畑新田","zipCode":"6700036"},{"prefectureJisCode":"28","cityJisCode":"28201","townNameKana":"ﾔﾏﾌﾞｷ","townName":"山吹","zipCode":"6700085"},{"prefectureJisCode":"28","cityJisCode":"28201","townNameKana":"ﾕﾒｻｷﾁｮｳｱｼﾀﾞ","townName":"夢前町芦田","zipCode":"6712133"},{"prefectureJisCode":"28","cityJisCode":"28201","townNameKana":"ﾕﾒｻｷﾁｮｳｱｿﾞﾉ","townName":"夢前町莇野","zipCode":"6712106"},{"prefectureJisCode":"28","cityJisCode":"28201","townNameKana":"ﾕﾒｻｷﾁｮｳｲﾄﾀ","townName":"夢前町糸田","zipCode":"6712114"},{"prefectureJisCode":"28","cityJisCode":"28201","townNameKana":"ﾕﾒｻｷﾁｮｳｵｷﾓﾄ","townName":"夢前町置本","zipCode":"6712122"},{"prefectureJisCode":"28","cityJisCode":"28201","townNameKana":"ﾕﾒｻｷﾁｮｳｺｳﾁｮｳ","townName":"夢前町高長","zipCode":"6712117"},{"prefectureJisCode":"28","cityJisCode":"28201","townNameKana":"ﾕﾒｻｷﾁｮｳｺｾﾊﾞﾀ","townName":"夢前町古瀬畑","zipCode":"6712132"},{"prefectureJisCode":"28","cityJisCode":"28201","townNameKana":"ﾕﾒｻｷﾁｮｳｺﾁﾉｼｮｳ","townName":"夢前町古知之庄","zipCode":"6712113"},{"prefectureJisCode":"28","cityJisCode":"28201","townNameKana":"ﾕﾒｻｷﾁｮｳｺﾉｸｻ","townName":"夢前町神種","zipCode":"6712105"},{"prefectureJisCode":"28","cityJisCode":"28201","townNameKana":"ﾕﾒｻｷﾁｮｳｺﾞｼﾞ","townName":"夢前町護持","zipCode":"6712136"},{"prefectureJisCode":"28","cityJisCode":"28201","townNameKana":"ﾕﾒｻｷﾁｮｳｼｵﾀ","townName":"夢前町塩田","zipCode":"6712112"},{"prefectureJisCode":"28","cityJisCode":"28201","townNameKana":"ﾕﾒｻｷﾁｮｳｼﾝｼﾞｮｳ","townName":"夢前町新庄","zipCode":"6712102"},{"prefectureJisCode":"28","cityJisCode":"28201","townNameKana":"ﾕﾒｻｷﾁｮｳｽｷﾞﾉｳﾁ","townName":"夢前町杉之内","zipCode":"6712111"},{"prefectureJisCode":"28","cityJisCode":"28201","townNameKana":"ﾕﾒｻｷﾁｮｳｽｺﾞｳﾀﾞﾆ","townName":"夢前町菅生澗","zipCode":"6712134"},{"prefectureJisCode":"28","cityJisCode":"28201","townNameKana":"ﾕﾒｻｷﾁｮｳﾀﾏﾀﾞ","townName":"夢前町玉田","zipCode":"6712124"},{"prefectureJisCode":"28","cityJisCode":"28201","townNameKana":"ﾕﾒｻｷﾁｮｳﾂｶﾓﾄ","townName":"夢前町塚本","zipCode":"6712135"},{"prefectureJisCode":"28","cityJisCode":"28201","townNameKana":"ﾕﾒｻｷﾁｮｳﾃﾗ","townName":"夢前町寺","zipCode":"6712116"},{"prefectureJisCode":"28","cityJisCode":"28201","townNameKana":"ﾕﾒｻｷﾁｮｳﾄｸﾗ","townName":"夢前町戸倉","zipCode":"6712131"},{"prefectureJisCode":"28","cityJisCode":"28201","townNameKana":"ﾕﾒｻｷﾁｮｳﾉﾊﾞﾀｹ","townName":"夢前町野畑","zipCode":"6712137"},{"prefectureJisCode":"28","cityJisCode":"28201","townNameKana":"ﾕﾒｻｷﾁｮｳﾏｴﾉｼｮｳ","townName":"夢前町前之庄","zipCode":"6712103"},{"prefectureJisCode":"28","cityJisCode":"28201","townNameKana":"ﾕﾒｻｷﾁｮｳﾏﾀｻｶ","townName":"夢前町又坂","zipCode":"6712115"},{"prefectureJisCode":"28","cityJisCode":"28201","townNameKana":"ﾕﾒｻｷﾁｮｳﾐﾔｵｷ","townName":"夢前町宮置","zipCode":"6712121"},{"prefectureJisCode":"28","cityJisCode":"28201","townNameKana":"ﾕﾒｻｷﾁｮｳﾔﾏﾄﾐ","townName":"夢前町山冨","zipCode":"6712123"},{"prefectureJisCode":"28","cityJisCode":"28201","townNameKana":"ﾕﾒｻｷﾁｮｳﾔﾏﾉｳﾁ","townName":"夢前町山之内","zipCode":"6712101"},{"prefectureJisCode":"28","cityJisCode":"28201","townNameKana":"ﾖｼﾀﾞﾏﾁ","townName":"吉田町","zipCode":"6700031"},{"prefectureJisCode":"28","cityJisCode":"28201","townNameKana":"ﾖﾈﾀﾞﾏﾁ","townName":"米田町","zipCode":"6700042"},{"prefectureJisCode":"28","cityJisCode":"28201","townNameKana":"ﾖﾍﾞｸｶﾐｶﾞﾜﾗ","townName":"余部区上川原","zipCode":"6711263"},{"prefectureJisCode":"28","cityJisCode":"28201","townNameKana":"ﾖﾍﾞｸｶﾐﾖﾍﾞ","townName":"余部区上余部","zipCode":"6711262"},{"prefectureJisCode":"28","cityJisCode":"28201","townNameKana":"ﾖﾍﾞｸｼﾓﾖﾍﾞ","townName":"余部区下余部","zipCode":"6711261"},{"prefectureJisCode":"28","cityJisCode":"28201","townNameKana":"ﾛｯｶｸ","townName":"六角","zipCode":"6712242"},{"prefectureJisCode":"28","cityJisCode":"28201","townNameKana":"ﾜｶﾅﾁｮｳ","townName":"若菜町","zipCode":"6700941"},{"prefectureJisCode":"28","cityJisCode":"28201","townNameKana":"ﾜﾀﾏﾁ","townName":"綿町","zipCode":"6700921"}]