[{"prefectureJisCode":"28","cityJisCode":"28209","townNameKana":"ｱｶｲｼ","townName":"赤石","zipCode":"6680801"},{"prefectureJisCode":"28","cityJisCode":"28209","townNameKana":"ｲｶﾞﾀﾞﾆ","townName":"伊賀谷","zipCode":"6680001"},{"prefectureJisCode":"28","cityJisCode":"28209","townNameKana":"ｲｽﾞｼﾁｮｳｱﾗｷ","townName":"出石町荒木","zipCode":"6680261"},{"prefectureJisCode":"28","cityJisCode":"28209","townNameKana":"ｲｽﾞｼﾁｮｳｲｷﾞ","townName":"出石町伊木","zipCode":"6680213"},{"prefectureJisCode":"28","cityJisCode":"28209","townNameKana":"ｲｽﾞｼﾁｮｳｲｽﾞ","townName":"出石町伊豆","zipCode":"6680207"},{"prefectureJisCode":"28","cityJisCode":"28209","townNameKana":"ｲｽﾞｼﾁｮｳｲﾙｻ","townName":"出石町入佐","zipCode":"6680218"},{"prefectureJisCode":"28","cityJisCode":"28209","townNameKana":"ｲｽﾞｼﾁｮｳｳｴﾉ","townName":"出石町上野","zipCode":"6680244"},{"prefectureJisCode":"28","cityJisCode":"28209","townNameKana":"ｲｽﾞｼﾁｮｳｳｵﾔ","townName":"出石町魚屋","zipCode":"6680215"},{"prefectureJisCode":"28","cityJisCode":"28209","townNameKana":"ｲｽﾞｼﾁｮｳｳﾁﾏﾁ","townName":"出石町内町","zipCode":"6680214"},{"prefectureJisCode":"28","cityJisCode":"28209","townNameKana":"ｲｽﾞｼﾁｮｳｵｵﾀﾆ","townName":"出石町大谷","zipCode":"6680271"},{"prefectureJisCode":"28","cityJisCode":"28209","townNameKana":"ｲｽﾞｼﾁｮｳｵｸｵﾉ","townName":"出石町奥小野","zipCode":"6680201"},{"prefectureJisCode":"28","cityJisCode":"28209","townNameKana":"ｲｽﾞｼﾁｮｳｵｸﾔﾏ","townName":"出石町奥山","zipCode":"6680251"},{"prefectureJisCode":"28","cityJisCode":"28209","townNameKana":"ｲｽﾞｼﾁｮｳｶｼﾞﾔ","townName":"出石町鍛冶屋","zipCode":"6680235"},{"prefectureJisCode":"28","cityJisCode":"28209","townNameKana":"ｲｽﾞｼﾁｮｳｶﾀﾏ","townName":"出石町片間","zipCode":"6680279"},{"prefectureJisCode":"28","cityJisCode":"28209","townNameKana":"ｲｽﾞｼﾁｮｳｶﾐﾑﾗ","townName":"出石町上村","zipCode":"6680255"},{"prefectureJisCode":"28","cityJisCode":"28209","townNameKana":"ｲｽﾞｼﾁｮｳｶﾜﾗ","townName":"出石町川原","zipCode":"6680231"},{"prefectureJisCode":"28","cityJisCode":"28209","townNameKana":"ｲｽﾞｼﾁｮｳｷﾘﾉ","townName":"出石町桐野","zipCode":"6680242"},{"prefectureJisCode":"28","cityJisCode":"28209","townNameKana":"ｲｽﾞｼﾁｮｳｸﾁｵﾉ","townName":"出石町口小野","zipCode":"6680202"},{"prefectureJisCode":"28","cityJisCode":"28209","townNameKana":"ｲｽﾞｼﾁｮｳｸﾚｻｶ","townName":"出石町暮坂","zipCode":"6680264"},{"prefectureJisCode":"28","cityJisCode":"28209","townNameKana":"ｲｽﾞｼﾁｮｳｺﾋﾞﾄ","townName":"出石町小人","zipCode":"6680256"},{"prefectureJisCode":"28","cityJisCode":"28209","townNameKana":"ｲｽﾞｼﾁｮｳｻﾞｲﾓｸ","townName":"出石町材木","zipCode":"6680216"},{"prefectureJisCode":"28","cityJisCode":"28209","townNameKana":"ｲｽﾞｼﾁｮｳｼﾏ","townName":"出石町嶋","zipCode":"6680205"},{"prefectureJisCode":"28","cityJisCode":"28209","townNameKana":"ｲｽﾞｼﾁｮｳｼﾓﾀﾆ","townName":"出石町下谷","zipCode":"6680211"},{"prefectureJisCode":"28","cityJisCode":"28209","townNameKana":"ｲｽﾞｼﾁｮｳﾀｲﾉｼｮｳ","townName":"出石町田結庄","zipCode":"6680233"},{"prefectureJisCode":"28","cityJisCode":"28209","townNameKana":"ｲｽﾞｼﾁｮｳﾀﾀﾞﾁ","townName":"出石町田多地","zipCode":"6680209"},{"prefectureJisCode":"28","cityJisCode":"28209","townNameKana":"ｲｽﾞｼﾁｮｳﾀﾆﾔﾏ","townName":"出石町谷山","zipCode":"6680212"},{"prefectureJisCode":"28","cityJisCode":"28209","townNameKana":"ｲｽﾞｼﾁｮｳﾂﾎﾞｲ","townName":"出石町坪井","zipCode":"6680273"},{"prefectureJisCode":"28","cityJisCode":"28209","townNameKana":"ｲｽﾞｼﾁｮｳﾂﾎﾞｸﾞﾁ","townName":"出石町坪口","zipCode":"6680257"},{"prefectureJisCode":"28","cityJisCode":"28209","townNameKana":"ｲｽﾞｼﾁｮｳﾃｯﾎﾟｳ","townName":"出石町鉄砲","zipCode":"6680223"},{"prefectureJisCode":"28","cityJisCode":"28209","townNameKana":"ｲｽﾞｼﾁｮｳﾃﾗｻｶ","townName":"出石町寺坂","zipCode":"6680241"},{"prefectureJisCode":"28","cityJisCode":"28209","townNameKana":"ｲｽﾞｼﾁｮｳﾃﾗﾏﾁ","townName":"出石町寺町","zipCode":"6680222"},{"prefectureJisCode":"28","cityJisCode":"28209","townNameKana":"ｲｽﾞｼﾁｮｳﾄｳｼﾞｮｳ","townName":"出石町東條","zipCode":"6680217"},{"prefectureJisCode":"28","cityJisCode":"28209","townNameKana":"ｲｽﾞｼﾁｮｳﾄﾘｲ","townName":"出石町鳥居","zipCode":"6680272"},{"prefectureJisCode":"28","cityJisCode":"28209","townNameKana":"ｲｽﾞｼﾁｮｳﾅｶﾉ","townName":"出石町中野","zipCode":"6680243"},{"prefectureJisCode":"28","cityJisCode":"28209","townNameKana":"ｲｽﾞｼﾁｮｳﾅｶﾑﾗ","townName":"出石町中村","zipCode":"6680254"},{"prefectureJisCode":"28","cityJisCode":"28209","townNameKana":"ｲｽﾞｼﾁｮｳﾅｶﾞｽﾅ","townName":"出石町長砂","zipCode":"6680275"},{"prefectureJisCode":"28","cityJisCode":"28209","townNameKana":"ｲｽﾞｼﾁｮｳﾊｶｻﾞ","townName":"出石町袴狭","zipCode":"6680203"},{"prefectureJisCode":"28","cityJisCode":"28209","townNameKana":"ｲｽﾞｼﾁｮｳﾊﾞﾊﾞ","townName":"出石町馬場","zipCode":"6680237"},{"prefectureJisCode":"28","cityJisCode":"28209","townNameKana":"ｲｽﾞｼﾁｮｳﾋﾉﾍﾞ","townName":"出石町日野辺","zipCode":"6680246"},{"prefectureJisCode":"28","cityJisCode":"28209","townNameKana":"ｲｽﾞｼﾁｮｳﾋﾗﾀ","townName":"出石町平田","zipCode":"6680266"},{"prefectureJisCode":"28","cityJisCode":"28209","townNameKana":"ｲｽﾞｼﾁｮｳﾋﾛﾊﾗ","townName":"出石町弘原","zipCode":"6680238"},{"prefectureJisCode":"28","cityJisCode":"28209","townNameKana":"ｲｽﾞｼﾁｮｳﾌｸｲ","townName":"出石町福居","zipCode":"6680206"},{"prefectureJisCode":"28","cityJisCode":"28209","townNameKana":"ｲｽﾞｼﾁｮｳﾌｸｽﾐ","townName":"出石町福住","zipCode":"6680263"},{"prefectureJisCode":"28","cityJisCode":"28209","townNameKana":"ｲｽﾞｼﾁｮｳﾌｸﾐ","townName":"出石町福見","zipCode":"6680265"},{"prefectureJisCode":"28","cityJisCode":"28209","townNameKana":"ｲｽﾞｼﾁｮｳﾎｿﾐ","townName":"出石町細見","zipCode":"6680262"},{"prefectureJisCode":"28","cityJisCode":"28209","townNameKana":"ｲｽﾞｼﾁｮｳﾎﾝﾏﾁ","townName":"出石町本町","zipCode":"6680224"},{"prefectureJisCode":"28","cityJisCode":"28209","townNameKana":"ｲｽﾞｼﾁｮｳﾏﾁﾌﾞﾝ","townName":"出石町町分","zipCode":"6680221"},{"prefectureJisCode":"28","cityJisCode":"28209","townNameKana":"ｲｽﾞｼﾁｮｳﾏﾂｶﾞｴ","townName":"出石町松枝","zipCode":"6680236"},{"prefectureJisCode":"28","cityJisCode":"28209","townNameKana":"ｲｽﾞｼﾁｮｳﾏﾙﾅｶ","townName":"出石町丸中","zipCode":"6680277"},{"prefectureJisCode":"28","cityJisCode":"28209","townNameKana":"ｲｽﾞｼﾁｮｳﾐﾂｷ","townName":"出石町三木","zipCode":"6680278"},{"prefectureJisCode":"28","cityJisCode":"28209","townNameKana":"ｲｽﾞｼﾁｮｳﾐﾔｳﾁ","townName":"出石町宮内","zipCode":"6680204"},{"prefectureJisCode":"28","cityJisCode":"28209","townNameKana":"ｲｽﾞｼﾁｮｳﾑﾅｶﾞｲ","townName":"出石町水上","zipCode":"6680274"},{"prefectureJisCode":"28","cityJisCode":"28209","townNameKana":"ｲｽﾞｼﾁｮｳﾓﾘｲ","townName":"出石町森井","zipCode":"6680276"},{"prefectureJisCode":"28","cityJisCode":"28209","townNameKana":"ｲｽﾞｼﾁｮｳﾔｷﾞ","townName":"出石町八木","zipCode":"6680225"},{"prefectureJisCode":"28","cityJisCode":"28209","townNameKana":"ｲｽﾞｼﾁｮｳﾔｽﾗ","townName":"出石町安良","zipCode":"6680208"},{"prefectureJisCode":"28","cityJisCode":"28209","townNameKana":"ｲｽﾞｼﾁｮｳﾔﾅｷﾞ","townName":"出石町柳","zipCode":"6680234"},{"prefectureJisCode":"28","cityJisCode":"28209","townNameKana":"ｲｽﾞｼﾁｮｳﾕﾘ","townName":"出石町百合","zipCode":"6680245"},{"prefectureJisCode":"28","cityJisCode":"28209","townNameKana":"ｲｽﾞｼﾁｮｳﾖｲﾀﾞ","townName":"出石町宵田","zipCode":"6680232"},{"prefectureJisCode":"28","cityJisCode":"28209","townNameKana":"ｲｽﾞｼﾁｮｳﾖﾉﾐ","townName":"出石町榎見","zipCode":"6680253"},{"prefectureJisCode":"28","cityJisCode":"28209","townNameKana":"ｲｽﾞｼﾁｮｳﾜﾔ","townName":"出石町和屋","zipCode":"6680252"},{"prefectureJisCode":"28","cityJisCode":"28209","townNameKana":"ｲｽﾞﾐﾁｮｳ","townName":"泉町","zipCode":"6680021"},{"prefectureJisCode":"28","cityJisCode":"28209","townNameKana":"ｲﾁﾊﾞ","townName":"市場","zipCode":"6680821"},{"prefectureJisCode":"28","cityJisCode":"28209","townNameKana":"ｲﾏﾓﾘ","townName":"今森","zipCode":"6680851"},{"prefectureJisCode":"28","cityJisCode":"28209","townNameKana":"ｲﾜｲ","townName":"岩井","zipCode":"6680081"},{"prefectureJisCode":"28","cityJisCode":"28209","townNameKana":"ｲﾜｸﾏ","townName":"岩熊","zipCode":"6680002"},{"prefectureJisCode":"28","cityJisCode":"28209","townNameKana":"ｳﾁﾏﾁ","townName":"内町","zipCode":"6680071"},{"prefectureJisCode":"28","cityJisCode":"28209","townNameKana":"ｴﾓﾄ","townName":"江本","zipCode":"6680852"},{"prefectureJisCode":"28","cityJisCode":"28209","townNameKana":"ｵｵｲｿﾁｮｳ","townName":"大磯町","zipCode":"6680041"},{"prefectureJisCode":"28","cityJisCode":"28209","townNameKana":"ｵｵｼﾉｶ","townName":"大篠岡","zipCode":"6680861"},{"prefectureJisCode":"28","cityJisCode":"28209","townNameKana":"ｵｵﾀﾆ","townName":"大谷","zipCode":"6680072"},{"prefectureJisCode":"28","cityJisCode":"28209","townNameKana":"ｵｵﾃﾏﾁ","townName":"大手町","zipCode":"6680031"},{"prefectureJisCode":"28","cityJisCode":"28209","townNameKana":"ｵｸﾉ","townName":"奥野","zipCode":"6680822"},{"prefectureJisCode":"28","cityJisCode":"28209","townNameKana":"ｵｼﾏ","townName":"小島","zipCode":"6696123"},{"prefectureJisCode":"28","cityJisCode":"28209","townNameKana":"ｵﾀﾞｲﾁｮｳ","townName":"小田井町","zipCode":"6680022"},{"prefectureJisCode":"28","cityJisCode":"28209","townNameKana":"ｶｼﾞﾜﾗ","townName":"梶原","zipCode":"6680871"},{"prefectureJisCode":"28","cityJisCode":"28209","townNameKana":"ｶｽﾐ","townName":"香住","zipCode":"6680862"},{"prefectureJisCode":"28","cityJisCode":"28209","townNameKana":"ｶﾋﾛﾁｮｳ","townName":"加広町","zipCode":"6680023"},{"prefectureJisCode":"28","cityJisCode":"28209","townNameKana":"ｶﾏﾀ","townName":"鎌田","zipCode":"6680811"},{"prefectureJisCode":"28","cityJisCode":"28209","townNameKana":"ｶﾐｶｹﾞ","townName":"上陰","zipCode":"6680011"},{"prefectureJisCode":"28","cityJisCode":"28209","townNameKana":"ｶﾐｻﾉ","townName":"上佐野","zipCode":"6680061"},{"prefectureJisCode":"28","cityJisCode":"28209","townNameKana":"ｶﾐﾊﾁﾔﾏ","townName":"上鉢山","zipCode":"6680863"},{"prefectureJisCode":"28","cityJisCode":"28209","townNameKana":"ｶﾐﾖｼﾀﾞｲ","townName":"神美台","zipCode":"6680831"},{"prefectureJisCode":"28","cityJisCode":"28209","townNameKana":"ｶﾔ","townName":"加陽","zipCode":"6680841"},{"prefectureJisCode":"28","cityJisCode":"28209","townNameKana":"ｷｮｳﾏﾁ","townName":"京町","zipCode":"6680042"},{"prefectureJisCode":"28","cityJisCode":"28209","townNameKana":"ｷﾅｼ","townName":"木内","zipCode":"6680864"},{"prefectureJisCode":"28","cityJisCode":"28209","townNameKana":"ｷﾉｻｷﾁｮｳｲﾏﾂﾞ","townName":"城崎町今津","zipCode":"6696103"},{"prefectureJisCode":"28","cityJisCode":"28209","townNameKana":"ｷﾉｻｷﾁｮｳｳﾔﾏ","townName":"城崎町上山","zipCode":"6696116"},{"prefectureJisCode":"28","cityJisCode":"28209","townNameKana":"ｷﾉｻｷﾁｮｳｸﾙﾋ","townName":"城崎町来日","zipCode":"6696115"},{"prefectureJisCode":"28","cityJisCode":"28209","townNameKana":"ｷﾉｻｷﾁｮｳｻｻｳﾗ","townName":"城崎町楽々浦","zipCode":"6696111"},{"prefectureJisCode":"28","cityJisCode":"28209","townNameKana":"ｷﾉｻｷﾁｮｳﾄｼﾏ","townName":"城崎町戸島","zipCode":"6696114"},{"prefectureJisCode":"28","cityJisCode":"28209","townNameKana":"ｷﾉｻｷﾁｮｳﾊﾝﾀﾞﾆ","townName":"城崎町飯谷","zipCode":"6696112"},{"prefectureJisCode":"28","cityJisCode":"28209","townNameKana":"ｷﾉｻｷﾁｮｳﾑｽﾌﾞ","townName":"城崎町結","zipCode":"6696113"},{"prefectureJisCode":"28","cityJisCode":"28209","townNameKana":"ｷﾉｻｷﾁｮｳﾓﾓｼﾏ","townName":"城崎町桃島","zipCode":"6696102"},{"prefectureJisCode":"28","cityJisCode":"28209","townNameKana":"ｷﾉｻｷﾁｮｳﾕｼﾏ","townName":"城崎町湯島","zipCode":"6696101"},{"prefectureJisCode":"28","cityJisCode":"28209","townNameKana":"ｸﾗﾐ","townName":"倉見","zipCode":"6680832"},{"prefectureJisCode":"28","cityJisCode":"28209","townNameKana":"ｹﾋ","townName":"気比","zipCode":"6696124"},{"prefectureJisCode":"28","cityJisCode":"28209","townNameKana":"ｺｳﾀﾞﾆ","townName":"河谷","zipCode":"6680872"},{"prefectureJisCode":"28","cityJisCode":"28209","townNameKana":"ｺｺﾉｶｲﾁｶﾐﾉﾁｮｳ","townName":"九日市上町","zipCode":"6680051"},{"prefectureJisCode":"28","cityJisCode":"28209","townNameKana":"ｺｺﾉｶｲﾁｼﾓﾉﾁｮｳ","townName":"九日市下町","zipCode":"6680052"},{"prefectureJisCode":"28","cityJisCode":"28209","townNameKana":"ｺｺﾉｶｲﾁﾅｶﾉﾁｮｳ","townName":"九日市中町","zipCode":"6680053"},{"prefectureJisCode":"28","cityJisCode":"28209","townNameKana":"ｺﾄﾌﾞｷﾁｮｳ","townName":"寿町","zipCode":"6680024"},{"prefectureJisCode":"28","cityJisCode":"28209","townNameKana":"ｺﾝｺﾞｳｼﾞ","townName":"金剛寺","zipCode":"6680802"},{"prefectureJisCode":"28","cityJisCode":"28209","townNameKana":"ｺﾞｳﾉ","townName":"江野","zipCode":"6680003"},{"prefectureJisCode":"28","cityJisCode":"28209","townNameKana":"ｻｲﾜｲﾁｮｳ","townName":"幸町","zipCode":"6680025"},{"prefectureJisCode":"28","cityJisCode":"28209","townNameKana":"ｻｶｴﾏﾁ","townName":"栄町","zipCode":"6680812"},{"prefectureJisCode":"28","cityJisCode":"28209","townNameKana":"ｻｸﾗﾏﾁ","townName":"桜町","zipCode":"6680043"},{"prefectureJisCode":"28","cityJisCode":"28209","townNameKana":"ｻﾉ","townName":"佐野","zipCode":"6680062"},{"prefectureJisCode":"28","cityJisCode":"28209","townNameKana":"ｻﾝﾉｳﾁｮｳ","townName":"山王町","zipCode":"6680044"},{"prefectureJisCode":"28","cityJisCode":"28209","townNameKana":"ｼｮｳ","townName":"庄","zipCode":"6680082"},{"prefectureJisCode":"28","cityJisCode":"28209","townNameKana":"ｼｮｳｳﾝｼﾞ","townName":"祥雲寺","zipCode":"6680814"},{"prefectureJisCode":"28","cityJisCode":"28209","townNameKana":"ｼｮｳｻﾞｶｲ","townName":"庄境","zipCode":"6680873"},{"prefectureJisCode":"28","cityJisCode":"28209","townNameKana":"ｼｮｳﾎﾞｳｼﾞ","townName":"正法寺","zipCode":"6680063"},{"prefectureJisCode":"28","cityJisCode":"28209","townNameKana":"ｼｮｳﾚﾝｼﾞ","townName":"清冷寺","zipCode":"6680853"},{"prefectureJisCode":"28","cityJisCode":"28209","townNameKana":"ｼｮｳﾜﾁｮｳ","townName":"昭和町","zipCode":"6680055"},{"prefectureJisCode":"28","cityJisCode":"28209","townNameKana":"ｼｵﾂﾁｮｳ","townName":"塩津町","zipCode":"6680054"},{"prefectureJisCode":"28","cityJisCode":"28209","townNameKana":"ｼﾓｶｹﾞ","townName":"下陰","zipCode":"6680012"},{"prefectureJisCode":"28","cityJisCode":"28209","townNameKana":"ｼﾓﾂﾙｲ","townName":"下鶴井","zipCode":"6680803"},{"prefectureJisCode":"28","cityJisCode":"28209","townNameKana":"ｼﾓﾉﾐﾔ","townName":"下宮","zipCode":"6680813"},{"prefectureJisCode":"28","cityJisCode":"28209","townNameKana":"ｼﾓﾊﾁﾔﾏ","townName":"下鉢山","zipCode":"6680865"},{"prefectureJisCode":"28","cityJisCode":"28209","townNameKana":"ｼﾝﾄﾞｳ","townName":"新堂","zipCode":"6680004"},{"prefectureJisCode":"28","cityJisCode":"28209","townNameKana":"ｼﾞｮｳﾅﾝﾁｮｳ","townName":"城南町","zipCode":"6680045"},{"prefectureJisCode":"28","cityJisCode":"28209","townNameKana":"ｾﾄ","townName":"瀬戸","zipCode":"6696122"},{"prefectureJisCode":"28","cityJisCode":"28209","townNameKana":"ﾀｲ","townName":"田結","zipCode":"6696125"},{"prefectureJisCode":"28","cityJisCode":"28209","townNameKana":"ﾀｶﾔ","townName":"高屋","zipCode":"6680064"},{"prefectureJisCode":"28","cityJisCode":"28209","townNameKana":"ﾀｷ","townName":"滝","zipCode":"6680005"},{"prefectureJisCode":"28","cityJisCode":"28209","townNameKana":"ﾀｹﾉﾁｮｳｱｺﾝﾀﾞﾆ","townName":"竹野町阿金谷","zipCode":"6696214"},{"prefectureJisCode":"28","cityJisCode":"28209","townNameKana":"ﾀｹﾉﾁｮｳｱｼﾀﾞﾆ","townName":"竹野町芦谷","zipCode":"6696223"},{"prefectureJisCode":"28","cityJisCode":"28209","townNameKana":"ﾀｹﾉﾁｮｳｳﾋ","townName":"竹野町宇日","zipCode":"6696202"},{"prefectureJisCode":"28","cityJisCode":"28209","townNameKana":"ﾀｹﾉﾁｮｳｵｵﾓﾘ","townName":"竹野町大森","zipCode":"6696352"},{"prefectureJisCode":"28","cityJisCode":"28209","townNameKana":"ﾀｹﾉﾁｮｳｵｸｽｲ","townName":"竹野町奥須井","zipCode":"6696218"},{"prefectureJisCode":"28","cityJisCode":"28209","townNameKana":"ﾀｹﾉﾁｮｳｵｼﾞﾝﾀﾞﾆ","townName":"竹野町鬼神谷","zipCode":"6696224"},{"prefectureJisCode":"28","cityJisCode":"28209","townNameKana":"ﾀｹﾉﾁｮｳｵﾝﾏﾀ","townName":"竹野町御又","zipCode":"6696333"},{"prefectureJisCode":"28","cityJisCode":"28209","townNameKana":"ﾀｹﾉﾁｮｳｶﾅﾝﾀﾞﾆ","townName":"竹野町川南谷","zipCode":"6696354"},{"prefectureJisCode":"28","cityJisCode":"28209","townNameKana":"ﾀｹﾉﾁｮｳｶﾜﾁ","townName":"竹野町河内","zipCode":"6696334"},{"prefectureJisCode":"28","cityJisCode":"28209","townNameKana":"ﾀｹﾉﾁｮｳｷﾘﾊﾏ","townName":"竹野町切浜","zipCode":"6696216"},{"prefectureJisCode":"28","cityJisCode":"28209","townNameKana":"ﾀｹﾉﾁｮｳｷﾝﾊﾞﾗ","townName":"竹野町金原","zipCode":"6696229"},{"prefectureJisCode":"28","cityJisCode":"28209","townNameKana":"ﾀｹﾉﾁｮｳｸｻｶｲ","townName":"竹野町草飼","zipCode":"6696215"},{"prefectureJisCode":"28","cityJisCode":"28209","townNameKana":"ﾀｹﾉﾁｮｳｸﾜﾉﾓﾄ","townName":"竹野町桑野本","zipCode":"6696353"},{"prefectureJisCode":"28","cityJisCode":"28209","townNameKana":"ﾀｹﾉﾁｮｳｺｼﾞｮｳ","townName":"竹野町小城","zipCode":"6696341"},{"prefectureJisCode":"28","cityJisCode":"28209","townNameKana":"ﾀｹﾉﾁｮｳｺﾏﾙ","townName":"竹野町小丸","zipCode":"6696222"},{"prefectureJisCode":"28","cityJisCode":"28209","townNameKana":"ﾀｹﾉﾁｮｳｼﾓﾂﾞｶ","townName":"竹野町下塚","zipCode":"6696226"},{"prefectureJisCode":"28","cityJisCode":"28209","townNameKana":"ﾀｹﾉﾁｮｳｽﾀﾞﾆ","townName":"竹野町須谷","zipCode":"6696221"},{"prefectureJisCode":"28","cityJisCode":"28209","townNameKana":"ﾀｹﾉﾁｮｳｽﾉﾀﾆ","townName":"竹野町須野谷","zipCode":"6696351"},{"prefectureJisCode":"28","cityJisCode":"28209","townNameKana":"ﾀｹﾉﾁｮｳﾀｸﾋ","townName":"竹野町田久日","zipCode":"6696203"},{"prefectureJisCode":"28","cityJisCode":"28209","townNameKana":"ﾀｹﾉﾁｮｳﾀｹﾉ","townName":"竹野町竹野","zipCode":"6696201"},{"prefectureJisCode":"28","cityJisCode":"28209","townNameKana":"ﾀｹﾉﾁｮｳﾀﾞﾝ","townName":"竹野町段","zipCode":"6696343"},{"prefectureJisCode":"28","cityJisCode":"28209","townNameKana":"ﾀｹﾉﾁｮｳﾄﾄﾞﾛｷ","townName":"竹野町轟","zipCode":"6696225"},{"prefectureJisCode":"28","cityJisCode":"28209","townNameKana":"ﾀｹﾉﾁｮｳﾆﾚﾝﾊﾞﾗ","townName":"竹野町二連原","zipCode":"6696342"},{"prefectureJisCode":"28","cityJisCode":"28209","townNameKana":"ﾀｹﾉﾁｮｳﾊｼﾞｶﾐ","townName":"竹野町椒","zipCode":"6696344"},{"prefectureJisCode":"28","cityJisCode":"28209","townNameKana":"ﾀｹﾉﾁｮｳﾊﾆｭｳ","townName":"竹野町羽入","zipCode":"6696213"},{"prefectureJisCode":"28","cityJisCode":"28209","townNameKana":"ﾀｹﾉﾁｮｳﾊﾏｽｲ","townName":"竹野町浜須井","zipCode":"6696217"},{"prefectureJisCode":"28","cityJisCode":"28209","townNameKana":"ﾀｹﾉﾁｮｳﾊﾔｼ","townName":"竹野町林","zipCode":"6696227"},{"prefectureJisCode":"28","cityJisCode":"28209","townNameKana":"ﾀｹﾉﾁｮｳﾋｶﾞｼｵｵﾀﾆ","townName":"竹野町東大谷","zipCode":"6696228"},{"prefectureJisCode":"28","cityJisCode":"28209","townNameKana":"ﾀｹﾉﾁｮｳﾎﾞｳｵｶ","townName":"竹野町坊岡","zipCode":"6696331"},{"prefectureJisCode":"28","cityJisCode":"28209","townNameKana":"ﾀｹﾉﾁｮｳﾏﾂﾓﾄ","townName":"竹野町松本","zipCode":"6696212"},{"prefectureJisCode":"28","cityJisCode":"28209","townNameKana":"ﾀｹﾉﾁｮｳﾐﾊﾗ","townName":"竹野町三原","zipCode":"6696355"},{"prefectureJisCode":"28","cityJisCode":"28209","townNameKana":"ﾀｹﾉﾁｮｳﾓﾘﾓﾄ","townName":"竹野町森本","zipCode":"6696332"},{"prefectureJisCode":"28","cityJisCode":"28209","townNameKana":"ﾀｹﾉﾁｮｳﾓﾝﾀﾞﾆ","townName":"竹野町門谷","zipCode":"6696335"},{"prefectureJisCode":"28","cityJisCode":"28209","townNameKana":"ﾀｹﾉﾁｮｳﾜﾀﾞ","townName":"竹野町和田","zipCode":"6696211"},{"prefectureJisCode":"28","cityJisCode":"28209","townNameKana":"ﾀﾁﾉﾁｮｳ","townName":"立野町","zipCode":"6680046"},{"prefectureJisCode":"28","cityJisCode":"28209","townNameKana":"ﾀﾃｲｼ","townName":"立石","zipCode":"6680833"},{"prefectureJisCode":"28","cityJisCode":"28209","townNameKana":"ﾀﾝﾄｳﾁｮｳｱｲﾀﾞ","townName":"但東町相田","zipCode":"6680324"},{"prefectureJisCode":"28","cityJisCode":"28209","townNameKana":"ﾀﾝﾄｳﾁｮｳｱｶﾊﾞﾅ","townName":"但東町赤花","zipCode":"6680352"},{"prefectureJisCode":"28","cityJisCode":"28209","townNameKana":"ﾀﾝﾄｳﾁｮｳｱﾏﾀﾞﾆ","townName":"但東町天谷","zipCode":"6680316"},{"prefectureJisCode":"28","cityJisCode":"28209","townNameKana":"ﾀﾝﾄｳﾁｮｳｳｼﾛ","townName":"但東町後","zipCode":"6680374"},{"prefectureJisCode":"28","cityJisCode":"28209","townNameKana":"ﾀﾝﾄｳﾁｮｳｵｵｺﾞｳﾁ","townName":"但東町大河内","zipCode":"6680372"},{"prefectureJisCode":"28","cityJisCode":"28209","townNameKana":"ﾀﾝﾄｳﾁｮｳｵｵﾀ","townName":"但東町太田","zipCode":"6680335"},{"prefectureJisCode":"28","cityJisCode":"28209","townNameKana":"ﾀﾝﾄｳﾁｮｳｵｸｱｶ","townName":"但東町奥赤","zipCode":"6680353"},{"prefectureJisCode":"28","cityJisCode":"28209","townNameKana":"ﾀﾝﾄｳﾁｮｳｵｸﾌｼﾞ","townName":"但東町奥藤","zipCode":"6680343"},{"prefectureJisCode":"28","cityJisCode":"28209","townNameKana":"ﾀﾝﾄｳﾁｮｳｵｸﾔﾈ","townName":"但東町奥矢根","zipCode":"6680301"},{"prefectureJisCode":"28","cityJisCode":"28209","townNameKana":"ﾀﾝﾄｳﾁｮｳｵﾀﾞﾆ","townName":"但東町小谷","zipCode":"6680323"},{"prefectureJisCode":"28","cityJisCode":"28209","townNameKana":"ﾀﾝﾄｳﾁｮｳｶﾗｶﾜ","townName":"但東町唐川","zipCode":"6680321"},{"prefectureJisCode":"28","cityJisCode":"28209","townNameKana":"ﾀﾝﾄｳﾁｮｳｷﾑﾗ","townName":"但東町木村","zipCode":"6680331"},{"prefectureJisCode":"28","cityJisCode":"28209","townNameKana":"ﾀﾝﾄｳﾁｮｳｸﾁﾌｼﾞ","townName":"但東町口藤","zipCode":"6680341"},{"prefectureJisCode":"28","cityJisCode":"28209","townNameKana":"ﾀﾝﾄｳﾁｮｳｸﾊﾞﾀ","townName":"但東町久畑","zipCode":"6680373"},{"prefectureJisCode":"28","cityJisCode":"28209","townNameKana":"ﾀﾝﾄｳﾁｮｳｸﾘｵ","townName":"但東町栗尾","zipCode":"6680363"},{"prefectureJisCode":"28","cityJisCode":"28209","townNameKana":"ﾀﾝﾄｳﾁｮｳｺｳﾓﾄ","townName":"但東町河本","zipCode":"6680315"},{"prefectureJisCode":"28","cityJisCode":"28209","townNameKana":"ﾀﾝﾄｳﾁｮｳｺｳﾘｭｳｼﾞ","townName":"但東町高龍寺","zipCode":"6680333"},{"prefectureJisCode":"28","cityJisCode":"28209","townNameKana":"ﾀﾝﾄｳﾁｮｳｺｻﾞｺ","townName":"但東町小坂","zipCode":"6680376"},{"prefectureJisCode":"28","cityJisCode":"28209","townNameKana":"ﾀﾝﾄｳﾁｮｳｻｶﾂﾞ","townName":"但東町坂津","zipCode":"6680354"},{"prefectureJisCode":"28","cityJisCode":"28209","townNameKana":"ﾀﾝﾄｳﾁｮｳｻｶﾉ","townName":"但東町坂野","zipCode":"6680334"},{"prefectureJisCode":"28","cityJisCode":"28209","townNameKana":"ﾀﾝﾄｳﾁｮｳｻｻｷ","townName":"但東町佐々木","zipCode":"6680325"},{"prefectureJisCode":"28","cityJisCode":"28209","townNameKana":"ﾀﾝﾄｳﾁｮｳｻﾀﾞ","townName":"但東町佐田","zipCode":"6680364"},{"prefectureJisCode":"28","cityJisCode":"28209","townNameKana":"ﾀﾝﾄｳﾁｮｳｼｮｳﾎﾞｳｼﾞ","townName":"但東町正法寺","zipCode":"6680361"},{"prefectureJisCode":"28","cityJisCode":"28209","townNameKana":"ﾀﾝﾄｳﾁｮｳﾃﾞｱｲ","townName":"但東町出合","zipCode":"6680311"},{"prefectureJisCode":"28","cityJisCode":"28209","townNameKana":"ﾀﾝﾄｳﾁｮｳﾃﾞｱｲｲﾁﾊﾞ","townName":"但東町出合市場","zipCode":"6680313"},{"prefectureJisCode":"28","cityJisCode":"28209","townNameKana":"ﾀﾝﾄｳﾁｮｳﾄｳﾘ","townName":"但東町東里","zipCode":"6680337"},{"prefectureJisCode":"28","cityJisCode":"28209","townNameKana":"ﾀﾝﾄｳﾁｮｳﾅｶﾌｼﾞ","townName":"但東町中藤","zipCode":"6680342"},{"prefectureJisCode":"28","cityJisCode":"28209","townNameKana":"ﾀﾝﾄｳﾁｮｳﾅｶﾔﾏ","townName":"但東町中山","zipCode":"6680345"},{"prefectureJisCode":"28","cityJisCode":"28209","townNameKana":"ﾀﾝﾄｳﾁｮｳﾆｼﾀﾞﾆ","townName":"但東町西谷","zipCode":"6680317"},{"prefectureJisCode":"28","cityJisCode":"28209","townNameKana":"ﾀﾝﾄｳﾁｮｳﾆｼﾉﾉ","townName":"但東町西野々","zipCode":"6680332"},{"prefectureJisCode":"28","cityJisCode":"28209","townNameKana":"ﾀﾝﾄｳﾁｮｳﾊﾀ","townName":"但東町畑","zipCode":"6680303"},{"prefectureJisCode":"28","cityJisCode":"28209","townNameKana":"ﾀﾝﾄｳﾁｮｳﾊﾀﾔﾏ","townName":"但東町畑山","zipCode":"6680351"},{"prefectureJisCode":"28","cityJisCode":"28209","townNameKana":"ﾀﾝﾄｳﾁｮｳﾋｶﾞｼﾅｶ","townName":"但東町東中","zipCode":"6680375"},{"prefectureJisCode":"28","cityJisCode":"28209","townNameKana":"ﾀﾝﾄｳﾁｮｳﾋﾄﾞﾉ","townName":"但東町日殿","zipCode":"6680314"},{"prefectureJisCode":"28","cityJisCode":"28209","townNameKana":"ﾀﾝﾄｳﾁｮｳﾋﾅﾀﾞ","townName":"但東町日向","zipCode":"6680336"},{"prefectureJisCode":"28","cityJisCode":"28209","townNameKana":"ﾀﾝﾄｳﾁｮｳﾋﾗﾀ","townName":"但東町平田","zipCode":"6680362"},{"prefectureJisCode":"28","cityJisCode":"28209","townNameKana":"ﾀﾝﾄｳﾁｮｳﾐｽﾞｼ","townName":"但東町水石","zipCode":"6680304"},{"prefectureJisCode":"28","cityJisCode":"28209","townNameKana":"ﾀﾝﾄｳﾁｮｳﾐﾉｵ","townName":"但東町南尾","zipCode":"6680312"},{"prefectureJisCode":"28","cityJisCode":"28209","townNameKana":"ﾀﾝﾄｳﾁｮｳﾐﾊﾗ","townName":"但東町三原","zipCode":"6680322"},{"prefectureJisCode":"28","cityJisCode":"28209","townNameKana":"ﾀﾝﾄｳﾁｮｳﾑｼｭｳ","townName":"但東町虫生","zipCode":"6680344"},{"prefectureJisCode":"28","cityJisCode":"28209","townNameKana":"ﾀﾝﾄｳﾁｮｳﾔｸｵｳｼﾞ","townName":"但東町薬王寺","zipCode":"6680371"},{"prefectureJisCode":"28","cityJisCode":"28209","townNameKana":"ﾀﾝﾄｳﾁｮｳﾔﾈ","townName":"但東町矢根","zipCode":"6680302"},{"prefectureJisCode":"28","cityJisCode":"28209","townNameKana":"ﾀﾞｻｶ","townName":"駄坂","zipCode":"6680866"},{"prefectureJisCode":"28","cityJisCode":"28209","townNameKana":"ﾁｭｳｵｳﾏﾁ","townName":"中央町","zipCode":"6680033"},{"prefectureJisCode":"28","cityJisCode":"28209","townNameKana":"ﾁﾖﾀﾞﾁｮｳ","townName":"千代田町","zipCode":"6680032"},{"prefectureJisCode":"28","cityJisCode":"28209","townNameKana":"ﾂｲﾔﾏ","townName":"津居山","zipCode":"6696121"},{"prefectureJisCode":"28","cityJisCode":"28209","townNameKana":"ﾂｼﾞ","townName":"辻","zipCode":"6680073"},{"prefectureJisCode":"28","cityJisCode":"28209","townNameKana":"ﾄﾁｴ","townName":"栃江","zipCode":"6680083"},{"prefectureJisCode":"28","cityJisCode":"28209","townNameKana":"ﾄﾍﾞﾗ","townName":"戸牧","zipCode":"6680065"},{"prefectureJisCode":"28","cityJisCode":"28209","townNameKana":"ﾅｶｶｹﾞ","townName":"中陰","zipCode":"6680013"},{"prefectureJisCode":"28","cityJisCode":"28209","townNameKana":"ﾅｶﾉｺﾞｳ","townName":"中郷","zipCode":"6680842"},{"prefectureJisCode":"28","cityJisCode":"28209","townNameKana":"ﾅｶﾉﾀﾆ","townName":"中谷","zipCode":"6680874"},{"prefectureJisCode":"28","cityJisCode":"28209","townNameKana":"ﾅｶﾞﾀﾆ","townName":"長谷","zipCode":"6680834"},{"prefectureJisCode":"28","cityJisCode":"28209","townNameKana":"ﾉｶﾞｷ","townName":"野垣","zipCode":"6680074"},{"prefectureJisCode":"28","cityJisCode":"28209","townNameKana":"ﾉｼﾞｮｳ","townName":"野上","zipCode":"6680804"},{"prefectureJisCode":"28","cityJisCode":"28209","townNameKana":"ﾉﾀﾞ","townName":"野田","zipCode":"6680014"},{"prefectureJisCode":"28","cityJisCode":"28209","townNameKana":"ﾊｻﾐ","townName":"八社宮","zipCode":"6680854"},{"prefectureJisCode":"28","cityJisCode":"28209","townNameKana":"ﾊﾀｶﾞﾐ","townName":"畑上","zipCode":"6696127"},{"prefectureJisCode":"28","cityJisCode":"28209","townNameKana":"ﾋｷﾉ","townName":"引野","zipCode":"6680843"},{"prefectureJisCode":"28","cityJisCode":"28209","townNameKana":"ﾋｼﾞｳﾁ","townName":"土渕","zipCode":"6680844"},{"prefectureJisCode":"28","cityJisCode":"28209","townNameKana":"ﾋﾀﾞｶﾁｮｳｱｶｻｷ","townName":"日高町赤崎","zipCode":"6695314"},{"prefectureJisCode":"28","cityJisCode":"28209","townNameKana":"ﾋﾀﾞｶﾁｮｳｱｹﾞｼ","townName":"日高町上石","zipCode":"6695331"},{"prefectureJisCode":"28","cityJisCode":"28209","townNameKana":"ﾋﾀﾞｶﾁｮｳｱｻｸﾗ","townName":"日高町浅倉","zipCode":"6695315"},{"prefectureJisCode":"28","cityJisCode":"28209","townNameKana":"ﾋﾀﾞｶﾁｮｳｱﾗｶﾜ","townName":"日高町荒川","zipCode":"6695356"},{"prefectureJisCode":"28","cityJisCode":"28209","townNameKana":"ﾋﾀﾞｶﾁｮｳｲｹｶﾞﾐ","townName":"日高町池上","zipCode":"6695326"},{"prefectureJisCode":"28","cityJisCode":"28209","townNameKana":"ﾋﾀﾞｶﾁｮｳｲｼｲ","townName":"日高町石井","zipCode":"6695367"},{"prefectureJisCode":"28","cityJisCode":"28209","townNameKana":"ﾋﾀﾞｶﾁｮｳｲﾅﾝﾊﾞ","townName":"日高町稲葉","zipCode":"6695375"},{"prefectureJisCode":"28","cityJisCode":"28209","townNameKana":"ﾋﾀﾞｶﾁｮｳｲﾉｺｶﾞｷ","townName":"日高町猪子垣","zipCode":"6695357"},{"prefectureJisCode":"28","cityJisCode":"28209","townNameKana":"ﾋﾀﾞｶﾁｮｳｲﾉﾂﾒ","townName":"日高町猪爪","zipCode":"6695338"},{"prefectureJisCode":"28","cityJisCode":"28209","townNameKana":"ﾋﾀﾞｶﾁｮｳｲﾌﾞ","townName":"日高町伊府","zipCode":"6695346"},{"prefectureJisCode":"28","cityJisCode":"28209","townNameKana":"ﾋﾀﾞｶﾁｮｳｲﾜﾅｶ","townName":"日高町岩中","zipCode":"6695302"},{"prefectureJisCode":"28","cityJisCode":"28209","townNameKana":"ﾋﾀﾞｶﾁｮｳｴﾊﾞﾗ","townName":"日高町江原","zipCode":"6695301"},{"prefectureJisCode":"28","cityJisCode":"28209","townNameKana":"ﾋﾀﾞｶﾁｮｳｵｵｵｶ","townName":"日高町大岡","zipCode":"6695339"},{"prefectureJisCode":"28","cityJisCode":"28209","townNameKana":"ﾋﾀﾞｶﾁｮｳｶﾐﾉｺﾞｳ","townName":"日高町上郷","zipCode":"6695324"},{"prefectureJisCode":"28","cityJisCode":"28209","townNameKana":"ﾋﾀﾞｶﾁｮｳｶﾜｴ","townName":"日高町河江","zipCode":"6695339"},{"prefectureJisCode":"28","cityJisCode":"28209","townNameKana":"ﾋﾀﾞｶﾁｮｳｶﾝﾉﾝｼﾞ","townName":"日高町観音寺","zipCode":"6695354"},{"prefectureJisCode":"28","cityJisCode":"28209","townNameKana":"ﾋﾀﾞｶﾁｮｳｸﾀﾀﾞﾆ","townName":"日高町久田谷","zipCode":"6695345"},{"prefectureJisCode":"28","cityJisCode":"28209","townNameKana":"ﾋﾀﾞｶﾁｮｳｸﾄ","townName":"日高町久斗","zipCode":"6695342"},{"prefectureJisCode":"28","cityJisCode":"28209","townNameKana":"ﾋﾀﾞｶﾁｮｳｸﾘｽﾉ","townName":"日高町栗栖野","zipCode":"6695372"},{"prefectureJisCode":"28","cityJisCode":"28209","townNameKana":"ﾋﾀﾞｶﾁｮｳｸﾘﾔﾏ","townName":"日高町栗山","zipCode":"6695361"},{"prefectureJisCode":"28","cityJisCode":"28209","townNameKana":"ﾋﾀﾞｶﾁｮｳｺｶﾞﾜｴ","townName":"日高町小河江","zipCode":"6695339"},{"prefectureJisCode":"28","cityJisCode":"28209","townNameKana":"ﾋﾀﾞｶﾁｮｳｺｸﾌﾞﾝｼﾞ","townName":"日高町国分寺","zipCode":"6695341"},{"prefectureJisCode":"28","cityJisCode":"28209","townNameKana":"ﾋﾀﾞｶﾁｮｳｺﾛｶﾞｷ","townName":"日高町頃垣","zipCode":"6695366"},{"prefectureJisCode":"28","cityJisCode":"28209","townNameKana":"ﾋﾀﾞｶﾁｮｳｻﾀ","townName":"日高町佐田","zipCode":"6695351"},{"prefectureJisCode":"28","cityJisCode":"28209","townNameKana":"ﾋﾀﾞｶﾁｮｳｼｮｳｻﾞｶｴ","townName":"日高町庄境","zipCode":"6695364"},{"prefectureJisCode":"28","cityJisCode":"28209","townNameKana":"ﾋﾀﾞｶﾁｮｳｼﾉｶﾞｷ","townName":"日高町篠垣","zipCode":"6695355"},{"prefectureJisCode":"28","cityJisCode":"28209","townNameKana":"ﾋﾀﾞｶﾁｮｳｼﾊﾞ","townName":"日高町芝","zipCode":"6695362"},{"prefectureJisCode":"28","cityJisCode":"28209","townNameKana":"ﾋﾀﾞｶﾁｮｳｼﾞｭｳｺﾞ","townName":"日高町十戸","zipCode":"6695365"},{"prefectureJisCode":"28","cityJisCode":"28209","townNameKana":"ﾋﾀﾞｶﾁｮｳﾀｶﾇｷ","townName":"日高町竹貫","zipCode":"6695332"},{"prefectureJisCode":"28","cityJisCode":"28209","townNameKana":"ﾋﾀﾞｶﾁｮｳﾀﾀﾞ","townName":"日高町太田","zipCode":"6695371"},{"prefectureJisCode":"28","cityJisCode":"28209","townNameKana":"ﾋﾀﾞｶﾁｮｳﾀﾆ","townName":"日高町谷","zipCode":"6695336"},{"prefectureJisCode":"28","cityJisCode":"28209","townNameKana":"ﾋﾀﾞｶﾁｮｳﾀﾉｸﾁ","townName":"日高町田ノ口","zipCode":"6695357"},{"prefectureJisCode":"28","cityJisCode":"28209","townNameKana":"ﾋﾀﾞｶﾁｮｳﾁﾐ","townName":"日高町知見","zipCode":"6695352"},{"prefectureJisCode":"28","cityJisCode":"28209","townNameKana":"ﾋﾀﾞｶﾁｮｳﾂﾙｵｶ","townName":"日高町鶴岡","zipCode":"6695313"},{"prefectureJisCode":"28","cityJisCode":"28209","townNameKana":"ﾋﾀﾞｶﾁｮｳﾄﾁﾓﾄ","townName":"日高町栃本","zipCode":"6695369"},{"prefectureJisCode":"28","cityJisCode":"28209","townNameKana":"ﾋﾀﾞｶﾁｮｳﾄﾉ","townName":"日高町殿","zipCode":"6695358"},{"prefectureJisCode":"28","cityJisCode":"28209","townNameKana":"ﾋﾀﾞｶﾁｮｳﾄﾞｲ","townName":"日高町土居","zipCode":"6695321"},{"prefectureJisCode":"28","cityJisCode":"28209","townNameKana":"ﾋﾀﾞｶﾁｮｳﾄﾞｳｼﾞｮｳ","townName":"日高町道場","zipCode":"6695343"},{"prefectureJisCode":"28","cityJisCode":"28209","townNameKana":"ﾋﾀﾞｶﾁｮｳﾅｶ","townName":"日高町中","zipCode":"6695337"},{"prefectureJisCode":"28","cityJisCode":"28209","townNameKana":"ﾋﾀﾞｶﾁｮｳﾅｻｼﾞ","townName":"日高町奈佐路","zipCode":"6695335"},{"prefectureJisCode":"28","cityJisCode":"28209","townNameKana":"ﾋﾀﾞｶﾁｮｳﾅｼｷ","townName":"日高町名色","zipCode":"6695379"},{"prefectureJisCode":"28","cityJisCode":"28209","townNameKana":"ﾋﾀﾞｶﾁｮｳﾅﾂｸﾘ","townName":"日高町夏栗","zipCode":"6695344"},{"prefectureJisCode":"28","cityJisCode":"28209","townNameKana":"ﾋﾀﾞｶﾁｮｳﾆｮｳ","townName":"日高町祢布","zipCode":"6695305"},{"prefectureJisCode":"28","cityJisCode":"28209","townNameKana":"ﾋﾀﾞｶﾁｮｳﾆｼｼﾊﾞ","townName":"日高町西芝","zipCode":"6695328"},{"prefectureJisCode":"28","cityJisCode":"28209","townNameKana":"ﾋﾀﾞｶﾁｮｳﾉ","townName":"日高町野","zipCode":"6695363"},{"prefectureJisCode":"28","cityJisCode":"28209","townNameKana":"ﾋﾀﾞｶﾁｮｳﾉﾉｼｮｳ","townName":"日高町野々庄","zipCode":"6695327"},{"prefectureJisCode":"28","cityJisCode":"28209","townNameKana":"ﾋﾀﾞｶﾁｮｳﾊｼﾞﾘ","townName":"日高町羽尻","zipCode":"6695359"},{"prefectureJisCode":"28","cityJisCode":"28209","townNameKana":"ﾋﾀﾞｶﾁｮｳﾋｵｷ","townName":"日高町日置","zipCode":"6695311"},{"prefectureJisCode":"28","cityJisCode":"28209","townNameKana":"ﾋﾀﾞｶﾁｮｳﾋｶﾞｼｶﾞﾏｴ","townName":"日高町東構","zipCode":"6695303"},{"prefectureJisCode":"28","cityJisCode":"28209","townNameKana":"ﾋﾀﾞｶﾁｮｳﾋｶﾞｼｺﾞｳﾁ","townName":"日高町東河内","zipCode":"6695373"},{"prefectureJisCode":"28","cityJisCode":"28209","townNameKana":"ﾋﾀﾞｶﾁｮｳﾋｶﾞｼｼﾊﾞ","townName":"日高町東芝","zipCode":"6695328"},{"prefectureJisCode":"28","cityJisCode":"28209","townNameKana":"ﾋﾀﾞｶﾁｮｳﾋﾀﾞｶ","townName":"日高町日高","zipCode":"6695312"},{"prefectureJisCode":"28","cityJisCode":"28209","townNameKana":"ﾋﾀﾞｶﾁｮｳﾋﾛｲ","townName":"日高町広井","zipCode":"6695358"},{"prefectureJisCode":"28","cityJisCode":"28209","townNameKana":"ﾋﾀﾞｶﾁｮｳﾌｲﾁﾊﾞ","townName":"日高町府市場","zipCode":"6695322"},{"prefectureJisCode":"28","cityJisCode":"28209","townNameKana":"ﾋﾀﾞｶﾁｮｳﾌｼﾞｲ","townName":"日高町藤井","zipCode":"6695333"},{"prefectureJisCode":"28","cityJisCode":"28209","townNameKana":"ﾋﾀﾞｶﾁｮｳﾌﾁｭｳｼﾝ","townName":"日高町府中新","zipCode":"6695323"},{"prefectureJisCode":"28","cityJisCode":"28209","townNameKana":"ﾋﾀﾞｶﾁｮｳﾎﾘ","townName":"日高町堀","zipCode":"6695325"},{"prefectureJisCode":"28","cityJisCode":"28209","townNameKana":"ﾋﾀﾞｶﾁｮｳﾏﾂｵｶ","townName":"日高町松岡","zipCode":"6695307"},{"prefectureJisCode":"28","cityJisCode":"28209","townNameKana":"ﾋﾀﾞｶﾁｮｳﾏﾝｺﾞｳ","townName":"日高町万劫","zipCode":"6695376"},{"prefectureJisCode":"28","cityJisCode":"28209","townNameKana":"ﾋﾀﾞｶﾁｮｳﾏﾝﾊﾞ","townName":"日高町万場","zipCode":"6695378"},{"prefectureJisCode":"28","cityJisCode":"28209","townNameKana":"ﾋﾀﾞｶﾁｮｳﾐﾉｶﾐ","townName":"日高町水上","zipCode":"6695306"},{"prefectureJisCode":"28","cityJisCode":"28209","townNameKana":"ﾋﾀﾞｶﾁｮｳﾐﾉｸﾁ","townName":"日高町水口","zipCode":"6695374"},{"prefectureJisCode":"28","cityJisCode":"28209","townNameKana":"ﾋﾀﾞｶﾁｮｳﾓﾘﾔﾏ","townName":"日高町森山","zipCode":"6695353"},{"prefectureJisCode":"28","cityJisCode":"28209","townNameKana":"ﾋﾀﾞｶﾁｮｳﾔｼﾛ","townName":"日高町八代","zipCode":"6695339"},{"prefectureJisCode":"28","cityJisCode":"28209","townNameKana":"ﾋﾀﾞｶﾁｮｳﾔﾏﾀ","townName":"日高町山田","zipCode":"6695377"},{"prefectureJisCode":"28","cityJisCode":"28209","townNameKana":"ﾋﾀﾞｶﾁｮｳﾔﾏﾉﾐﾔ","townName":"日高町山宮","zipCode":"6695368"},{"prefectureJisCode":"28","cityJisCode":"28209","townNameKana":"ﾋﾀﾞｶﾁｮｳﾔﾏﾓﾄ","townName":"日高町山本","zipCode":"6695334"},{"prefectureJisCode":"28","cityJisCode":"28209","townNameKana":"ﾋﾀﾞｶﾁｮｳﾖｲﾀﾞ","townName":"日高町宵田","zipCode":"6695304"},{"prefectureJisCode":"28","cityJisCode":"28209","townNameKana":"ﾋﾄｲﾁ","townName":"一日市","zipCode":"6680015"},{"prefectureJisCode":"28","cityJisCode":"28209","townNameKana":"ﾋﾅﾄﾞ","townName":"日撫","zipCode":"6680815"},{"prefectureJisCode":"28","cityJisCode":"28209","townNameKana":"ﾌｸｼﾞｮｳｼﾞ","townName":"福成寺","zipCode":"6680075"},{"prefectureJisCode":"28","cityJisCode":"28209","townNameKana":"ﾌｸﾀﾞ","townName":"福田","zipCode":"6680084"},{"prefectureJisCode":"28","cityJisCode":"28209","townNameKana":"ﾌｼ","townName":"伏","zipCode":"6680855"},{"prefectureJisCode":"28","cityJisCode":"28209","townNameKana":"ﾌﾅﾀﾞﾆ","townName":"船谷","zipCode":"6680076"},{"prefectureJisCode":"28","cityJisCode":"28209","townNameKana":"ﾌﾅﾏﾁ","townName":"船町","zipCode":"6680805"},{"prefectureJisCode":"28","cityJisCode":"28209","townNameKana":"ﾎｯｹｲｼﾞ","townName":"法花寺","zipCode":"6680816"},{"prefectureJisCode":"28","cityJisCode":"28209","townNameKana":"ﾐｮｳﾗｸｼﾞ","townName":"妙楽寺","zipCode":"6680056"},{"prefectureJisCode":"28","cityJisCode":"28209","townNameKana":"ﾐｻｶﾁｮｳ","townName":"三坂町","zipCode":"6680047"},{"prefectureJisCode":"28","cityJisCode":"28209","townNameKana":"ﾐﾊﾗ","townName":"三原","zipCode":"6696126"},{"prefectureJisCode":"28","cityJisCode":"28209","townNameKana":"ﾐﾔｲ","townName":"宮井","zipCode":"6680085"},{"prefectureJisCode":"28","cityJisCode":"28209","townNameKana":"ﾐﾔｹ","townName":"三宅","zipCode":"6680823"},{"prefectureJisCode":"28","cityJisCode":"28209","townNameKana":"ﾐﾔｼﾞﾏ","townName":"宮島","zipCode":"6680016"},{"prefectureJisCode":"28","cityJisCode":"28209","townNameKana":"ﾒｻｶ","townName":"目坂","zipCode":"6680077"},{"prefectureJisCode":"28","cityJisCode":"28209","townNameKana":"ﾓﾄﾏﾁ","townName":"元町","zipCode":"6680026"},{"prefectureJisCode":"28","cityJisCode":"28209","townNameKana":"ﾓﾘ","townName":"森","zipCode":"6680806"},{"prefectureJisCode":"28","cityJisCode":"28209","townNameKana":"ﾓﾘｵ","townName":"森尾","zipCode":"6680824"},{"prefectureJisCode":"28","cityJisCode":"28209","townNameKana":"ﾓﾘﾂﾞ","townName":"森津","zipCode":"6680006"},{"prefectureJisCode":"28","cityJisCode":"28209","townNameKana":"ﾔｻｶﾁｮｳ","townName":"弥栄町","zipCode":"6680057"},{"prefectureJisCode":"28","cityJisCode":"28209","townNameKana":"ﾔﾏﾓﾄ","townName":"山本","zipCode":"6680807"},{"prefectureJisCode":"28","cityJisCode":"28209","townNameKana":"ﾕﾙｼﾞ","townName":"百合地","zipCode":"6680875"},{"prefectureJisCode":"28","cityJisCode":"28209","townNameKana":"ﾖｼｲ","townName":"吉井","zipCode":"6680078"},{"prefectureJisCode":"28","cityJisCode":"28209","townNameKana":"ﾛｸｼﾞｿﾞｳ","townName":"六地蔵","zipCode":"6680817"},{"prefectureJisCode":"28","cityJisCode":"28209","townNameKana":"ﾜｶﾏﾂﾁｮｳ","townName":"若松町","zipCode":"6680027"}]