[{"prefectureJisCode":"05","cityJisCode":"05201","townNameKana":"ｱｻﾋｶﾜｷﾖｽﾐﾏﾁ","townName":"旭川清澄町","zipCode":"0100831"},{"prefectureJisCode":"05","cityJisCode":"05201","townNameKana":"ｱｻﾋｶﾜｼﾝﾄｳﾀﾞﾆｼﾏﾁ","townName":"旭川新藤田西町","zipCode":"0100832"},{"prefectureJisCode":"05","cityJisCode":"05201","townNameKana":"ｱｻﾋｶﾜｼﾝﾄｳﾀﾞﾋｶﾞｼﾏﾁ","townName":"旭川新藤田東町","zipCode":"0100833"},{"prefectureJisCode":"05","cityJisCode":"05201","townNameKana":"ｱｻﾋｶﾜﾐﾅﾐﾏﾁ","townName":"旭川南町","zipCode":"0100834"},{"prefectureJisCode":"05","cityJisCode":"05201","townNameKana":"ｱﾗﾔｱｻﾋﾏﾁ","townName":"新屋朝日町","zipCode":"0101613"},{"prefectureJisCode":"05","cityJisCode":"05201","townNameKana":"ｱﾗﾔｵｵｶﾜﾏﾁ","townName":"新屋大川町","zipCode":"0101632"},{"prefectureJisCode":"05","cityJisCode":"05201","townNameKana":"ｱﾗﾔｵｵｷﾞﾏﾁ","townName":"新屋扇町","zipCode":"0101637"},{"prefectureJisCode":"05","cityJisCode":"05201","townNameKana":"ｱﾗﾔｵｷﾀﾏﾁ","townName":"新屋沖田町","zipCode":"0101634"},{"prefectureJisCode":"05","cityJisCode":"05201","townNameKana":"ｱﾗﾔｵﾓﾃﾏﾁ","townName":"新屋表町","zipCode":"0101638"},{"prefectureJisCode":"05","cityJisCode":"05201","townNameKana":"ｱﾗﾔｶﾂﾋﾗﾀﾞｲ","townName":"新屋勝平台","zipCode":"0101603"},{"prefectureJisCode":"05","cityJisCode":"05201","townNameKana":"ｱﾗﾔｶﾂﾋﾗﾏﾁ","townName":"新屋勝平町","zipCode":"0101605"},{"prefectureJisCode":"05","cityJisCode":"05201","townNameKana":"ｱﾗﾔｷﾀﾊﾏﾁｮｳ","townName":"新屋北浜町","zipCode":"0101608"},{"prefectureJisCode":"05","cityJisCode":"05201","townNameKana":"ｱﾗﾔｸﾘﾀﾏﾁ","townName":"新屋栗田町","zipCode":"0101621"},{"prefectureJisCode":"05","cityJisCode":"05201","townNameKana":"ｱﾗﾔｺﾄﾌﾞｷﾏﾁ","townName":"新屋寿町","zipCode":"0101606"},{"prefectureJisCode":"05","cityJisCode":"05201","townNameKana":"ｱﾗﾔｼﾀｶﾜﾗﾏﾁ","townName":"新屋下川原町","zipCode":"0101602"},{"prefectureJisCode":"05","cityJisCode":"05201","townNameKana":"ｱﾗﾔｼﾌﾞﾔﾏﾁ","townName":"新屋渋谷町","zipCode":"0101642"},{"prefectureJisCode":"05","cityJisCode":"05201","townNameKana":"ｱﾗﾔﾀｶﾐﾏﾁ","townName":"新屋高美町","zipCode":"0101641"},{"prefectureJisCode":"05","cityJisCode":"05201","townNameKana":"ｱﾗﾔﾀｼﾞﾘｻﾞﾜﾅｶﾏﾁ","townName":"新屋田尻沢中町","zipCode":"0101644"},{"prefectureJisCode":"05","cityJisCode":"05201","townNameKana":"ｱﾗﾔﾀｼﾞﾘｻﾞﾜﾆｼﾏﾁ","townName":"新屋田尻沢西町","zipCode":"0101645"},{"prefectureJisCode":"05","cityJisCode":"05201","townNameKana":"ｱﾗﾔﾀｼﾞﾘｻﾞﾜﾋｶﾞｼﾏﾁ","townName":"新屋田尻沢東町","zipCode":"0101643"},{"prefectureJisCode":"05","cityJisCode":"05201","townNameKana":"ｱﾗﾔﾃﾝﾋﾞﾝﾉ","townName":"新屋天秤野","zipCode":"0101611"},{"prefectureJisCode":"05","cityJisCode":"05201","townNameKana":"ｱﾗﾔﾄﾘｷﾏﾁ","townName":"新屋鳥木町","zipCode":"0101633"},{"prefectureJisCode":"05","cityJisCode":"05201","townNameKana":"ｱﾗﾔﾋﾅｲﾏﾁ","townName":"新屋比内町","zipCode":"0101636"},{"prefectureJisCode":"05","cityJisCode":"05201","townNameKana":"ｱﾗﾔﾋﾖｼﾏﾁ","townName":"新屋日吉町","zipCode":"0101622"},{"prefectureJisCode":"05","cityJisCode":"05201","townNameKana":"ｱﾗﾔﾌﾅﾊﾞﾏﾁ","townName":"新屋船場町","zipCode":"0101615"},{"prefectureJisCode":"05","cityJisCode":"05201","townNameKana":"ｱﾗﾔﾏｴﾉﾏﾁ","townName":"新屋前野町","zipCode":"0101635"},{"prefectureJisCode":"05","cityJisCode":"05201","townNameKana":"ｱﾗﾔﾏﾁ","townName":"新屋町","zipCode":"0101623"},{"prefectureJisCode":"05","cityJisCode":"05201","townNameKana":"ｱﾗﾔﾏﾂﾐｶﾞｵｶｷﾀﾁｮｳ","townName":"新屋松美ガ丘北町","zipCode":"0101618"},{"prefectureJisCode":"05","cityJisCode":"05201","townNameKana":"ｱﾗﾔﾏﾂﾐｶﾞｵｶﾋｶﾞｼﾁｮｳ","townName":"新屋松美ガ丘東町","zipCode":"0101617"},{"prefectureJisCode":"05","cityJisCode":"05201","townNameKana":"ｱﾗﾔﾏﾂﾐｶﾞｵｶﾐﾅﾐﾁｮｳ","townName":"新屋松美ガ丘南町","zipCode":"0101616"},{"prefectureJisCode":"05","cityJisCode":"05201","townNameKana":"ｱﾗﾔﾏﾂﾐﾏﾁ","townName":"新屋松美町","zipCode":"0101604"},{"prefectureJisCode":"05","cityJisCode":"05201","townNameKana":"ｱﾗﾔﾐﾅﾐﾊﾏﾏﾁ","townName":"新屋南浜町","zipCode":"0101607"},{"prefectureJisCode":"05","cityJisCode":"05201","townNameKana":"ｱﾗﾔﾓﾄﾏﾁ","townName":"新屋元町","zipCode":"0101631"},{"prefectureJisCode":"05","cityJisCode":"05201","townNameKana":"ｱﾗﾔﾕﾀｶﾏﾁ","townName":"新屋豊町","zipCode":"0101612"},{"prefectureJisCode":"05","cityJisCode":"05201","townNameKana":"ｱﾗﾔﾜﾘﾔﾏﾏﾁ","townName":"新屋割山町","zipCode":"0101614"},{"prefectureJisCode":"05","cityJisCode":"05201","townNameKana":"ｲｲｼﾞﾏ","townName":"飯島","zipCode":"0110911"},{"prefectureJisCode":"05","cityJisCode":"05201","townNameKana":"ｲｲｼﾞﾏｲｲﾀﾞ","townName":"飯島飯田","zipCode":"0110949"},{"prefectureJisCode":"05","cityJisCode":"05201","townNameKana":"ｲｲｼﾞﾏｶﾜﾊﾞﾀ","townName":"飯島川端","zipCode":"0110912"},{"prefectureJisCode":"05","cityJisCode":"05201","townNameKana":"ｲｲｼﾞﾏｺｸﾁｮｳ","townName":"飯島穀丁","zipCode":"0110916"},{"prefectureJisCode":"05","cityJisCode":"05201","townNameKana":"ｲｲｼﾞﾏｼﾝﾁｮｳ","townName":"飯島新町","zipCode":"0110947"},{"prefectureJisCode":"05","cityJisCode":"05201","townNameKana":"ｲｲｼﾞﾏﾅｶﾞﾉｶﾐﾁｮｳ","townName":"飯島長野上町","zipCode":"0110928"},{"prefectureJisCode":"05","cityJisCode":"05201","townNameKana":"ｲｲｼﾞﾏﾅｶﾞﾉﾅｶﾁｮｳ","townName":"飯島長野中町","zipCode":"0110925"},{"prefectureJisCode":"05","cityJisCode":"05201","townNameKana":"ｲｲｼﾞﾏﾅｶﾞﾉﾎﾝﾁｮｳ","townName":"飯島長野本町","zipCode":"0110924"},{"prefectureJisCode":"05","cityJisCode":"05201","townNameKana":"ｲｲｼﾞﾏﾆｼﾌﾞｸﾛ","townName":"飯島西袋","zipCode":"0110948"},{"prefectureJisCode":"05","cityJisCode":"05201","townNameKana":"ｲｲｼﾞﾏﾈｽﾞﾐﾀ","townName":"飯島鼠田","zipCode":"0110913"},{"prefectureJisCode":"05","cityJisCode":"05201","townNameKana":"ｲｲｼﾞﾏﾌﾞﾝｷｮｳﾁｮｳ","townName":"飯島文京町","zipCode":"0110923"},{"prefectureJisCode":"05","cityJisCode":"05201","townNameKana":"ｲｲｼﾞﾏﾏﾂﾈﾆｼﾁｮｳ","townName":"飯島松根西町","zipCode":"0110921"},{"prefectureJisCode":"05","cityJisCode":"05201","townNameKana":"ｲｲｼﾞﾏﾏﾂﾈﾋｶﾞｼﾁｮｳ","townName":"飯島松根東町","zipCode":"0110922"},{"prefectureJisCode":"05","cityJisCode":"05201","townNameKana":"ｲｲｼﾞﾏﾐｻｺﾞﾁｮｳ","townName":"飯島美砂町","zipCode":"0110914"},{"prefectureJisCode":"05","cityJisCode":"05201","townNameKana":"ｲｲｼﾞﾏﾐﾁﾋｶﾞｼ","townName":"飯島道東","zipCode":"0110917"},{"prefectureJisCode":"05","cityJisCode":"05201","townNameKana":"ｲｲｼﾞﾏﾐﾄﾞﾘｶﾞｵｶﾁｮｳ","townName":"飯島緑丘町","zipCode":"0110915"},{"prefectureJisCode":"05","cityJisCode":"05201","townNameKana":"ｲｽﾞﾐ","townName":"泉","zipCode":"0100816"},{"prefectureJisCode":"05","cityJisCode":"05201","townNameKana":"ｲｽﾞﾐｲﾁﾉﾂﾎﾞ","townName":"泉一ノ坪","zipCode":"0100813"},{"prefectureJisCode":"05","cityJisCode":"05201","townNameKana":"ｲｽﾞﾐｶﾏﾉﾏﾁ","townName":"泉釜ノ町","zipCode":"0100811"},{"prefectureJisCode":"05","cityJisCode":"05201","townNameKana":"ｲｽﾞﾐｷﾀ","townName":"泉北","zipCode":"0100916"},{"prefectureJisCode":"05","cityJisCode":"05201","townNameKana":"ｲｽﾞﾐｽｶﾞﾉ","townName":"泉菅野","zipCode":"0100817"},{"prefectureJisCode":"05","cityJisCode":"05201","townNameKana":"ｲｽﾞﾐﾁｭｳｵｳ","townName":"泉中央","zipCode":"0100917"},{"prefectureJisCode":"05","cityJisCode":"05201","townNameKana":"ｲｽﾞﾐﾊﾞﾊﾞ","townName":"泉馬場","zipCode":"0100815"},{"prefectureJisCode":"05","cityJisCode":"05201","townNameKana":"ｲｽﾞﾐﾋｶﾞｼﾏﾁ","townName":"泉東町","zipCode":"0100814"},{"prefectureJisCode":"05","cityJisCode":"05201","townNameKana":"ｲｽﾞﾐﾐﾀｹﾈ","townName":"泉三嶽根","zipCode":"0100812"},{"prefectureJisCode":"05","cityJisCode":"05201","townNameKana":"ｲｽﾞﾐﾐﾅﾐ","townName":"泉南","zipCode":"0100918"},{"prefectureJisCode":"05","cityJisCode":"05201","townNameKana":"ｳｼｼﾞﾏ","townName":"牛島","zipCode":"0100064"},{"prefectureJisCode":"05","cityJisCode":"05201","townNameKana":"ｳｼｼﾞﾏﾆｼ","townName":"牛島西","zipCode":"0100063"},{"prefectureJisCode":"05","cityJisCode":"05201","townNameKana":"ｳｼｼﾞﾏﾋｶﾞｼ","townName":"牛島東","zipCode":"0100062"},{"prefectureJisCode":"05","cityJisCode":"05201","townNameKana":"ｳｼｼﾞﾏﾐﾅﾐ","townName":"牛島南","zipCode":"0100066"},{"prefectureJisCode":"05","cityJisCode":"05201","townNameKana":"ｵｵｽﾐ","townName":"大住","zipCode":"0101436"},{"prefectureJisCode":"05","cityJisCode":"05201","townNameKana":"ｵｵｽﾐﾐﾅﾐ","townName":"大住南","zipCode":"0101420"},{"prefectureJisCode":"05","cityJisCode":"05201","townNameKana":"ｵｵﾋﾗﾀﾞｲ","townName":"大平台","zipCode":"0101428"},{"prefectureJisCode":"05","cityJisCode":"05201","townNameKana":"ｵｵﾏﾁ","townName":"大町","zipCode":"0100921"},{"prefectureJisCode":"05","cityJisCode":"05201","townNameKana":"ｵﾉﾊﾞ","townName":"御野場","zipCode":"0101424"},{"prefectureJisCode":"05","cityJisCode":"05201","townNameKana":"ｵﾉﾊﾞｼﾝﾏﾁ","townName":"御野場新町","zipCode":"0101425"},{"prefectureJisCode":"05","cityJisCode":"05201","townNameKana":"ｵﾛｼﾏﾁ","townName":"卸町","zipCode":"0100061"},{"prefectureJisCode":"05","cityJisCode":"05201","townNameKana":"ｶﾅｱｼｲﾜｾ","townName":"金足岩瀬","zipCode":"0100111"},{"prefectureJisCode":"05","cityJisCode":"05201","townNameKana":"ｶﾅｱｼｳﾗﾔﾏ","townName":"金足浦山","zipCode":"0100113"},{"prefectureJisCode":"05","cityJisCode":"05201","townNameKana":"ｶﾅｱｼｵｲﾜｹ","townName":"金足追分","zipCode":"0100126"},{"prefectureJisCode":"05","cityJisCode":"05201","townNameKana":"ｶﾅｱｼｵｵｼﾐｽﾞ","townName":"金足大清水","zipCode":"0100115"},{"prefectureJisCode":"05","cityJisCode":"05201","townNameKana":"ｶﾅｱｼｶﾀﾀﾞ","townName":"金足片田","zipCode":"0100123"},{"prefectureJisCode":"05","cityJisCode":"05201","townNameKana":"ｶﾅｱｼｸﾛｶﾜ","townName":"金足黒川","zipCode":"0100121"},{"prefectureJisCode":"05","cityJisCode":"05201","townNameKana":"ｶﾅｱｼｺｲｽﾞﾐ","townName":"金足小泉","zipCode":"0100116"},{"prefectureJisCode":"05","cityJisCode":"05201","townNameKana":"ｶﾅｱｼｼﾀｶﾘ","townName":"金足下刈","zipCode":"0100114"},{"prefectureJisCode":"05","cityJisCode":"05201","townNameKana":"ｶﾅｱｼﾀｶｵｶ","townName":"金足高岡","zipCode":"0100125"},{"prefectureJisCode":"05","cityJisCode":"05201","townNameKana":"ｶﾅｱｼﾆｵｻﾞｷ","townName":"金足鳰崎","zipCode":"0100124"},{"prefectureJisCode":"05","cityJisCode":"05201","townNameKana":"ｶﾅｱｼﾎﾘｳﾁ","townName":"金足堀内","zipCode":"0100112"},{"prefectureJisCode":"05","cityJisCode":"05201","townNameKana":"ｶﾅｱｼﾖｼﾀﾞ","townName":"金足吉田","zipCode":"0100122"},{"prefectureJisCode":"05","cityJisCode":"05201","townNameKana":"ｶﾐｷﾀﾃｱﾗﾏｷ","townName":"上北手荒巻","zipCode":"0101403"},{"prefectureJisCode":"05","cityJisCode":"05201","townNameKana":"ｶﾐｷﾀﾃｵｵｽｷﾞｻﾜ","townName":"上北手大杉沢","zipCode":"0101401"},{"prefectureJisCode":"05","cityJisCode":"05201","townNameKana":"ｶﾐｷﾀﾃｵｵﾄﾞ","townName":"上北手大戸","zipCode":"0101408"},{"prefectureJisCode":"05","cityJisCode":"05201","townNameKana":"ｶﾐｷﾀﾃｵｵﾔﾏﾀﾞ","townName":"上北手大山田","zipCode":"0101405"},{"prefectureJisCode":"05","cityJisCode":"05201","townNameKana":"ｶﾐｷﾀﾃｵﾔﾏﾀﾞ","townName":"上北手小山田","zipCode":"0101402"},{"prefectureJisCode":"05","cityJisCode":"05201","townNameKana":"ｶﾐｷﾀﾃｺﾉ","townName":"上北手古野","zipCode":"0101404"},{"prefectureJisCode":"05","cityJisCode":"05201","townNameKana":"ｶﾐｷﾀﾃｺﾞｼｮﾉ","townName":"上北手御所野","zipCode":"0101411"},{"prefectureJisCode":"05","cityJisCode":"05201","townNameKana":"ｶﾐｷﾀﾃｻﾙﾀ","townName":"上北手猿田","zipCode":"0101406"},{"prefectureJisCode":"05","cityJisCode":"05201","townNameKana":"ｶﾐｷﾀﾃﾓﾓｻﾞｷ","townName":"上北手百崎","zipCode":"0101407"},{"prefectureJisCode":"05","cityJisCode":"05201","townNameKana":"ｶﾐｼﾝｼﾞｮｳｲｼﾅｻﾞｶ","townName":"上新城石名坂","zipCode":"0100137"},{"prefectureJisCode":"05","cityJisCode":"05201","townNameKana":"ｶﾐｼﾝｼﾞｮｳｵﾏﾀ","townName":"上新城小又","zipCode":"0100132"},{"prefectureJisCode":"05","cityJisCode":"05201","townNameKana":"ｶﾐｼﾝｼﾞｮｳｺﾞｼﾞｯﾁｮｳ","townName":"上新城五十丁","zipCode":"0100135"},{"prefectureJisCode":"05","cityJisCode":"05201","townNameKana":"ｶﾐｼﾝｼﾞｮｳｼﾗﾔﾏ","townName":"上新城白山","zipCode":"0100131"},{"prefectureJisCode":"05","cityJisCode":"05201","townNameKana":"ｶﾐｼﾝｼﾞｮｳﾅｶ","townName":"上新城中","zipCode":"0100136"},{"prefectureJisCode":"05","cityJisCode":"05201","townNameKana":"ｶﾐｼﾝｼﾞｮｳﾎﾀﾉ","townName":"上新城保多野","zipCode":"0100138"},{"prefectureJisCode":"05","cityJisCode":"05201","townNameKana":"ｶﾐｼﾝｼﾞｮｳﾐﾁｶﾜ","townName":"上新城道川","zipCode":"0100134"},{"prefectureJisCode":"05","cityJisCode":"05201","townNameKana":"ｶﾐｼﾝｼﾞｮｳﾕﾉｻﾄ","townName":"上新城湯ノ里","zipCode":"0100133"},{"prefectureJisCode":"05","cityJisCode":"05201","townNameKana":"ｶﾜｼﾘｳｴﾉﾏﾁ","townName":"川尻上野町","zipCode":"0100947"},{"prefectureJisCode":"05","cityJisCode":"05201","townNameKana":"ｶﾜｼﾘｵｵｶﾜﾏﾁ","townName":"川尻大川町","zipCode":"0100942"},{"prefectureJisCode":"05","cityJisCode":"05201","townNameKana":"ｶﾜｼﾘｵﾔｽﾐﾏﾁ","townName":"川尻御休町","zipCode":"0100943"},{"prefectureJisCode":"05","cityJisCode":"05201","townNameKana":"ｶﾜｼﾘｼﾝｶﾜﾏﾁ","townName":"川尻新川町","zipCode":"0100948"},{"prefectureJisCode":"05","cityJisCode":"05201","townNameKana":"ｶﾜｼﾘｿｳｼｬﾏﾁ","townName":"川尻総社町","zipCode":"0100946"},{"prefectureJisCode":"05","cityJisCode":"05201","townNameKana":"ｶﾜｼﾘﾏﾁ","townName":"川尻町","zipCode":"0100941"},{"prefectureJisCode":"05","cityJisCode":"05201","townNameKana":"ｶﾜｼﾘﾐﾖｼﾏﾁ","townName":"川尻みよし町","zipCode":"0100945"},{"prefectureJisCode":"05","cityJisCode":"05201","townNameKana":"ｶﾜｼﾘﾜｶﾊﾞﾏﾁ","townName":"川尻若葉町","zipCode":"0100944"},{"prefectureJisCode":"05","cityJisCode":"05201","townNameKana":"ｶﾜﾍﾞｱｶﾋﾗ","townName":"河辺赤平","zipCode":"0192623"},{"prefectureJisCode":"05","cityJisCode":"05201","townNameKana":"ｶﾜﾍﾞｲﾜﾐ","townName":"河辺岩見","zipCode":"0192741"},{"prefectureJisCode":"05","cityJisCode":"05201","townNameKana":"ｶﾜﾍﾞｵｵｻﾜ","townName":"河辺大沢","zipCode":"0192624"},{"prefectureJisCode":"05","cityJisCode":"05201","townNameKana":"ｶﾜﾍﾞｵｵﾊﾞﾘﾉ","townName":"河辺大張野","zipCode":"0192632"},{"prefectureJisCode":"05","cityJisCode":"05201","townNameKana":"ｶﾜﾍﾞｷﾀﾉﾀﾞｺｳﾔ","townName":"河辺北野田高屋","zipCode":"0192625"},{"prefectureJisCode":"05","cityJisCode":"05201","townNameKana":"ｶﾜﾍﾞｻﾝﾅｲ","townName":"河辺三内","zipCode":"0192742"},{"prefectureJisCode":"05","cityJisCode":"05201","townNameKana":"ｶﾜﾍﾞｼﾞﾝﾅｲ","townName":"河辺神内","zipCode":"0192631"},{"prefectureJisCode":"05","cityJisCode":"05201","townNameKana":"ｶﾜﾍﾞﾀｶｵｶ","townName":"河辺高岡","zipCode":"0192622"},{"prefectureJisCode":"05","cityJisCode":"05201","townNameKana":"ｶﾜﾍﾞﾄｼﾏ","townName":"河辺戸島","zipCode":"0192611"},{"prefectureJisCode":"05","cityJisCode":"05201","townNameKana":"ｶﾜﾍﾞﾄﾖﾅﾘ","townName":"河辺豊成","zipCode":"0192614"},{"prefectureJisCode":"05","cityJisCode":"05201","townNameKana":"ｶﾜﾍﾞﾊﾀﾔ","townName":"河辺畑谷","zipCode":"0192612"},{"prefectureJisCode":"05","cityJisCode":"05201","townNameKana":"ｶﾜﾍﾞﾏﾂﾌﾞﾁ","townName":"河辺松渕","zipCode":"0192613"},{"prefectureJisCode":"05","cityJisCode":"05201","townNameKana":"ｶﾜﾍﾞﾓﾛｲ","townName":"河辺諸井","zipCode":"0192621"},{"prefectureJisCode":"05","cityJisCode":"05201","townNameKana":"ｶﾜﾍﾞﾜﾀﾞ","townName":"河辺和田","zipCode":"0192601"},{"prefectureJisCode":"05","cityJisCode":"05201","townNameKana":"ｶﾜﾓﾄｵｶﾞﾜﾏﾁ","townName":"川元小川町","zipCode":"0100935"},{"prefectureJisCode":"05","cityJisCode":"05201","townNameKana":"ｶﾜﾓﾄｶｲﾜﾏﾁ","townName":"川元開和町","zipCode":"0100932"},{"prefectureJisCode":"05","cityJisCode":"05201","townNameKana":"ｶﾜﾓﾄﾏﾂｵｶﾏﾁ","townName":"川元松丘町","zipCode":"0100933"},{"prefectureJisCode":"05","cityJisCode":"05201","townNameKana":"ｶﾜﾓﾄﾑﾂﾐﾏﾁ","townName":"川元むつみ町","zipCode":"0100934"},{"prefectureJisCode":"05","cityJisCode":"05201","townNameKana":"ｶﾜﾓﾄﾔﾏｼﾀﾏﾁ","townName":"川元山下町","zipCode":"0100931"},{"prefectureJisCode":"05","cityJisCode":"05201","townNameKana":"ｷｮｸﾅﾝ","townName":"旭南","zipCode":"0100925"},{"prefectureJisCode":"05","cityJisCode":"05201","townNameKana":"ｷｮｸﾎｸｻｶｴﾏﾁ","townName":"旭北栄町","zipCode":"0100922"},{"prefectureJisCode":"05","cityJisCode":"05201","townNameKana":"ｷｮｸﾎｸﾃﾗﾏﾁ","townName":"旭北寺町","zipCode":"0100924"},{"prefectureJisCode":"05","cityJisCode":"05201","townNameKana":"ｷｮｸﾎｸﾆｼｷﾏﾁ","townName":"旭北錦町","zipCode":"0100923"},{"prefectureJisCode":"05","cityJisCode":"05201","townNameKana":"ｺｳﾎｸｼﾝﾁｮｳ","townName":"港北新町","zipCode":"0110927"},{"prefectureJisCode":"05","cityJisCode":"05201","townNameKana":"ｺｳﾎｸﾏﾂﾉﾁｮｳ","townName":"港北松野町","zipCode":"0110926"},{"prefectureJisCode":"05","cityJisCode":"05201","townNameKana":"ｺｳﾖｳｱｵﾔｷﾞﾁｮｳ","townName":"高陽青柳町","zipCode":"0100966"},{"prefectureJisCode":"05","cityJisCode":"05201","townNameKana":"ｺｳﾖｳｻｲﾜｲﾁｮｳ","townName":"高陽幸町","zipCode":"0100967"},{"prefectureJisCode":"05","cityJisCode":"05201","townNameKana":"ｺﾞｼｮﾉｼﾓﾂﾂﾐ","townName":"御所野下堤","zipCode":"0101412"},{"prefectureJisCode":"05","cityJisCode":"05201","townNameKana":"ｺﾞｼｮﾉｼﾞｿﾞｳﾃﾞﾝ","townName":"御所野地蔵田","zipCode":"0101413"},{"prefectureJisCode":"05","cityJisCode":"05201","townNameKana":"ｺﾞｼｮﾉﾂﾂﾐﾀﾞｲ","townName":"御所野堤台","zipCode":"0101419"},{"prefectureJisCode":"05","cityJisCode":"05201","townNameKana":"ｺﾞｼｮﾉﾓﾄﾏﾁ","townName":"御所野元町","zipCode":"0101414"},{"prefectureJisCode":"05","cityJisCode":"05201","townNameKana":"ｺﾞｼｮﾉﾕﾓﾄ","townName":"御所野湯本","zipCode":"0101415"},{"prefectureJisCode":"05","cityJisCode":"05201","townNameKana":"ｻｸﾗ","townName":"桜","zipCode":"0100042"},{"prefectureJisCode":"05","cityJisCode":"05201","townNameKana":"ｻｸﾗｶﾞｵｶ","townName":"桜ガ丘","zipCode":"0100043"},{"prefectureJisCode":"05","cityJisCode":"05201","townNameKana":"ｻｸﾗﾀﾞｲ","townName":"桜台","zipCode":"0100059"},{"prefectureJisCode":"05","cityJisCode":"05201","townNameKana":"ｻﾝﾅｲ","townName":"山内","zipCode":"0100823"},{"prefectureJisCode":"05","cityJisCode":"05201","townNameKana":"ｻﾝﾉｳ","townName":"山王","zipCode":"0100951"},{"prefectureJisCode":"05","cityJisCode":"05201","townNameKana":"ｻﾝﾉｳｼﾝﾏﾁ","townName":"山王新町","zipCode":"0100952"},{"prefectureJisCode":"05","cityJisCode":"05201","townNameKana":"ｻﾝﾉｳﾅｶｼﾞﾏﾏﾁ","townName":"山王中島町","zipCode":"0100955"},{"prefectureJisCode":"05","cityJisCode":"05201","townNameKana":"ｻﾝﾉｳﾅｶｿﾞﾉﾏﾁ","townName":"山王中園町","zipCode":"0100953"},{"prefectureJisCode":"05","cityJisCode":"05201","townNameKana":"ｻﾝﾉｳﾇﾏﾀﾏﾁ","townName":"山王沼田町","zipCode":"0100954"},{"prefectureJisCode":"05","cityJisCode":"05201","townNameKana":"ｻﾝﾉｳﾘﾝｶｲﾏﾁ","townName":"山王臨海町","zipCode":"0100956"},{"prefectureJisCode":"05","cityJisCode":"05201","townNameKana":"ｼｮｳｸﾞﾝﾉｱｵﾔﾏﾁｮｳ","townName":"将軍野青山町","zipCode":"0110932"},{"prefectureJisCode":"05","cityJisCode":"05201","townNameKana":"ｼｮｳｸﾞﾝﾉｶﾂﾗﾁｮｳ","townName":"将軍野桂町","zipCode":"0110934"},{"prefectureJisCode":"05","cityJisCode":"05201","townNameKana":"ｼｮｳｸﾞﾝﾉｾｷｺｼ","townName":"将軍野堰越","zipCode":"0110933"},{"prefectureJisCode":"05","cityJisCode":"05201","townNameKana":"ｼｮｳｸﾞﾝﾉﾋｶﾞｼ","townName":"将軍野東","zipCode":"0110931"},{"prefectureJisCode":"05","cityJisCode":"05201","townNameKana":"ｼｮｳｸﾞﾝﾉﾐﾅﾐ","townName":"将軍野南","zipCode":"0110936"},{"prefectureJisCode":"05","cityJisCode":"05201","townNameKana":"ｼｮｳｸﾞﾝﾉﾑｶｲﾔﾏ","townName":"将軍野向山","zipCode":"0110935"},{"prefectureJisCode":"05","cityJisCode":"05201","townNameKana":"ｼﾓｷﾀﾃｸﾛｶﾜ","townName":"下北手黒川","zipCode":"0100056"},{"prefectureJisCode":"05","cityJisCode":"05201","townNameKana":"ｼﾓｷﾀﾃｻｸﾗ","townName":"下北手桜","zipCode":"0100058"},{"prefectureJisCode":"05","cityJisCode":"05201","townNameKana":"ｼﾓｷﾀﾃｻﾑｶﾜ","townName":"下北手寒川","zipCode":"0100053"},{"prefectureJisCode":"05","cityJisCode":"05201","townNameKana":"ｼﾓｷﾀﾃﾀｶﾗｶﾜ","townName":"下北手宝川","zipCode":"0100054"},{"prefectureJisCode":"05","cityJisCode":"05201","townNameKana":"ｼﾓｷﾀﾃﾄｵﾘｻﾜ","townName":"下北手通沢","zipCode":"0100055"},{"prefectureJisCode":"05","cityJisCode":"05201","townNameKana":"ｼﾓｷﾀﾃﾅｼﾋﾗ","townName":"下北手梨平","zipCode":"0100057"},{"prefectureJisCode":"05","cityJisCode":"05201","townNameKana":"ｼﾓｷﾀﾃﾏﾂｻｷ","townName":"下北手松崎","zipCode":"0100051"},{"prefectureJisCode":"05","cityJisCode":"05201","townNameKana":"ｼﾓｷﾀﾃﾔﾅｷﾞﾀﾃ","townName":"下北手柳館","zipCode":"0100052"},{"prefectureJisCode":"05","cityJisCode":"05201","townNameKana":"ｼﾓｼﾝｼﾞｮｳｱｵｻﾞｷ","townName":"下新城青崎","zipCode":"0100142"},{"prefectureJisCode":"05","cityJisCode":"05201","townNameKana":"ｼﾓｼﾝｼﾞｮｳｲﾜｷ","townName":"下新城岩城","zipCode":"0100144"},{"prefectureJisCode":"05","cityJisCode":"05201","townNameKana":"ｼﾓｼﾝｼﾞｮｳｵﾄﾓ","townName":"下新城小友","zipCode":"0100143"},{"prefectureJisCode":"05","cityJisCode":"05201","townNameKana":"ｼﾓｼﾝｼﾞｮｳｶｻｵｶ","townName":"下新城笠岡","zipCode":"0100145"},{"prefectureJisCode":"05","cityJisCode":"05201","townNameKana":"ｼﾓｼﾝｼﾞｮｳﾅｶﾉ","townName":"下新城中野","zipCode":"0100146"},{"prefectureJisCode":"05","cityJisCode":"05201","townNameKana":"ｼﾓｼﾝｼﾞｮｳﾅｶﾞｵｶ","townName":"下新城長岡","zipCode":"0100141"},{"prefectureJisCode":"05","cityJisCode":"05201","townNameKana":"ｼﾓﾊﾏｶﾂﾗﾈ","townName":"下浜桂根","zipCode":"0101501"},{"prefectureJisCode":"05","cityJisCode":"05201","townNameKana":"ｼﾓﾊﾏﾅｶﾞﾊﾏ","townName":"下浜長浜","zipCode":"0101502"},{"prefectureJisCode":"05","cityJisCode":"05201","townNameKana":"ｼﾓﾊﾏﾅﾗﾀﾞ","townName":"下浜楢田","zipCode":"0101506"},{"prefectureJisCode":"05","cityJisCode":"05201","townNameKana":"ｼﾓﾊﾏﾊｯﾀ","townName":"下浜八田","zipCode":"0101505"},{"prefectureJisCode":"05","cityJisCode":"05201","townNameKana":"ｼﾓﾊﾏﾊﾈｶﾜ","townName":"下浜羽川","zipCode":"0101503"},{"prefectureJisCode":"05","cityJisCode":"05201","townNameKana":"ｼﾓﾊﾏﾐｮｳｶﾞｻﾜ","townName":"下浜名ケ沢","zipCode":"0101504"},{"prefectureJisCode":"05","cityJisCode":"05201","townNameKana":"ｼﾝﾄｳﾀﾞ","townName":"新藤田","zipCode":"0100826"},{"prefectureJisCode":"05","cityJisCode":"05201","townNameKana":"ｾﾝｼｭｳｷﾀﾉﾏﾙ","townName":"千秋北の丸","zipCode":"0100872"},{"prefectureJisCode":"05","cityJisCode":"05201","townNameKana":"ｾﾝｼｭｳｸﾎﾞﾀﾏﾁ","townName":"千秋久保田町","zipCode":"0100874"},{"prefectureJisCode":"05","cityJisCode":"05201","townNameKana":"ｾﾝｼｭｳｺｳｴﾝ","townName":"千秋公園","zipCode":"0100876"},{"prefectureJisCode":"05","cityJisCode":"05201","townNameKana":"ｾﾝｼｭｳｼﾞｮｳｶﾏﾁ","townName":"千秋城下町","zipCode":"0100873"},{"prefectureJisCode":"05","cityJisCode":"05201","townNameKana":"ｾﾝｼｭｳﾅｶｼﾞﾏﾏﾁ","townName":"千秋中島町","zipCode":"0100871"},{"prefectureJisCode":"05","cityJisCode":"05201","townNameKana":"ｾﾝｼｭｳﾒｲﾄｸﾏﾁ","townName":"千秋明徳町","zipCode":"0100875"},{"prefectureJisCode":"05","cityJisCode":"05201","townNameKana":"ｾﾝｼｭｳﾔﾄﾞﾒﾏﾁ","townName":"千秋矢留町","zipCode":"0100877"},{"prefectureJisCode":"05","cityJisCode":"05201","townNameKana":"ｿｴｶﾞﾜ","townName":"添川","zipCode":"0100822"},{"prefectureJisCode":"05","cityJisCode":"05201","townNameKana":"ｿﾄｱｻﾋｶﾜ","townName":"外旭川","zipCode":"0100802"},{"prefectureJisCode":"05","cityJisCode":"05201","townNameKana":"ｿﾄｱｻﾋｶﾜﾊﾁﾏﾝﾃﾞﾝ","townName":"外旭川八幡田","zipCode":"0100804"},{"prefectureJisCode":"05","cityJisCode":"05201","townNameKana":"ｿﾄｱｻﾋｶﾜﾔﾂﾔﾅｷﾞ","townName":"外旭川八柳","zipCode":"0100803"},{"prefectureJisCode":"05","cityJisCode":"05201","townNameKana":"ﾀｲﾍｲｸﾛｻﾜ","townName":"太平黒沢","zipCode":"0101105"},{"prefectureJisCode":"05","cityJisCode":"05201","townNameKana":"ﾀｲﾍｲﾃﾗﾆﾜ","townName":"太平寺庭","zipCode":"0101104"},{"prefectureJisCode":"05","cityJisCode":"05201","townNameKana":"ﾀｲﾍｲﾅｶｾﾞｷ","townName":"太平中関","zipCode":"0101103"},{"prefectureJisCode":"05","cityJisCode":"05201","townNameKana":"ﾀｲﾍｲﾊｯﾀ","townName":"太平八田","zipCode":"0101101"},{"prefectureJisCode":"05","cityJisCode":"05201","townNameKana":"ﾀｲﾍｲﾒﾅｶﾞｻｷ","townName":"太平目長崎","zipCode":"0101102"},{"prefectureJisCode":"05","cityJisCode":"05201","townNameKana":"ﾀｲﾍｲﾔﾏﾔ","townName":"太平山谷","zipCode":"0101106"},{"prefectureJisCode":"05","cityJisCode":"05201","townNameKana":"ﾂﾁｻﾞｷﾐﾅﾄｷﾀ","townName":"土崎港北","zipCode":"0110941"},{"prefectureJisCode":"05","cityJisCode":"05201","townNameKana":"ﾂﾁｻﾞｷﾐﾅﾄｺｸﾎﾞﾁｮｳ","townName":"土崎港穀保町","zipCode":"0110944"},{"prefectureJisCode":"05","cityJisCode":"05201","townNameKana":"ﾂﾁｻﾞｷﾐﾅﾄｿｳｾﾞﾝﾏﾁ","townName":"土崎港相染町","zipCode":"0110951"},{"prefectureJisCode":"05","cityJisCode":"05201","townNameKana":"ﾂﾁｻﾞｷﾐﾅﾄﾁｭｳｵｳ","townName":"土崎港中央","zipCode":"0110946"},{"prefectureJisCode":"05","cityJisCode":"05201","townNameKana":"ﾂﾁｻﾞｷﾐﾅﾄﾆｼ","townName":"土崎港西","zipCode":"0110945"},{"prefectureJisCode":"05","cityJisCode":"05201","townNameKana":"ﾂﾁｻﾞｷﾐﾅﾄﾋｶﾞｼ","townName":"土崎港東","zipCode":"0110942"},{"prefectureJisCode":"05","cityJisCode":"05201","townNameKana":"ﾂﾁｻﾞｷﾐﾅﾄﾌﾙｶﾜﾏﾁ","townName":"土崎港古川町","zipCode":"0110951"},{"prefectureJisCode":"05","cityJisCode":"05201","townNameKana":"ﾂﾁｻﾞｷﾐﾅﾄﾐﾅﾐ","townName":"土崎港南","zipCode":"0110943"},{"prefectureJisCode":"05","cityJisCode":"05201","townNameKana":"ﾃｶﾞﾀ","townName":"手形","zipCode":"0100851"},{"prefectureJisCode":"05","cityJisCode":"05201","townNameKana":"ﾃｶﾞﾀｶﾗﾐﾃﾞﾝ","townName":"手形からみでん","zipCode":"0100861"},{"prefectureJisCode":"05","cityJisCode":"05201","townNameKana":"ﾃｶﾞﾀｶﾞｸｴﾝﾏﾁ","townName":"手形学園町","zipCode":"0100852"},{"prefectureJisCode":"05","cityJisCode":"05201","townNameKana":"ﾃｶﾞﾀｷｭｳｶﾏﾁ","townName":"手形休下町","zipCode":"0100863"},{"prefectureJisCode":"05","cityJisCode":"05201","townNameKana":"ﾃｶﾞﾀｼﾝｻｶｴﾏﾁ","townName":"手形新栄町","zipCode":"0100865"},{"prefectureJisCode":"05","cityJisCode":"05201","townNameKana":"ﾃｶﾞﾀｽﾐﾖｼﾁｮｳ","townName":"手形住吉町","zipCode":"0100864"},{"prefectureJisCode":"05","cityJisCode":"05201","townNameKana":"ﾃｶﾞﾀﾀﾅｶ","townName":"手形田中","zipCode":"0100862"},{"prefectureJisCode":"05","cityJisCode":"05201","townNameKana":"ﾃｶﾞﾀﾔﾏｷﾀﾏﾁ","townName":"手形山北町","zipCode":"0100842"},{"prefectureJisCode":"05","cityJisCode":"05201","townNameKana":"ﾃｶﾞﾀﾔﾏｻﾞｷﾁｮｳ","townName":"手形山崎町","zipCode":"0100854"},{"prefectureJisCode":"05","cityJisCode":"05201","townNameKana":"ﾃｶﾞﾀﾔﾏﾅｶﾏﾁ","townName":"手形山中町","zipCode":"0100844"},{"prefectureJisCode":"05","cityJisCode":"05201","townNameKana":"ﾃｶﾞﾀﾔﾏﾆｼﾏﾁ","townName":"手形山西町","zipCode":"0100841"},{"prefectureJisCode":"05","cityJisCode":"05201","townNameKana":"ﾃｶﾞﾀﾔﾏﾋｶﾞｼﾏﾁ","townName":"手形山東町","zipCode":"0100843"},{"prefectureJisCode":"05","cityJisCode":"05201","townNameKana":"ﾃｶﾞﾀﾔﾏﾐﾅﾐﾏﾁ","townName":"手形山南町","zipCode":"0100845"},{"prefectureJisCode":"05","cityJisCode":"05201","townNameKana":"ﾃﾗｳﾁ","townName":"寺内","zipCode":"0110901"},{"prefectureJisCode":"05","cityJisCode":"05201","townNameKana":"ﾃﾗｳﾁｱﾌﾞﾗﾃﾞﾝ","townName":"寺内油田","zipCode":"0110903"},{"prefectureJisCode":"05","cityJisCode":"05201","townNameKana":"ﾃﾗｳﾁｳｼﾛｼﾞｮｳ","townName":"寺内後城","zipCode":"0110906"},{"prefectureJisCode":"05","cityJisCode":"05201","townNameKana":"ﾃﾗｳﾁｳﾉｷ","townName":"寺内鵜ノ木","zipCode":"0110938"},{"prefectureJisCode":"05","cityJisCode":"05201","townNameKana":"ﾃﾗｳﾁｵｵｺｳｼﾞ","townName":"寺内大小路","zipCode":"0110908"},{"prefectureJisCode":"05","cityJisCode":"05201","townNameKana":"ﾃﾗｳﾁｵｵﾊﾀ","townName":"寺内大畑","zipCode":"0110939"},{"prefectureJisCode":"05","cityJisCode":"05201","townNameKana":"ﾃﾗｳﾁｶﾐﾔｼｷ","townName":"寺内神屋敷","zipCode":"0110905"},{"prefectureJisCode":"05","cityJisCode":"05201","townNameKana":"ﾃﾗｳﾁｺｳﾔ","townName":"寺内高野","zipCode":"0110937"},{"prefectureJisCode":"05","cityJisCode":"05201","townNameKana":"ﾃﾗｳﾁｺｻﾞｸﾗ","townName":"寺内児桜","zipCode":"0110909"},{"prefectureJisCode":"05","cityJisCode":"05201","townNameKana":"ﾃﾗｳﾁﾄﾞｳﾉｻﾜ","townName":"寺内堂ノ沢","zipCode":"0110902"},{"prefectureJisCode":"05","cityJisCode":"05201","townNameKana":"ﾃﾗｳﾁﾋﾙﾈ","townName":"寺内蛭根","zipCode":"0110904"},{"prefectureJisCode":"05","cityJisCode":"05201","townNameKana":"ﾃﾗｳﾁﾔｹﾔﾏ","townName":"寺内焼山","zipCode":"0110907"},{"prefectureJisCode":"05","cityJisCode":"05201","townNameKana":"ﾄﾖｲﾜｲｼﾀﾞｻﾞｶ","townName":"豊岩石田坂","zipCode":"0101651"},{"prefectureJisCode":"05","cityJisCode":"05201","townNameKana":"ﾄﾖｲﾜｵﾔﾏ","townName":"豊岩小山","zipCode":"0101653"},{"prefectureJisCode":"05","cityJisCode":"05201","townNameKana":"ﾄﾖｲﾜﾄﾖﾏｷ","townName":"豊岩豊巻","zipCode":"0101652"},{"prefectureJisCode":"05","cityJisCode":"05201","townNameKana":"ﾅｶﾄﾞｵﾘ","townName":"中通","zipCode":"0100001"},{"prefectureJisCode":"05","cityJisCode":"05201","townNameKana":"ﾅﾗﾔﾏ","townName":"楢山","zipCode":"0100034"},{"prefectureJisCode":"05","cityJisCode":"05201","townNameKana":"ﾅﾗﾔﾏｱﾀｺﾞｼﾀ","townName":"楢山愛宕下","zipCode":"0100037"},{"prefectureJisCode":"05","cityJisCode":"05201","townNameKana":"ﾅﾗﾔﾏｲｼﾂﾞｶﾁｮｳ","townName":"楢山石塚町","zipCode":"0100033"},{"prefectureJisCode":"05","cityJisCode":"05201","townNameKana":"ﾅﾗﾔﾏｵｵﾀﾏﾁ","townName":"楢山太田町","zipCode":"0100032"},{"prefectureJisCode":"05","cityJisCode":"05201","townNameKana":"ﾅﾗﾔﾏｵｵﾓﾄﾏﾁ","townName":"楢山大元町","zipCode":"0100031"},{"prefectureJisCode":"05","cityJisCode":"05201","townNameKana":"ﾅﾗﾔﾏｶﾜｸﾞﾁｻｶｲ","townName":"楢山川口境","zipCode":"0100029"},{"prefectureJisCode":"05","cityJisCode":"05201","townNameKana":"ﾅﾗﾔﾏｷｮｳﾜﾏﾁ","townName":"楢山共和町","zipCode":"0100028"},{"prefectureJisCode":"05","cityJisCode":"05201","townNameKana":"ﾅﾗﾔﾏｷﾝｼｮｳﾏﾁ","townName":"楢山金照町","zipCode":"0100036"},{"prefectureJisCode":"05","cityJisCode":"05201","townNameKana":"ﾅﾗﾔﾏｻﾀｹﾏﾁ","townName":"楢山佐竹町","zipCode":"0100025"},{"prefectureJisCode":"05","cityJisCode":"05201","townNameKana":"ﾅﾗﾔﾏｼﾞｮｳﾅﾝｼﾝﾏﾁ","townName":"楢山城南新町","zipCode":"0100038"},{"prefectureJisCode":"05","cityJisCode":"05201","townNameKana":"ﾅﾗﾔﾏｼﾞｮｳﾅﾝﾏﾁ","townName":"楢山城南町","zipCode":"0100035"},{"prefectureJisCode":"05","cityJisCode":"05201","townNameKana":"ﾅﾗﾔﾏﾉﾎﾞﾘﾏﾁ","townName":"楢山登町","zipCode":"0100021"},{"prefectureJisCode":"05","cityJisCode":"05201","townNameKana":"ﾅﾗﾔﾏﾌﾙｶﾜｼﾝﾏﾁ","townName":"楢山古川新町","zipCode":"0100026"},{"prefectureJisCode":"05","cityJisCode":"05201","townNameKana":"ﾅﾗﾔﾏﾎﾝﾁｮｳ","townName":"楢山本町","zipCode":"0100023"},{"prefectureJisCode":"05","cityJisCode":"05201","townNameKana":"ﾅﾗﾔﾏﾐﾅﾐｼﾝﾏﾁｶﾐﾁｮｳ","townName":"楢山南新町上丁","zipCode":"0100024"},{"prefectureJisCode":"05","cityJisCode":"05201","townNameKana":"ﾅﾗﾔﾏﾐﾅﾐｼﾝﾏﾁｼﾓﾁｮｳ","townName":"楢山南新町下丁","zipCode":"0100027"},{"prefectureJisCode":"05","cityJisCode":"05201","townNameKana":"ﾅﾗﾔﾏﾐﾅﾐﾅｶﾁｮｳ","townName":"楢山南中町","zipCode":"0100022"},{"prefectureJisCode":"05","cityJisCode":"05201","townNameKana":"ﾆｲﾀﾞ","townName":"仁井田","zipCode":"0101423"},{"prefectureJisCode":"05","cityJisCode":"05201","townNameKana":"ﾆｲﾀﾞｶﾀﾅｶﾁｮｳ","townName":"仁井田潟中町","zipCode":"0101435"},{"prefectureJisCode":"05","cityJisCode":"05201","townNameKana":"ﾆｲﾀﾞｺﾅｶｼﾞﾏ","townName":"仁井田小中島","zipCode":"0101426"},{"prefectureJisCode":"05","cityJisCode":"05201","townNameKana":"ﾆｲﾀﾞｻｶｴﾁｮｳ","townName":"仁井田栄町","zipCode":"0101433"},{"prefectureJisCode":"05","cityJisCode":"05201","townNameKana":"ﾆｲﾀﾞｼﾝﾃﾞﾝ","townName":"仁井田新田","zipCode":"0101427"},{"prefectureJisCode":"05","cityJisCode":"05201","townNameKana":"ﾆｲﾀﾞﾌｷﾐﾁｮｳ","townName":"仁井田蕗見町","zipCode":"0101434"},{"prefectureJisCode":"05","cityJisCode":"05201","townNameKana":"ﾆｲﾀﾞﾌｸｼﾏ","townName":"仁井田福島","zipCode":"0101432"},{"prefectureJisCode":"05","cityJisCode":"05201","townNameKana":"ﾆｲﾀﾞﾌﾀﾂﾔ","townName":"仁井田二ツ屋","zipCode":"0101431"},{"prefectureJisCode":"05","cityJisCode":"05201","townNameKana":"ﾆｲﾀﾞﾎﾝﾁｮｳ","townName":"仁井田本町","zipCode":"0101421"},{"prefectureJisCode":"05","cityJisCode":"05201","townNameKana":"ﾆｲﾀﾞﾐﾄﾞﾘﾁｮｳ","townName":"仁井田緑町","zipCode":"0101437"},{"prefectureJisCode":"05","cityJisCode":"05201","townNameKana":"ﾆｲﾀﾞﾒﾅｶﾞﾀ","townName":"仁井田目長田","zipCode":"0101422"},{"prefectureJisCode":"05","cityJisCode":"05201","townNameKana":"ﾆｺﾞﾘｶﾜ","townName":"濁川","zipCode":"0100821"},{"prefectureJisCode":"05","cityJisCode":"05201","townNameKana":"ﾆﾍﾞﾂ","townName":"仁別","zipCode":"0100824"},{"prefectureJisCode":"05","cityJisCode":"05201","townNameKana":"ﾊﾏﾀﾞ","townName":"浜田","zipCode":"0101654"},{"prefectureJisCode":"05","cityJisCode":"05201","townNameKana":"ﾊﾞﾗｼﾞﾏ","townName":"茨島","zipCode":"0100065"},{"prefectureJisCode":"05","cityJisCode":"05201","townNameKana":"ﾋｶﾞｼﾄﾞｵﾘ","townName":"東通","zipCode":"0100003"},{"prefectureJisCode":"05","cityJisCode":"05201","townNameKana":"ﾋｶﾞｼﾄﾞｵﾘｶﾝﾉﾝﾏｴ","townName":"東通観音前","zipCode":"0100004"},{"prefectureJisCode":"05","cityJisCode":"05201","townNameKana":"ﾋｶﾞｼﾄﾞｵﾘﾀﾃﾉｺｼ","townName":"東通館ノ越","zipCode":"0100006"},{"prefectureJisCode":"05","cityJisCode":"05201","townNameKana":"ﾋｶﾞｼﾄﾞｵﾘﾅｶﾏﾁ","townName":"東通仲町","zipCode":"0100002"},{"prefectureJisCode":"05","cityJisCode":"05201","townNameKana":"ﾋｶﾞｼﾄﾞｵﾘﾐｮｳﾃﾞﾝ","townName":"東通明田","zipCode":"0100005"},{"prefectureJisCode":"05","cityJisCode":"05201","townNameKana":"ﾋﾛｵﾓﾃ","townName":"広面","zipCode":"0100041"},{"prefectureJisCode":"05","cityJisCode":"05201","townNameKana":"ﾍﾋﾞﾉ","townName":"蛇野","zipCode":"0100853"},{"prefectureJisCode":"05","cityJisCode":"05201","townNameKana":"ﾎﾄﾞﾉ","townName":"保戸野","zipCode":"0100915"},{"prefectureJisCode":"05","cityJisCode":"05201","townNameKana":"ﾎﾄﾞﾉｶﾅｻﾏﾁ","townName":"保戸野金砂町","zipCode":"0100902"},{"prefectureJisCode":"05","cityJisCode":"05201","townNameKana":"ﾎﾄﾞﾉｻｸﾗﾏﾁ","townName":"保戸野桜町","zipCode":"0100901"},{"prefectureJisCode":"05","cityJisCode":"05201","townNameKana":"ﾎﾄﾞﾉｽﾜﾁｮｳ","townName":"保戸野すわ町","zipCode":"0100911"},{"prefectureJisCode":"05","cityJisCode":"05201","townNameKana":"ﾎﾄﾞﾉﾁﾖﾀﾞﾏﾁ","townName":"保戸野千代田町","zipCode":"0100914"},{"prefectureJisCode":"05","cityJisCode":"05201","townNameKana":"ﾎﾄﾞﾉﾃｯﾎﾟｳﾏﾁ","townName":"保戸野鉄砲町","zipCode":"0100913"},{"prefectureJisCode":"05","cityJisCode":"05201","townNameKana":"ﾎﾄﾞﾉﾄｵﾘﾏﾁ","townName":"保戸野通町","zipCode":"0100912"},{"prefectureJisCode":"05","cityJisCode":"05201","townNameKana":"ﾎﾄﾞﾉﾅｶﾁｮｳ","townName":"保戸野中町","zipCode":"0100905"},{"prefectureJisCode":"05","cityJisCode":"05201","townNameKana":"ﾎﾄﾞﾉﾊｯﾁｮｳ","townName":"保戸野八丁","zipCode":"0100903"},{"prefectureJisCode":"05","cityJisCode":"05201","townNameKana":"ﾎﾄﾞﾉﾊﾗﾉﾏﾁ","townName":"保戸野原の町","zipCode":"0100904"},{"prefectureJisCode":"05","cityJisCode":"05201","townNameKana":"ﾐﾅﾐｶﾞｵｶ","townName":"南ケ丘","zipCode":"0101409"},{"prefectureJisCode":"05","cityJisCode":"05201","townNameKana":"ﾐﾅﾐﾄﾞｵﾘｶﾒﾉﾁｮｳ","townName":"南通亀の町","zipCode":"0100011"},{"prefectureJisCode":"05","cityJisCode":"05201","townNameKana":"ﾐﾅﾐﾄﾞｵﾘﾂｷｼﾞ","townName":"南通築地","zipCode":"0100013"},{"prefectureJisCode":"05","cityJisCode":"05201","townNameKana":"ﾐﾅﾐﾄﾞｵﾘﾐｿﾉﾏﾁ","townName":"南通みその町","zipCode":"0100012"},{"prefectureJisCode":"05","cityJisCode":"05201","townNameKana":"ﾐﾅﾐﾄﾞｵﾘﾐﾔﾀ","townName":"南通宮田","zipCode":"0100014"},{"prefectureJisCode":"05","cityJisCode":"05201","townNameKana":"ﾑｶｲﾊﾏ","townName":"向浜","zipCode":"0101601"},{"prefectureJisCode":"05","cityJisCode":"05201","townNameKana":"ﾔﾅｷﾞﾀﾞ","townName":"柳田","zipCode":"0100825"},{"prefectureJisCode":"05","cityJisCode":"05201","townNameKana":"ﾔﾊﾞｾ","townName":"八橋","zipCode":"0100975"},{"prefectureJisCode":"05","cityJisCode":"05201","townNameKana":"ﾔﾊﾞｾｲｻﾉ","townName":"八橋イサノ","zipCode":"0100961"},{"prefectureJisCode":"05","cityJisCode":"05201","townNameKana":"ﾔﾊﾞｾｳﾝﾄﾞｳｺｳｴﾝ","townName":"八橋運動公園","zipCode":"0100974"},{"prefectureJisCode":"05","cityJisCode":"05201","townNameKana":"ﾔﾊﾞｾｵｵﾇﾏﾁｮｳ","townName":"八橋大沼町","zipCode":"0100963"},{"prefectureJisCode":"05","cityJisCode":"05201","townNameKana":"ﾔﾊﾞｾｵｵﾊﾀ","townName":"八橋大畑","zipCode":"0100962"},{"prefectureJisCode":"05","cityJisCode":"05201","townNameKana":"ﾔﾊﾞｾｼﾝｶﾜﾑｶｲ","townName":"八橋新川向","zipCode":"0100965"},{"prefectureJisCode":"05","cityJisCode":"05201","townNameKana":"ﾔﾊﾞｾﾀｺﾞﾛｳ","townName":"八橋田五郎","zipCode":"0100972"},{"prefectureJisCode":"05","cityJisCode":"05201","townNameKana":"ﾔﾊﾞｾﾀﾞｲﾄﾞｳﾋｶﾞｼ","townName":"八橋大道東","zipCode":"0100977"},{"prefectureJisCode":"05","cityJisCode":"05201","townNameKana":"ﾔﾊﾞｾﾄﾞｼﾞｮｳﾇﾏﾏﾁ","townName":"八橋鯲沼町","zipCode":"0100964"},{"prefectureJisCode":"05","cityJisCode":"05201","townNameKana":"ﾔﾊﾞｾﾎﾝﾁｮｳ","townName":"八橋本町","zipCode":"0100973"},{"prefectureJisCode":"05","cityJisCode":"05201","townNameKana":"ﾔﾊﾞｾﾐﾅﾐ","townName":"八橋南","zipCode":"0100976"},{"prefectureJisCode":"05","cityJisCode":"05201","townNameKana":"ﾔﾊﾞｾﾐﾜﾁｮｳ","townName":"八橋三和町","zipCode":"0100971"},{"prefectureJisCode":"05","cityJisCode":"05201","townNameKana":"ﾔﾏﾃﾀﾞｲ","townName":"山手台","zipCode":"0101429"},{"prefectureJisCode":"05","cityJisCode":"05201","townNameKana":"ﾕｳﾜｱｲｶﾜ","townName":"雄和相川","zipCode":"0101231"},{"prefectureJisCode":"05","cityJisCode":"05201","townNameKana":"ﾕｳﾜｱﾗﾜ","townName":"雄和新波","zipCode":"0101341"},{"prefectureJisCode":"05","cityJisCode":"05201","townNameKana":"ﾕｳﾜｲｶﾘﾀﾞ","townName":"雄和碇田","zipCode":"0101351"},{"prefectureJisCode":"05","cityJisCode":"05201","townNameKana":"ﾕｳﾜｲｼﾀﾞ","townName":"雄和石田","zipCode":"0101222"},{"prefectureJisCode":"05","cityJisCode":"05201","townNameKana":"ﾕｳﾜｶﾔｶﾞｻﾜ","townName":"雄和萱ケ沢","zipCode":"0101352"},{"prefectureJisCode":"05","cityJisCode":"05201","townNameKana":"ﾕｳﾜｻﾃﾞｺ","townName":"雄和左手子","zipCode":"0101225"},{"prefectureJisCode":"05","cityJisCode":"05201","townNameKana":"ﾕｳﾜｼﾊﾞﾉｼﾝﾃﾞﾝ","townName":"雄和芝野新田","zipCode":"0101202"},{"prefectureJisCode":"05","cityJisCode":"05201","townNameKana":"ﾕｳﾜｼﾓｸﾛｾ","townName":"雄和下黒瀬","zipCode":"0101203"},{"prefectureJisCode":"05","cityJisCode":"05201","townNameKana":"ﾕｳﾜｼﾞﾝｶﾞﾑﾗ","townName":"雄和神ケ村","zipCode":"0101342"},{"prefectureJisCode":"05","cityJisCode":"05201","townNameKana":"ﾕｳﾜﾀｸｻｶﾞﾜ","townName":"雄和田草川","zipCode":"0101201"},{"prefectureJisCode":"05","cityJisCode":"05201","townNameKana":"ﾕｳﾜﾀﾈｻﾞﾜ","townName":"雄和種沢","zipCode":"0101224"},{"prefectureJisCode":"05","cityJisCode":"05201","townNameKana":"ﾕｳﾜﾂﾅｷﾞ","townName":"雄和繋","zipCode":"0101343"},{"prefectureJisCode":"05","cityJisCode":"05201","townNameKana":"ﾕｳﾜﾂﾊﾞｷｶﾜ","townName":"雄和椿川","zipCode":"0101211"},{"prefectureJisCode":"05","cityJisCode":"05201","townNameKana":"ﾕｳﾜﾄｶﾞｻﾞﾜ","townName":"雄和戸賀沢","zipCode":"0101232"},{"prefectureJisCode":"05","cityJisCode":"05201","townNameKana":"ﾕｳﾜﾋﾗｵﾄﾘ","townName":"雄和平尾鳥","zipCode":"0101212"},{"prefectureJisCode":"05","cityJisCode":"05201","townNameKana":"ﾕｳﾜﾋﾗｻﾜ","townName":"雄和平沢","zipCode":"0101221"},{"prefectureJisCode":"05","cityJisCode":"05201","townNameKana":"ﾕｳﾜﾐｮｳﾎｳ","townName":"雄和妙法","zipCode":"0101223"},{"prefectureJisCode":"05","cityJisCode":"05201","townNameKana":"ﾕｳﾜﾑｶｲﾉ","townName":"雄和向野","zipCode":"0101344"},{"prefectureJisCode":"05","cityJisCode":"05201","townNameKana":"ﾕｳﾜﾒﾒｷ","townName":"雄和女米木","zipCode":"0101233"},{"prefectureJisCode":"05","cityJisCode":"05201","townNameKana":"ﾖｺﾓﾘ","townName":"横森","zipCode":"0100044"},{"prefectureJisCode":"05","cityJisCode":"05201","townNameKana":"ﾖﾂｺﾞﾔ","townName":"四ツ小屋","zipCode":"0101417"},{"prefectureJisCode":"05","cityJisCode":"05201","townNameKana":"ﾖﾂｺﾞﾔｺｱｼﾞ","townName":"四ツ小屋小阿地","zipCode":"0101418"},{"prefectureJisCode":"05","cityJisCode":"05201","townNameKana":"ﾖﾂｺﾞﾔｽｴﾄﾞﾏﾂﾓﾄ","townName":"四ツ小屋末戸松本","zipCode":"0101416"}]