[{"prefectureJisCode":"04","cityJisCode":"04212","zipCode":"9870443","prefectureNameKana":"ﾐﾔｷﾞｹﾝ","cityNameKana":"ﾄﾒｼ","townNameKana":"ﾐﾅﾐｶﾀﾏﾁｲﾀｶﾞｻﾜ","prefectureName":"宮城県","cityName":"登米市","townName":"南方町板ケ沢"},{"prefectureJisCode":"04","cityJisCode":"04212","zipCode":"9870443","prefectureNameKana":"ﾐﾔｷﾞｹﾝ","cityNameKana":"ﾄﾒｼ","townNameKana":"ﾐﾅﾐｶﾀﾏﾁｲﾁｱｼﾞ","prefectureName":"宮城県","cityName":"登米市","townName":"南方町一網"},{"prefectureJisCode":"04","cityJisCode":"04212","zipCode":"9870443","prefectureNameKana":"ﾐﾔｷﾞｹﾝ","cityNameKana":"ﾄﾒｼ","townNameKana":"ﾐﾅﾐｶﾀﾏﾁｵｵｻﾞｶﾏｴ","prefectureName":"宮城県","cityName":"登米市","townName":"南方町大坂前"},{"prefectureJisCode":"04","cityJisCode":"04212","zipCode":"9870443","prefectureNameKana":"ﾐﾔｷﾞｹﾝ","cityNameKana":"ﾄﾒｼ","townNameKana":"ﾐﾅﾐｶﾀﾏﾁｵｵﾆｼ","prefectureName":"宮城県","cityName":"登米市","townName":"南方町大西"},{"prefectureJisCode":"04","cityJisCode":"04212","zipCode":"9870443","prefectureNameKana":"ﾐﾔｷﾞｹﾝ","cityNameKana":"ﾄﾒｼ","townNameKana":"ﾐﾅﾐｶﾀﾏﾁｵﾓﾃﾏｴ","prefectureName":"宮城県","cityName":"登米市","townName":"南方町表前"},{"prefectureJisCode":"04","cityJisCode":"04212","zipCode":"9870443","prefectureNameKana":"ﾐﾔｷﾞｹﾝ","cityNameKana":"ﾄﾒｼ","townNameKana":"ﾐﾅﾐｶﾀﾏﾁｺｹﾉﾔﾁ","prefectureName":"宮城県","cityName":"登米市","townName":"南方町苔野谷地"},{"prefectureJisCode":"04","cityJisCode":"04212","zipCode":"9870443","prefectureNameKana":"ﾐﾔｷﾞｹﾝ","cityNameKana":"ﾄﾒｼ","townNameKana":"ﾐﾅﾐｶﾀﾏﾁｼﾝﾉﾔﾁ","prefectureName":"宮城県","cityName":"登米市","townName":"南方町新野谷地"},{"prefectureJisCode":"04","cityJisCode":"04212","zipCode":"9870443","prefectureNameKana":"ﾐﾔｷﾞｹﾝ","cityNameKana":"ﾄﾒｼ","townNameKana":"ﾐﾅﾐｶﾀﾏﾁｿﾄｳﾗ","prefectureName":"宮城県","cityName":"登米市","townName":"南方町外浦"},{"prefectureJisCode":"04","cityJisCode":"04212","zipCode":"9870443","prefectureNameKana":"ﾐﾔｷﾞｹﾝ","cityNameKana":"ﾄﾒｼ","townNameKana":"ﾐﾅﾐｶﾀﾏﾁﾅｶﾞﾈ","prefectureName":"宮城県","cityName":"登米市","townName":"南方町長根"},{"prefectureJisCode":"04","cityJisCode":"04212","zipCode":"9870443","prefectureNameKana":"ﾐﾔｷﾞｹﾝ","cityNameKana":"ﾄﾒｼ","townNameKana":"ﾐﾅﾐｶﾀﾏﾁﾅｶﾞﾈｼﾀ","prefectureName":"宮城県","cityName":"登米市","townName":"南方町長根下"},{"prefectureJisCode":"04","cityJisCode":"04212","zipCode":"9870443","prefectureNameKana":"ﾐﾔｷﾞｹﾝ","cityNameKana":"ﾄﾒｼ","townNameKana":"ﾐﾅﾐｶﾀﾏﾁﾉﾔﾁ","prefectureName":"宮城県","cityName":"登米市","townName":"南方町野谷地"}]